Workbook

Sheet 00_Tong_quan
A1: DIGIWIN | SEMICONDUCTOR PAID
A3: Đơn vị tiền: VNĐ. Theo dõi đề xuất ngân sách, triển khai và đánh giá. Mục tiêu: xây dựng nhận thức về chuyên môn vận hành ngành bán dẫn trong đúng nhóm doanh nghiệp và vai trò.
A5: KHUNG CƠ BẢN ĐỀ XUẤT / NGÀY | E5: KHUNG CẤP 2 / DUYỆT RIÊNG | I5: THỰC CHI QUẢNG CÁO
A6: ='01_Thiet_lap'!$D$7 | E6: ='01_Thiet_lap'!$D$12 | I6: =IF(COUNT('03_Chi_tieu'!$I$7:$I$96)=0,"Chưa ghi nhận",SUM('03_Chi_tieu'!$I$7:$I$96))
A9: NGÀY HỢP LỆ ĐÃ GHI NHẬN | E9: DỰ PHÒNG CÒN GIỮ | I9: DÒNG CHI CẦN RÀ SOÁT
A10: =SUM('03_Chi_tieu'!$S$7:$S$96) | E10: =IF(SUM('03_Chi_tieu'!$S$7:$S$96)=0,"Chưa ghi nhận",IF(COUNT('03_Chi_tieu'!$K$7:$K$96)<SUM('03_Chi_tieu'!$S$7:$S$96),"Chưa đầy đủ",SUM('03_Chi_tieu'!$K$7:$K$96))) | I10: =COUNTIF('03_Chi_tieu'!$P$7:$P$96,"?*")-COUNTIF('03_Chi_tieu'!$P$7:$P$96,"Đã ghi nhận")
A13: ="Phạm vi thuế/phí: "&'01_Thiet_lap'!$D$27&" | Bắt đầu: "&IF(ISNUMBER('01_Thiet_lap'!$D$25),TEXT('01_Thiet_lap'!$D$25,"dd/mm/yyyy"),'01_Thiet_lap'!$D$25)&" | Kết thúc: "&IF(ISNUMBER('01_Thiet_lap'!$D$26),TEXT('01_Thiet_lap'!$D$26,"dd/mm/yyyy"),'01_Thiet_lap'!$D$26)
A16: Mã | B16: Giai đoạn | E16: Phê duyệt | G16: Hợp lệ | H16: Mốc ngày | I16: Thực chi quảng cáo
A17: ='02_Lo_trinh'!A7 | B17: ='02_Lo_trinh'!B7 | E17: ='02_Lo_trinh'!J7 | G17: ='02_Lo_trinh'!K7 | H17: ='02_Lo_trinh'!C7 | I17: =IF(ISNUMBER('02_Lo_trinh'!L7),'02_Lo_trinh'!L7,"Chưa ghi nhận")
A18: ='02_Lo_trinh'!A8 | B18: ='02_Lo_trinh'!B8 | E18: ='02_Lo_trinh'!J8 | G18: ='02_Lo_trinh'!K8 | H18: ='02_Lo_trinh'!C8 | I18: =IF(ISNUMBER('02_Lo_trinh'!L8),'02_Lo_trinh'!L8,"Chưa ghi nhận")
A19: ='02_Lo_trinh'!A9 | B19: ='02_Lo_trinh'!B9 | E19: ='02_Lo_trinh'!J9 | G19: ='02_Lo_trinh'!K9 | H19: ='02_Lo_trinh'!C9 | I19: =IF(ISNUMBER('02_Lo_trinh'!L9),'02_Lo_trinh'!L9,"Chưa ghi nhận")
A20: ='02_Lo_trinh'!A10 | B20: ='02_Lo_trinh'!B10 | E20: ='02_Lo_trinh'!J10 | G20: ='02_Lo_trinh'!K10 | H20: ='02_Lo_trinh'!C10 | I20: =IF(ISNUMBER('02_Lo_trinh'!L10),'02_Lo_trinh'!L10,"Chưa ghi nhận")
A21: ='02_Lo_trinh'!A11 | B21: ='02_Lo_trinh'!B11 | E21: ='02_Lo_trinh'!J11 | G21: ='02_Lo_trinh'!K11 | H21: ='02_Lo_trinh'!C11 | I21: =IF(ISNUMBER('02_Lo_trinh'!L11),'02_Lo_trinh'!L11,"Chưa ghi nhận")
A23: ="Khung tham chiếu đến hết cấp 1 • "&SUM('02_Lo_trinh'!$C$7:$C$10)&" ngày hợp lệ (có điều kiện)" | I23: =SUM('02_Lo_trinh'!$G$7:$G$10)
A26: Phân bổ khởi động | E26: Dự kiến/ngày | G26: Tỷ trọng | I26: Thực chi đã ghi nhận
A27: LinkedIn | E27: ='01_Thiet_lap'!$D$8 | G27: =IF('01_Thiet_lap'!$D$7>0,E27/'01_Thiet_lap'!$D$7,"") | I27: =IF(COUNT('03_Chi_tieu'!$E$7:$E$96)=0,"Chưa ghi nhận",SUM('03_Chi_tieu'!$E$7:$E$96))
A28: Google Search | E28: ='01_Thiet_lap'!$D$9 | G28: =IF('01_Thiet_lap'!$D$7>0,E28/'01_Thiet_lap'!$D$7,"") | I28: =IF(COUNT('03_Chi_tieu'!$F$7:$F$96)=0,"Chưa ghi nhận",SUM('03_Chi_tieu'!$F$7:$F$96))
A29: Tiếp thị lại | E29: =0 | G29: =IF('01_Thiet_lap'!$D$7>0,E29/'01_Thiet_lap'!$D$7,"") | I29: =IF(COUNT('03_Chi_tieu'!$G$7:$G$96)=0,"Chưa ghi nhận",SUM('03_Chi_tieu'!$G$7:$G$96))
A30: Thử nghiệm khác | E30: =0 | G30: =IF('01_Thiet_lap'!$D$7>0,E30/'01_Thiet_lap'!$D$7,"") | I30: =IF(COUNT('03_Chi_tieu'!$H$7:$H$96)=0,"Chưa ghi nhận",SUM('03_Chi_tieu'!$H$7:$H$96))
A31: Dự phòng (đã nằm trong chi phí kênh) | E31: ='01_Thiet_lap'!$D$10 | G31: =IF('01_Thiet_lap'!$D$7>0,E31/'01_Thiet_lap'!$D$7,"") | I31: =IF(COUNT('03_Chi_tieu'!$J$7:$J$96)=0,"Chưa ghi nhận",SUM('03_Chi_tieu'!$J$7:$J$96))
A33: Dự phòng không phải khoản chi cộng thêm: phần đã dùng nằm trong thực chi của từng kênh. Dự phòng còn giữ chỉ tổng hợp theo ngày hợp lệ có dữ liệu đầy đủ, không mặc định được chuyển sang kỳ sau. Mọi số liệu thực tế hiện để trống, chờ cập nhật.
A37: CÁCH SỬ DỤNG BẢNG THEO DÕI
A38: 01_Thiet_lap | D38: Xác nhận phạm vi ngân sách, ngày chạy, mốc đánh giá và định nghĩa chỉ số. Các phương án cấp 1 được đặt ở cuối sheet.
A39: 02_Lo_trinh | D39: Cập nhật ngày và phê duyệt từng giai đoạn. Theo dõi ngày hợp lệ, thực chi và phần khung còn lại.
A40: 03_Chi_tieu | D40: Mỗi ngày một dòng. Nhập đủ bốn khoản chi; nhập dự phòng sử dụng và thuế/phí riêng. Nhập 0 nếu không phát sinh.
A41: 04_Danh_gia | D41: Điền số liệu và bằng chứng theo mã kỳ KY01–KY12. Kết quả chỉ là tham chiếu cho đánh giá.
A42: 05_Bao_cao_tuan | D42: Chốt khoảng ngày theo thực tế; cập nhật nhóm tiếp cận, mức quan tâm, nội dung rút ra và đề xuất tiếp theo.
A43: 06_Kiem_tra | D43: Xác nhận điều kiện triển khai, đầu mối phụ trách và hồ sơ. Ngày chưa thống nhất tiếp tục để placeholder.
A45: Ký hiệu: ô vàng là nơi nhập/cập nhật; ô xám là công thức hoặc nội dung tham chiếu. Thay [Chưa chốt] bằng ngày Excel thực (dd/mm/yyyy), không nhập ngày dưới dạng ghi chú. Nhật ký có sẵn 90 dòng, báo cáo và đánh giá có 12 kỳ.
A49: Lưu ý về lộ trình: bản nháp nêu mở rộng cấp 1 theo chu kỳ 7 ngày và yêu cầu hai chu kỳ trước khi xét cấp 2; mẫu tách G3.1/G3.2 để thống nhất hai nội dung. Mức 1.250.000 VNĐ/ngày, lịch chạy và tổng chi theo các giai đoạn đều chưa mặc định được duyệt. Nguồn số liệu đề xuất: nội dung được cung cấp trong cuộc trao đổi; không bổ sung chuẩn thị trường hoặc kết quả giả định.

Sheet 01_Thiet_lap
A1: THIẾT LẬP NGÂN SÁCH & MỐC THAM CHIẾU
A3: Nguồn: bản nháp đề xuất được cung cấp trong cuộc trao đổi. Các giá trị là đề xuất nội bộ, chưa mặc định được phê duyệt.
A6: Mã | B6: Thông số | D6: Giá trị / trạng thái | F6: Cơ sở và cách sử dụng
A7: NS01 | B7: Khung quảng cáo cơ bản/ngày | D7: 1000000 | F7: Bản nháp: 1.000.000 VNĐ/ngày chạy hợp lệ; là mốc quản trị bình quân.
A8: NS02 | B8: LinkedIn cơ sở/ngày | D8: 600000 | F8: Bản nháp: phân bổ khởi động cho LinkedIn.
A9: NS03 | B9: Google Search cơ sở/ngày | D9: 250000 | F9: Bản nháp: phân bổ khởi động cho Google Search.
A10: NS04 | B10: Dự phòng trong khung cơ bản/ngày | D10: 150000 | F10: Bản nháp: giữ lại khi chưa có thử nghiệm hoặc phương án đủ căn cứ.
A11: NS05 | B11: Tổng phân bổ cơ sở/ngày | D11: =SUM(D8:D9) | F11: Tự tính từ LinkedIn và Google Search; chưa bao gồm dự phòng.
A12: NS06 | B12: Khung cấp 2 đề xuất/ngày | D12: 1250000 | F12: Bản nháp: chỉ triển khai sau khi được phê duyệt riêng.
A13: TG01 | B13: Số ngày giai đoạn thử nghiệm | D13: 7 | F13: Bản nháp: 7 ngày chạy hợp lệ.
A14: TG02 | B14: Số ngày giai đoạn xác nhận | D14: 14 | F14: Bản nháp: 14 ngày chạy hợp lệ.
A15: TG03 | B15: Số ngày mỗi chu kỳ cấp 1 | D15: 7 | F15: Bản nháp: mỗi chu kỳ mở rộng cấp 1 kéo dài 7 ngày hợp lệ.
A16: TG04 | B16: Số chu kỳ cấp 1 trước khi xét cấp 2 | D16: 2 | F16: Bản nháp yêu cầu hai chu kỳ 7 ngày. Mẫu đã tách hai chu kỳ; điều chỉnh số chu kỳ cần cập nhật cấu trúc lộ trình.
A17: TG05 | B17: Số ngày đầu của cấp 2 | D17: 7 | F17: Bản nháp: 7 ngày đầu sau khi được phê duyệt.
A18: DG01 | B18: Tỷ lệ nhấp Search đúng chủ đề | D18: 0.7 | F18: Bản nháp: tối thiểu 7/10 lượt nhấp quan sát được; mốc tham chiếu ban đầu.
A19: DG02 | B19: Duy trì mức quan tâm tối thiểu | D19: 0.8 | F19: Bản nháp: tối thiểu 80% so với mốc ban đầu; dùng cùng một chỉ số.
A20: DG03 | B20: Mức cải thiện tham chiếu | D20: 0.2 | F20: Bản nháp: cải thiện tối thiểu 20%; chỉ số cần được thống nhất trước.
A21: DG04 | B21: Mức giảm chi phí tham chiếu | D21: 0.15 | F21: Bản nháp: chi phí thấp hơn tối thiểu 15%, kèm chất lượng tương đương.
A22: DG05 | B22: Mức suy giảm tối đa khi xét cấp 2 | D22: 0.1 | F22: Bản nháp: mức suy giảm không vượt quá 10%; cần hai chu kỳ cấp 1.
A23: DG06 | B23: Số nhấp để đối chiếu mốc 7/10 | D23: 10 | F23: Quy ước theo dõi từ mốc 7/10; không thay thế đánh giá độ tin cậy của mẫu.
A24: NS07 | B24: Dự phòng cấp 2/ngày | D24: [Chưa chốt] | F24: Chưa có phân bổ chi tiết trong bản nháp. Cập nhật khi trình duyệt cấp 2.
A25: TG06 | B25: Ngày bắt đầu chiến dịch | D25: [Chưa chốt] | F25: Thay placeholder bằng ngày thực tế sau khi được thống nhất.
A26: TG07 | B26: Ngày kết thúc chiến dịch | D26: [Chưa chốt] | F26: Không tự suy ra ngày kết thúc từ số ngày lịch.
A27: PD01 | B27: Phạm vi thuế và phí | D27: Chưa xác nhận | F27: Cần tách thuế/phí trước khi áp dụng nếu khung được duyệt đã bao gồm các khoản này.
A28: DL01 | B28: Chỉ số mức độ quan tâm | D28: [Chưa thống nhất] | F28: Ghi tên chỉ số và cách đo; giữ nhất quán giữa mốc ban đầu và kỳ hiện tại.
A29: DL02 | B29: Chỉ số đánh giá cải thiện | D29: [Chưa thống nhất] | F29: Chọn chỉ số mà giá trị tăng thể hiện cải thiện; ghi rõ đơn vị và nguồn.
A30: DL03 | B30: Đơn vị chi phí dùng để đối chiếu | D30: [Chưa thống nhất] | F30: Thống nhất cùng một đơn vị chi phí và điều kiện chất lượng.
A31: PD02 | B31: Phạm vi điều chỉnh được duyệt | D31: [Chưa thống nhất] | F31: Ghi thẩm quyền điều chỉnh giữa các kênh và sử dụng dự phòng.
A32: DL04 | B32: Nguồn dữ liệu và ngày hợp lệ | D32: [Chưa thống nhất] | F32: Ghi nguồn đối chiếu và điều kiện xác nhận ngày chạy, gồm trạng thái từng kênh.
A33: NS08 | B33: Dự phòng còn lại sau ưu tiên cấp 1 | D33: 50000 | F33: Bản nháp: các phương án cấp 1 dùng thêm 100.000 VNĐ, giữ lại 50.000 VNĐ.
A35: Ô vàng: nhập/cập nhật sau khi thống nhất. Ô xám: công thức. Đơn vị tiền: VNĐ. Các mốc tỷ lệ là tham chiếu vận hành, không tự động quyết định tăng ngân sách.
A38: Phương án phân bổ/ngày | C38: LinkedIn | D38: Google Search | E38: Tiếp thị lại | F38: Dự phòng còn giữ | G38: Tổng khung
A39: Khởi động | C39: =$D$8 | D39: =$D$9 | E39: =0 | F39: =$D$10 | G39: =SUM(C39:F39)
A40: Ưu tiên LinkedIn | C40: =$D$8+$D$10-$D$33 | D40: =$D$9 | E40: =0 | F40: =$D$33 | G40: =SUM(C40:F40)
A41: Ưu tiên Search | C41: =$D$8 | D41: =$D$9+$D$10-$D$33 | E41: =0 | F41: =$D$33 | G41: =SUM(C41:F41)
A42: Ưu tiên tiếp thị lại | C42: =$D$8 | D42: =$D$9 | E42: =$D$10-$D$33 | F42: =$D$33 | G42: =SUM(C42:F42)
A43: Cấp 2 — chờ phân bổ | C43: [Chưa chốt] | D43: [Chưa chốt] | E43: [Chưa chốt] | F43: [Chưa chốt] | G43: =$D$12
A45: Dự phòng sử dụng trong nhật ký chi là một phần của chi phí kênh, không cộng thêm lần nữa. Các phương án cấp 1 giữ tổng 1.000.000 VNĐ/ngày. Phương án cấp 2 cần chốt phân bổ và phê duyệt riêng.

Sheet 02_Lo_trinh
A1: LỘ TRÌNH TRIỂN KHAI & PHÊ DUYỆT
A3: Ngày bắt đầu/kết thúc để [Chưa chốt]. Hai chu kỳ cấp 1 được tách riêng; đủ số ngày chưa đồng nghĩa với đủ điều kiện mở rộng.
A6: Mã | B6: Giai đoạn | C6: Ngày tham chiếu | D6: Ngày bắt đầu | E6: Ngày kết thúc | F6: Khung đề xuất/ngày | G6: Khung tối đa/chu kỳ | H6: Trong đó: cơ sở | I6: Trong đó: dự phòng | J6: Phê duyệt | K6: Ngày hợp lệ đã ghi nhận | L6: Thực chi quảng cáo | M6: Phần khung chưa dùng | N6: Trọng tâm / bước tiếp theo
A7: G1 | B7: 1. Thử nghiệm | C7: ='01_Thiet_lap'!$D$13 | D7: [Chưa chốt] | E7: [Chưa chốt] | F7: ='01_Thiet_lap'!$D$7 | G7: =C7*F7 | H7: =C7*'01_Thiet_lap'!$D$11 | I7: =C7*'01_Thiet_lap'!$D$10 | J7: Chờ xem xét | K7: =SUMIF('03_Chi_tieu'!$B$7:$B$96,A7,'03_Chi_tieu'!$S$7:$S$96) | L7: =IF(COUNTIFS('03_Chi_tieu'!$B$7:$B$96,A7,'03_Chi_tieu'!$I$7:$I$96,">0")=0,"",SUMIF('03_Chi_tieu'!$B$7:$B$96,A7,'03_Chi_tieu'!$I$7:$I$96)) | M7: =IF(ISNUMBER(L7),G7-L7,"") | N7: Đối chiếu đúng tệp, nhu cầu tìm kiếm và hệ thống đo lường.
A8: G2 | B8: 2. Xác nhận | C8: ='01_Thiet_lap'!$D$14 | D8: [Chưa chốt] | E8: [Chưa chốt] | F8: ='01_Thiet_lap'!$D$7 | G8: =C8*F8 | H8: =C8*'01_Thiet_lap'!$D$11 | I8: =C8*'01_Thiet_lap'!$D$10 | J8: Chờ xem xét | K8: =SUMIF('03_Chi_tieu'!$B$7:$B$96,A8,'03_Chi_tieu'!$S$7:$S$96) | L8: =IF(COUNTIFS('03_Chi_tieu'!$B$7:$B$96,A8,'03_Chi_tieu'!$I$7:$I$96,">0")=0,"",SUMIF('03_Chi_tieu'!$B$7:$B$96,A8,'03_Chi_tieu'!$I$7:$I$96)) | M8: =IF(ISNUMBER(L8),G8-L8,"") | N8: Theo dõi thông điệp/nhóm có tín hiệu tốt và khả năng duy trì.
A9: G3.1 | B9: 3. Cấp 1 — chu kỳ 1 | C9: ='01_Thiet_lap'!$D$15 | D9: [Chưa chốt] | E9: [Chưa chốt] | F9: ='01_Thiet_lap'!$D$7 | G9: =C9*F9 | H9: =C9*'01_Thiet_lap'!$D$11 | I9: =C9*'01_Thiet_lap'!$D$10 | J9: Chờ xem xét | K9: =SUMIF('03_Chi_tieu'!$B$7:$B$96,A9,'03_Chi_tieu'!$S$7:$S$96) | L9: =IF(COUNTIFS('03_Chi_tieu'!$B$7:$B$96,A9,'03_Chi_tieu'!$I$7:$I$96,">0")=0,"",SUMIF('03_Chi_tieu'!$B$7:$B$96,A9,'03_Chi_tieu'!$I$7:$I$96)) | M9: =IF(ISNUMBER(L9),G9-L9,"") | N9: Điều chỉnh dự phòng trong tổng khung 1.000.000 VNĐ/ngày.
A10: G3.2 | B10: 3. Cấp 1 — chu kỳ 2 | C10: ='01_Thiet_lap'!$D$15 | D10: [Chưa chốt] | E10: [Chưa chốt] | F10: ='01_Thiet_lap'!$D$7 | G10: =C10*F10 | H10: =C10*'01_Thiet_lap'!$D$11 | I10: =C10*'01_Thiet_lap'!$D$10 | J10: Chờ xem xét | K10: =SUMIF('03_Chi_tieu'!$B$7:$B$96,A10,'03_Chi_tieu'!$S$7:$S$96) | L10: =IF(COUNTIFS('03_Chi_tieu'!$B$7:$B$96,A10,'03_Chi_tieu'!$I$7:$I$96,">0")=0,"",SUMIF('03_Chi_tieu'!$B$7:$B$96,A10,'03_Chi_tieu'!$I$7:$I$96)) | M10: =IF(ISNUMBER(L10),G10-L10,"") | N10: Xác nhận khả năng lặp lại trước khi xem xét trình cấp 2.
A11: G4 | B11: 4. Cấp 2 — 7 ngày đầu | C11: ='01_Thiet_lap'!$D$17 | D11: [Chưa chốt] | E11: [Chưa chốt] | F11: ='01_Thiet_lap'!$D$12 | G11: =C11*F11 | H11: =IF(ISNUMBER('01_Thiet_lap'!$D$24),C11*(F11-'01_Thiet_lap'!$D$24),"") | I11: =IF(ISNUMBER('01_Thiet_lap'!$D$24),C11*'01_Thiet_lap'!$D$24,"") | J11: Chờ xem xét | K11: =SUMIF('03_Chi_tieu'!$B$7:$B$96,A11,'03_Chi_tieu'!$S$7:$S$96) | L11: =IF(COUNTIFS('03_Chi_tieu'!$B$7:$B$96,A11,'03_Chi_tieu'!$I$7:$I$96,">0")=0,"",SUMIF('03_Chi_tieu'!$B$7:$B$96,A11,'03_Chi_tieu'!$I$7:$I$96)) | M11: =IF(ISNUMBER(L11),G11-L11,"") | N11: Phê duyệt riêng; phân bổ chi tiết chờ thống nhất.
A13: Khung tham chiếu đến hết hai chu kỳ cấp 1 | G13: =SUM(G7:G10) | J13: Có điều kiện; không mặc định là tổng ngân sách đã duyệt.
A15: Khung tham chiếu cấp 1 gồm 7 + 14 + 7 + 7 ngày hợp lệ. Chu kỳ bổ sung hoặc kéo dài cần được ghi nhận trong phạm vi thời gian và ngân sách được duyệt; không tự động cộng thêm ngân sách.
A17: Chi phí thực tế vẫn được tổng hợp kể cả ở ngày chưa đủ điều kiện. Một ngày chỉ được tính tiến độ khi có ngày thực, mã giai đoạn hợp lệ, xác nhận 'Hợp lệ', đủ bốn khoản chi (nhập 0 nếu không phát sinh), tổng chi > 0 và không trùng ngày.

Sheet 03_Chi_tieu
A1: NHẬT KÝ CHI TIÊU HẰNG NGÀY
A3: Mỗi ngày một dòng tổng hợp. Thay [Chưa chốt] bằng ngày thực; nhập 0 cho khoản không phát sinh. Dự phòng đã dùng là một phần của chi phí kênh, không cộng thêm vào tổng.
A6: Ngày chạy | B6: Giai đoạn | C6: Xác nhận ngày | D6: Khung đề xuất/ngày | E6: Thực chi LinkedIn | F6: Thực chi Search | G6: Thực chi tiếp thị lại | H6: Thử nghiệm khác | I6: Tổng chi quảng cáo | J6: Trong đó: dự phòng đã dùng | K6: Dự phòng còn giữ | L6: Chênh lệch so với khung/ngày | M6: Thuế/phí thực tế | N6: Tổng chi gồm thuế/phí | O6: Phê duyệt giai đoạn | P6: Nội dung cần rà soát | Q6: Lý do dùng dự phòng / ghi chú | R6: Hồ sơ / bằng chứng | S6: Ngày được tính (0/1)
A7: [Chưa chốt] | C7: Chưa xác nhận | D7: =IF(B7="","",IFERROR(VLOOKUP(B7,'02_Lo_trinh'!$A$7:$N$11,6,FALSE),"")) | I7: =IF(COUNT(E7:H7)=0,"",SUM(E7:H7)) | K7: =IF(OR(S7<>1,NOT(ISNUMBER(J7)),J7<0,J7>I7),"",IF(B7="G4",IF(ISNUMBER('01_Thiet_lap'!$D$24),MAX(0,'01_Thiet_lap'!$D$24-J7),""),MAX(0,'01_Thiet_lap'!$D$10-J7))) | L7: =IF(AND(ISNUMBER(I7),ISNUMBER(D7)),D7-I7,"") | N7: =IF(AND(ISNUMBER(I7),ISNUMBER(M7)),I7+M7,"") | O7: =IF(B7="","",IFERROR(VLOOKUP(B7,'02_Lo_trinh'!$A$7:$N$11,10,FALSE),"Cần chọn lại giai đoạn")) | P7: =IF(COUNT(E7:H7,M7)=0,"",IF(NOT(ISNUMBER(A7)),"Cần cập nhật ngày",IF(COUNTIF('02_Lo_trinh'!$A$7:$A$11,B7)<>1,"Cần chọn giai đoạn",IF(COUNTIF($A$7:$A$96,A7)>1,"Cần rà soát ngày trùng",IF(COUNT(E7:H7)<4,"Cần nhập đủ 4 khoản chi",IF(MIN(E7:H7)<0,"Cần rà soát khoản chi âm",IF(O7<>"Đã phê duyệt","Cần đối chiếu phê duyệt",IF(NOT(ISNUMBER(J7)),"Cần ghi phần dự phòng",IF(OR(J7<0,J7>I7),"Cần rà soát số tiền dự phòng",IF(AND(B7="G4",NOT(ISNUMBER('01_Thiet_lap'!$D$24))),"Cần chốt dự phòng cấp 2",IF(AND(B7<>"G4",J7>'01_Thiet_lap'!$D$10),"Cần rà soát mức dự phòng",IF(AND(B7="G4",ISNUMBER('01_Thiet_lap'!$D$24),J7>'01_Thiet_lap'!$D$24),"Cần rà soát dự phòng cấp 2",IF(AND(J7>0,Q7=""),"Cần bổ sung lý do dùng dự phòng",IF(C7<>"Hợp lệ","Chi phát sinh ngoài ngày hợp lệ",IF(NOT(ISNUMBER(M7)),"Chờ xác nhận thuế/phí",IF(I7>D7,"Cần rà soát mức chi trong ngày","Đã ghi nhận")))))))))))))))) | S7: =IF(AND(ISNUMBER(A7),COUNTIF('02_Lo_trinh'!$A$7:$A$11,B7)=1,C7="Hợp lệ",COUNT(E7:H7)=4,I7>0,COUNTIF($A$7:$A$96,A7)=1),1,0)
A8: [Chưa chốt] | C8: Chưa xác nhận | D8: =IF(B8="","",IFERROR(VLOOKUP(B8,'02_Lo_trinh'!$A$7:$N$11,6,FALSE),"")) | I8: =IF(COUNT(E8:H8)=0,"",SUM(E8:H8)) | K8: =IF(OR(S8<>1,NOT(ISNUMBER(J8)),J8<0,J8>I8),"",IF(B8="G4",IF(ISNUMBER('01_Thiet_lap'!$D$24),MAX(0,'01_Thiet_lap'!$D$24-J8),""),MAX(0,'01_Thiet_lap'!$D$10-J8))) | L8: =IF(AND(ISNUMBER(I8),ISNUMBER(D8)),D8-I8,"") | N8: =IF(AND(ISNUMBER(I8),ISNUMBER(M8)),I8+M8,"") | O8: =IF(B8="","",IFERROR(VLOOKUP(B8,'02_Lo_trinh'!$A$7:$N$11,10,FALSE),"Cần chọn lại giai đoạn")) | P8: =IF(COUNT(E8:H8,M8)=0,"",IF(NOT(ISNUMBER(A8)),"Cần cập nhật ngày",IF(COUNTIF('02_Lo_trinh'!$A$7:$A$11,B8)<>1,"Cần chọn giai đoạn",IF(COUNTIF($A$7:$A$96,A8)>1,"Cần rà soát ngày trùng",IF(COUNT(E8:H8)<4,"Cần nhập đủ 4 khoản chi",IF(MIN(E8:H8)<0,"Cần rà soát khoản chi âm",IF(O8<>"Đã phê duyệt","Cần đối chiếu phê duyệt",IF(NOT(ISNUMBER(J8)),"Cần ghi phần dự phòng",IF(OR(J8<0,J8>I8),"Cần rà soát số tiền dự phòng",IF(AND(B8="G4",NOT(ISNUMBER('01_Thiet_lap'!$D$24))),"Cần chốt dự phòng cấp 2",IF(AND(B8<>"G4",J8>'01_Thiet_lap'!$D$10),"Cần rà soát mức dự phòng",IF(AND(B8="G4",ISNUMBER('01_Thiet_lap'!$D$24),J8>'01_Thiet_lap'!$D$24),"Cần rà soát dự phòng cấp 2",IF(AND(J8>0,Q8=""),"Cần bổ sung lý do dùng dự phòng",IF(C8<>"Hợp lệ","Chi phát sinh ngoài ngày hợp lệ",IF(NOT(ISNUMBER(M8)),"Chờ xác nhận thuế/phí",IF(I8>D8,"Cần rà soát mức chi trong ngày","Đã ghi nhận")))))))))))))))) | S8: =IF(AND(ISNUMBER(A8),COUNTIF('02_Lo_trinh'!$A$7:$A$11,B8)=1,C8="Hợp lệ",COUNT(E8:H8)=4,I8>0,COUNTIF($A$7:$A$96,A8)=1),1,0)
A9: [Chưa chốt] | C9: Chưa xác nhận | D9: =IF(B9="","",IFERROR(VLOOKUP(B9,'02_Lo_trinh'!$A$7:$N$11,6,FALSE),"")) | I9: =IF(COUNT(E9:H9)=0,"",SUM(E9:H9)) | K9: =IF(OR(S9<>1,NOT(ISNUMBER(J9)),J9<0,J9>I9),"",IF(B9="G4",IF(ISNUMBER('01_Thiet_lap'!$D$24),MAX(0,'01_Thiet_lap'!$D$24-J9),""),MAX(0,'01_Thiet_lap'!$D$10-J9))) | L9: =IF(AND(ISNUMBER(I9),ISNUMBER(D9)),D9-I9,"") | N9: =IF(AND(ISNUMBER(I9),ISNUMBER(M9)),I9+M9,"") | O9: =IF(B9="","",IFERROR(VLOOKUP(B9,'02_Lo_trinh'!$A$7:$N$11,10,FALSE),"Cần chọn lại giai đoạn")) | P9: =IF(COUNT(E9:H9,M9)=0,"",IF(NOT(ISNUMBER(A9)),"Cần cập nhật ngày",IF(COUNTIF('02_Lo_trinh'!$A$7:$A$11,B9)<>1,"Cần chọn giai đoạn",IF(COUNTIF($A$7:$A$96,A9)>1,"Cần rà soát ngày trùng",IF(COUNT(E9:H9)<4,"Cần nhập đủ 4 khoản chi",IF(MIN(E9:H9)<0,"Cần rà soát khoản chi âm",IF(O9<>"Đã phê duyệt","Cần đối chiếu phê duyệt",IF(NOT(ISNUMBER(J9)),"Cần ghi phần dự phòng",IF(OR(J9<0,J9>I9),"Cần rà soát số tiền dự phòng",IF(AND(B9="G4",NOT(ISNUMBER('01_Thiet_lap'!$D$24))),"Cần chốt dự phòng cấp 2",IF(AND(B9<>"G4",J9>'01_Thiet_lap'!$D$10),"Cần rà soát mức dự phòng",IF(AND(B9="G4",ISNUMBER('01_Thiet_lap'!$D$24),J9>'01_Thiet_lap'!$D$24),"Cần rà soát dự phòng cấp 2",IF(AND(J9>0,Q9=""),"Cần bổ sung lý do dùng dự phòng",IF(C9<>"Hợp lệ","Chi phát sinh ngoài ngày hợp lệ",IF(NOT(ISNUMBER(M9)),"Chờ xác nhận thuế/phí",IF(I9>D9,"Cần rà soát mức chi trong ngày","Đã ghi nhận")))))))))))))))) | S9: =IF(AND(ISNUMBER(A9),COUNTIF('02_Lo_trinh'!$A$7:$A$11,B9)=1,C9="Hợp lệ",COUNT(E9:H9)=4,I9>0,COUNTIF($A$7:$A$96,A9)=1),1,0)
A10: [Chưa chốt] | C10: Chưa xác nhận | D10: =IF(B10="","",IFERROR(VLOOKUP(B10,'02_Lo_trinh'!$A$7:$N$11,6,FALSE),"")) | I10: =IF(COUNT(E10:H10)=0,"",SUM(E10:H10)) | K10: =IF(OR(S10<>1,NOT(ISNUMBER(J10)),J10<0,J10>I10),"",IF(B10="G4",IF(ISNUMBER('01_Thiet_lap'!$D$24),MAX(0,'01_Thiet_lap'!$D$24-J10),""),MAX(0,'01_Thiet_lap'!$D$10-J10))) | L10: =IF(AND(ISNUMBER(I10),ISNUMBER(D10)),D10-I10,"") | N10: =IF(AND(ISNUMBER(I10),ISNUMBER(M10)),I10+M10,"") | O10: =IF(B10="","",IFERROR(VLOOKUP(B10,'02_Lo_trinh'!$A$7:$N$11,10,FALSE),"Cần chọn lại giai đoạn")) | P10: =IF(COUNT(E10:H10,M10)=0,"",IF(NOT(ISNUMBER(A10)),"Cần cập nhật ngày",IF(COUNTIF('02_Lo_trinh'!$A$7:$A$11,B10)<>1,"Cần chọn giai đoạn",IF(COUNTIF($A$7:$A$96,A10)>1,"Cần rà soát ngày trùng",IF(COUNT(E10:H10)<4,"Cần nhập đủ 4 khoản chi",IF(MIN(E10:H10)<0,"Cần rà soát khoản chi âm",IF(O10<>"Đã phê duyệt","Cần đối chiếu phê duyệt",IF(NOT(ISNUMBER(J10)),"Cần ghi phần dự phòng",IF(OR(J10<0,J10>I10),"Cần rà soát số tiền dự phòng",IF(AND(B10="G4",NOT(ISNUMBER('01_Thiet_lap'!$D$24))),"Cần chốt dự phòng cấp 2",IF(AND(B10<>"G4",J10>'01_Thiet_lap'!$D$10),"Cần rà soát mức dự phòng",IF(AND(B10="G4",ISNUMBER('01_Thiet_lap'!$D$24),J10>'01_Thiet_lap'!$D$24),"Cần rà soát dự phòng cấp 2",IF(AND(J10>0,Q10=""),"Cần bổ sung lý do dùng dự phòng",IF(C10<>"Hợp lệ","Chi phát sinh ngoài ngày hợp lệ",IF(NOT(ISNUMBER(M10)),"Chờ xác nhận thuế/phí",IF(I10>D10,"Cần rà soát mức chi trong ngày","Đã ghi nhận")))))))))))))))) | S10: =IF(AND(ISNUMBER(A10),COUNTIF('02_Lo_trinh'!$A$7:$A$11,B10)=1,C10="Hợp lệ",COUNT(E10:H10)=4,I10>0,COUNTIF($A$7:$A$96,A10)=1),1,0)
A11: [Chưa chốt] | C11: Chưa xác nhận | D11: =IF(B11="","",IFERROR(VLOOKUP(B11,'02_Lo_trinh'!$A$7:$N$11,6,FALSE),"")) | I11: =IF(COUNT(E11:H11)=0,"",SUM(E11:H11)) | K11: =IF(OR(S11<>1,NOT(ISNUMBER(J11)),J11<0,J11>I11),"",IF(B11="G4",IF(ISNUMBER('01_Thiet_lap'!$D$24),MAX(0,'01_Thiet_lap'!$D$24-J11),""),MAX(0,'01_Thiet_lap'!$D$10-J11))) | L11: =IF(AND(ISNUMBER(I11),ISNUMBER(D11)),D11-I11,"") | N11: =IF(AND(ISNUMBER(I11),ISNUMBER(M11)),I11+M11,"") | O11: =IF(B11="","",IFERROR(VLOOKUP(B11,'02_Lo_trinh'!$A$7:$N$11,10,FALSE),"Cần chọn lại giai đoạn")) | P11: =IF(COUNT(E11:H11,M11)=0,"",IF(NOT(ISNUMBER(A11)),"Cần cập nhật ngày",IF(COUNTIF('02_Lo_trinh'!$A$7:$A$11,B11)<>1,"Cần chọn giai đoạn",IF(COUNTIF($A$7:$A$96,A11)>1,"Cần rà soát ngày trùng",IF(COUNT(E11:H11)<4,"Cần nhập đủ 4 khoản chi",IF(MIN(E11:H11)<0,"Cần rà soát khoản chi âm",IF(O11<>"Đã phê duyệt","Cần đối chiếu phê duyệt",IF(NOT(ISNUMBER(J11)),"Cần ghi phần dự phòng",IF(OR(J11<0,J11>I11),"Cần rà soát số tiền dự phòng",IF(AND(B11="G4",NOT(ISNUMBER('01_Thiet_lap'!$D$24))),"Cần chốt dự phòng cấp 2",IF(AND(B11<>"G4",J11>'01_Thiet_lap'!$D$10),"Cần rà soát mức dự phòng",IF(AND(B11="G4",ISNUMBER('01_Thiet_lap'!$D$24),J11>'01_Thiet_lap'!$D$24),"Cần rà soát dự phòng cấp 2",IF(AND(J11>0,Q11=""),"Cần bổ sung lý do dùng dự phòng",IF(C11<>"Hợp lệ","Chi phát sinh ngoài ngày hợp lệ",IF(NOT(ISNUMBER(M11)),"Chờ xác nhận thuế/phí",IF(I11>D11,"Cần rà soát mức chi trong ngày","Đã ghi nhận")))))))))))))))) | S11: =IF(AND(ISNUMBER(A11),COUNTIF('02_Lo_trinh'!$A$7:$A$11,B11)=1,C11="Hợp lệ",COUNT(E11:H11)=4,I11>0,COUNTIF($A$7:$A$96,A11)=1),1,0)
A12: [Chưa chốt] | C12: Chưa xác nhận | D12: =IF(B12="","",IFERROR(VLOOKUP(B12,'02_Lo_trinh'!$A$7:$N$11,6,FALSE),"")) | I12: =IF(COUNT(E12:H12)=0,"",SUM(E12:H12)) | K12: =IF(OR(S12<>1,NOT(ISNUMBER(J12)),J12<0,J12>I12),"",IF(B12="G4",IF(ISNUMBER('01_Thiet_lap'!$D$24),MAX(0,'01_Thiet_lap'!$D$24-J12),""),MAX(0,'01_Thiet_lap'!$D$10-J12))) | L12: =IF(AND(ISNUMBER(I12),ISNUMBER(D12)),D12-I12,"") | N12: =IF(AND(ISNUMBER(I12),ISNUMBER(M12)),I12+M12,"") | O12: =IF(B12="","",IFERROR(VLOOKUP(B12,'02_Lo_trinh'!$A$7:$N$11,10,FALSE),"Cần chọn lại giai đoạn")) | P12: =IF(COUNT(E12:H12,M12)=0,"",IF(NOT(ISNUMBER(A12)),"Cần cập nhật ngày",IF(COUNTIF('02_Lo_trinh'!$A$7:$A$11,B12)<>1,"Cần chọn giai đoạn",IF(COUNTIF($A$7:$A$96,A12)>1,"Cần rà soát ngày trùng",IF(COUNT(E12:H12)<4,"Cần nhập đủ 4 khoản chi",IF(MIN(E12:H12)<0,"Cần rà soát khoản chi âm",IF(O12<>"Đã phê duyệt","Cần đối chiếu phê duyệt",IF(NOT(ISNUMBER(J12)),"Cần ghi phần dự phòng",IF(OR(J12<0,J12>I12),"Cần rà soát số tiền dự phòng",IF(AND(B12="G4",NOT(ISNUMBER('01_Thiet_lap'!$D$24))),"Cần chốt dự phòng cấp 2",IF(AND(B12<>"G4",J12>'01_Thiet_lap'!$D$10),"Cần rà soát mức dự phòng",IF(AND(B12="G4",ISNUMBER('01_Thiet_lap'!$D$24),J12>'01_Thiet_lap'!$D$24),"Cần rà soát dự phòng cấp 2",IF(AND(J12>0,Q12=""),"Cần bổ sung lý do dùng dự phòng",IF(C12<>"Hợp lệ","Chi phát sinh ngoài ngày hợp lệ",IF(NOT(ISNUMBER(M12)),"Chờ xác nhận thuế/phí",IF(I12>D12,"Cần rà soát mức chi trong ngày","Đã ghi nhận")))))))))))))))) | S12: =IF(AND(ISNUMBER(A12),COUNTIF('02_Lo_trinh'!$A$7:$A$11,B12)=1,C12="Hợp lệ",COUNT(E12:H12)=4,I12>0,COUNTIF($A$7:$A$96,A12)=1),1,0)
A13: [Chưa chốt] | C13: Chưa xác nhận | D13: =IF(B13="","",IFERROR(VLOOKUP(B13,'02_Lo_trinh'!$A$7:$N$11,6,FALSE),"")) | I13: =IF(COUNT(E13:H13)=0,"",SUM(E13:H13)) | K13: =IF(OR(S13<>1,NOT(ISNUMBER(J13)),J13<0,J13>I13),"",IF(B13="G4",IF(ISNUMBER('01_Thiet_lap'!$D$24),MAX(0,'01_Thiet_lap'!$D$24-J13),""),MAX(0,'01_Thiet_lap'!$D$10-J13))) | L13: =IF(AND(ISNUMBER(I13),ISNUMBER(D13)),D13-I13,"") | N13: =IF(AND(ISNUMBER(I13),ISNUMBER(M13)),I13+M13,"") | O13: =IF(B13="","",IFERROR(VLOOKUP(B13,'02_Lo_trinh'!$A$7:$N$11,10,FALSE),"Cần chọn lại giai đoạn")) | P13: =IF(COUNT(E13:H13,M13)=0,"",IF(NOT(ISNUMBER(A13)),"Cần cập nhật ngày",IF(COUNTIF('02_Lo_trinh'!$A$7:$A$11,B13)<>1,"Cần chọn giai đoạn",IF(COUNTIF($A$7:$A$96,A13)>1,"Cần rà soát ngày trùng",IF(COUNT(E13:H13)<4,"Cần nhập đủ 4 khoản chi",IF(MIN(E13:H13)<0,"Cần rà soát khoản chi âm",IF(O13<>"Đã phê duyệt","Cần đối chiếu phê duyệt",IF(NOT(ISNUMBER(J13)),"Cần ghi phần dự phòng",IF(OR(J13<0,J13>I13),"Cần rà soát số tiền dự phòng",IF(AND(B13="G4",NOT(ISNUMBER('01_Thiet_lap'!$D$24))),"Cần chốt dự phòng cấp 2",IF(AND(B13<>"G4",J13>'01_Thiet_lap'!$D$10),"Cần rà soát mức dự phòng",IF(AND(B13="G4",ISNUMBER('01_Thiet_lap'!$D$24),J13>'01_Thiet_lap'!$D$24),"Cần rà soát dự phòng cấp 2",IF(AND(J13>0,Q13=""),"Cần bổ sung lý do dùng dự phòng",IF(C13<>"Hợp lệ","Chi phát sinh ngoài ngày hợp lệ",IF(NOT(ISNUMBER(M13)),"Chờ xác nhận thuế/phí",IF(I13>D13,"Cần rà soát mức chi trong ngày","Đã ghi nhận")))))))))))))))) | S13: =IF(AND(ISNUMBER(A13),COUNTIF('02_Lo_trinh'!$A$7:$A$11,B13)=1,C13="Hợp lệ",COUNT(E13:H13)=4,I13>0,COUNTIF($A$7:$A$96,A13)=1),1,0)
A14: [Chưa chốt] | C14: Chưa xác nhận | D14: =IF(B14="","",IFERROR(VLOOKUP(B14,'02_Lo_trinh'!$A$7:$N$11,6,FALSE),"")) | I14: =IF(COUNT(E14:H14)=0,"",SUM(E14:H14)) | K14: =IF(OR(S14<>1,NOT(ISNUMBER(J14)),J14<0,J14>I14),"",IF(B14="G4",IF(ISNUMBER('01_Thiet_lap'!$D$24),MAX(0,'01_Thiet_lap'!$D$24-J14),""),MAX(0,'01_Thiet_lap'!$D$10-J14))) | L14: =IF(AND(ISNUMBER(I14),ISNUMBER(D14)),D14-I14,"") | N14: =IF(AND(ISNUMBER(I14),ISNUMBER(M14)),I14+M14,"") | O14: =IF(B14="","",IFERROR(VLOOKUP(B14,'02_Lo_trinh'!$A$7:$N$11,10,FALSE),"Cần chọn lại giai đoạn")) | P14: =IF(COUNT(E14:H14,M14)=0,"",IF(NOT(ISNUMBER(A14)),"Cần cập nhật ngày",IF(COUNTIF('02_Lo_trinh'!$A$7:$A$11,B14)<>1,"Cần chọn giai đoạn",IF(COUNTIF($A$7:$A$96,A14)>1,"Cần rà soát ngày trùng",IF(COUNT(E14:H14)<4,"Cần nhập đủ 4 khoản chi",IF(MIN(E14:H14)<0,"Cần rà soát khoản chi âm",IF(O14<>"Đã phê duyệt","Cần đối chiếu phê duyệt",IF(NOT(ISNUMBER(J14)),"Cần ghi phần dự phòng",IF(OR(J14<0,J14>I14),"Cần rà soát số tiền dự phòng",IF(AND(B14="G4",NOT(ISNUMBER('01_Thiet_lap'!$D$24))),"Cần chốt dự phòng cấp 2",IF(AND(B14<>"G4",J14>'01_Thiet_lap'!$D$10),"Cần rà soát mức dự phòng",IF(AND(B14="G4",ISNUMBER('01_Thiet_lap'!$D$24),J14>'01_Thiet_lap'!$D$24),"Cần rà soát dự phòng cấp 2",IF(AND(J14>0,Q14=""),"Cần bổ sung lý do dùng dự phòng",IF(C14<>"Hợp lệ","Chi phát sinh ngoài ngày hợp lệ",IF(NOT(ISNUMBER(M14)),"Chờ xác nhận thuế/phí",IF(I14>D14,"Cần rà soát mức chi trong ngày","Đã ghi nhận")))))))))))))))) | S14: =IF(AND(ISNUMBER(A14),COUNTIF('02_Lo_trinh'!$A$7:$A$11,B14)=1,C14="Hợp lệ",COUNT(E14:H14)=4,I14>0,COUNTIF($A$7:$A$96,A14)=1),1,0)
A15: [Chưa chốt] | C15: Chưa xác nhận | D15: =IF(B15="","",IFERROR(VLOOKUP(B15,'02_Lo_trinh'!$A$7:$N$11,6,FALSE),"")) | I15: =IF(COUNT(E15:H15)=0,"",SUM(E15:H15)) | K15: =IF(OR(S15<>1,NOT(ISNUMBER(J15)),J15<0,J15>I15),"",IF(B15="G4",IF(ISNUMBER('01_Thiet_lap'!$D$24),MAX(0,'01_Thiet_lap'!$D$24-J15),""),MAX(0,'01_Thiet_lap'!$D$10-J15))) | L15: =IF(AND(ISNUMBER(I15),ISNUMBER(D15)),D15-I15,"") | N15: =IF(AND(ISNUMBER(I15),ISNUMBER(M15)),I15+M15,"") | O15: =IF(B15="","",IFERROR(VLOOKUP(B15,'02_Lo_trinh'!$A$7:$N$11,10,FALSE),"Cần chọn lại giai đoạn")) | P15: =IF(COUNT(E15:H15,M15)=0,"",IF(NOT(ISNUMBER(A15)),"Cần cập nhật ngày",IF(COUNTIF('02_Lo_trinh'!$A$7:$A$11,B15)<>1,"Cần chọn giai đoạn",IF(COUNTIF($A$7:$A$96,A15)>1,"Cần rà soát ngày trùng",IF(COUNT(E15:H15)<4,"Cần nhập đủ 4 khoản chi",IF(MIN(E15:H15)<0,"Cần rà soát khoản chi âm",IF(O15<>"Đã phê duyệt","Cần đối chiếu phê duyệt",IF(NOT(ISNUMBER(J15)),"Cần ghi phần dự phòng",IF(OR(J15<0,J15>I15),"Cần rà soát số tiền dự phòng",IF(AND(B15="G4",NOT(ISNUMBER('01_Thiet_lap'!$D$24))),"Cần chốt dự phòng cấp 2",IF(AND(B15<>"G4",J15>'01_Thiet_lap'!$D$10),"Cần rà soát mức dự phòng",IF(AND(B15="G4",ISNUMBER('01_Thiet_lap'!$D$24),J15>'01_Thiet_lap'!$D$24),"Cần rà soát dự phòng cấp 2",IF(AND(J15>0,Q15=""),"Cần bổ sung lý do dùng dự phòng",IF(C15<>"Hợp lệ","Chi phát sinh ngoài ngày hợp lệ",IF(NOT(ISNUMBER(M15)),"Chờ xác nhận thuế/phí",IF(I15>D15,"Cần rà soát mức chi trong ngày","Đã ghi nhận")))))))))))))))) | S15: =IF(AND(ISNUMBER(A15),COUNTIF('02_Lo_trinh'!$A$7:$A$11,B15)=1,C15="Hợp lệ",COUNT(E15:H15)=4,I15>0,COUNTIF($A$7:$A$96,A15)=1),1,0)
A16: [Chưa chốt] | C16: Chưa xác nhận | D16: =IF(B16="","",IFERROR(VLOOKUP(B16,'02_Lo_trinh'!$A$7:$N$11,6,FALSE),"")) | I16: =IF(COUNT(E16:H16)=0,"",SUM(E16:H16)) | K16: =IF(OR(S16<>1,NOT(ISNUMBER(J16)),J16<0,J16>I16),"",IF(B16="G4",IF(ISNUMBER('01_Thiet_lap'!$D$24),MAX(0,'01_Thiet_lap'!$D$24-J16),""),MAX(0,'01_Thiet_lap'!$D$10-J16))) | L16: =IF(AND(ISNUMBER(I16),ISNUMBER(D16)),D16-I16,"") | N16: =IF(AND(ISNUMBER(I16),ISNUMBER(M16)),I16+M16,"") | O16: =IF(B16="","",IFERROR(VLOOKUP(B16,'02_Lo_trinh'!$A$7:$N$11,10,FALSE),"Cần chọn lại giai đoạn")) | P16: =IF(COUNT(E16:H16,M16)=0,"",IF(NOT(ISNUMBER(A16)),"Cần cập nhật ngày",IF(COUNTIF('02_Lo_trinh'!$A$7:$A$11,B16)<>1,"Cần chọn giai đoạn",IF(COUNTIF($A$7:$A$96,A16)>1,"Cần rà soát ngày trùng",IF(COUNT(E16:H16)<4,"Cần nhập đủ 4 khoản chi",IF(MIN(E16:H16)<0,"Cần rà soát khoản chi âm",IF(O16<>"Đã phê duyệt","Cần đối chiếu phê duyệt",IF(NOT(ISNUMBER(J16)),"Cần ghi phần dự phòng",IF(OR(J16<0,J16>I16),"Cần rà soát số tiền dự phòng",IF(AND(B16="G4",NOT(ISNUMBER('01_Thiet_lap'!$D$24))),"Cần chốt dự phòng cấp 2",IF(AND(B16<>"G4",J16>'01_Thiet_lap'!$D$10),"Cần rà soát mức dự phòng",IF(AND(B16="G4",ISNUMBER('01_Thiet_lap'!$D$24),J16>'01_Thiet_lap'!$D$24),"Cần rà soát dự phòng cấp 2",IF(AND(J16>0,Q16=""),"Cần bổ sung lý do dùng dự phòng",IF(C16<>"Hợp lệ","Chi phát sinh ngoài ngày hợp lệ",IF(NOT(ISNUMBER(M16)),"Chờ xác nhận thuế/phí",IF(I16>D16,"Cần rà soát mức chi trong ngày","Đã ghi nhận")))))))))))))))) | S16: =IF(AND(ISNUMBER(A16),COUNTIF('02_Lo_trinh'!$A$7:$A$11,B16)=1,C16="Hợp lệ",COUNT(E16:H16)=4,I16>0,COUNTIF($A$7:$A$96,A16)=1),1,0)
A17: [Chưa chốt] | C17: Chưa xác nhận | D17: =IF(B17="","",IFERROR(VLOOKUP(B17,'02_Lo_trinh'!$A$7:$N$11,6,FALSE),"")) | I17: =IF(COUNT(E17:H17)=0,"",SUM(E17:H17)) | K17: =IF(OR(S17<>1,NOT(ISNUMBER(J17)),J17<0,J17>I17),"",IF(B17="G4",IF(ISNUMBER('01_Thiet_lap'!$D$24),MAX(0,'01_Thiet_lap'!$D$24-J17),""),MAX(0,'01_Thiet_lap'!$D$10-J17))) | L17: =IF(AND(ISNUMBER(I17),ISNUMBER(D17)),D17-I17,"") | N17: =IF(AND(ISNUMBER(I17),ISNUMBER(M17)),I17+M17,"") | O17: =IF(B17="","",IFERROR(VLOOKUP(B17,'02_Lo_trinh'!$A$7:$N$11,10,FALSE),"Cần chọn lại giai đoạn")) | P17: =IF(COUNT(E17:H17,M17)=0,"",IF(NOT(ISNUMBER(A17)),"Cần cập nhật ngày",IF(COUNTIF('02_Lo_trinh'!$A$7:$A$11,B17)<>1,"Cần chọn giai đoạn",IF(COUNTIF($A$7:$A$96,A17)>1,"Cần rà soát ngày trùng",IF(COUNT(E17:H17)<4,"Cần nhập đủ 4 khoản chi",IF(MIN(E17:H17)<0,"Cần rà soát khoản chi âm",IF(O17<>"Đã phê duyệt","Cần đối chiếu phê duyệt",IF(NOT(ISNUMBER(J17)),"Cần ghi phần dự phòng",IF(OR(J17<0,J17>I17),"Cần rà soát số tiền dự phòng",IF(AND(B17="G4",NOT(ISNUMBER('01_Thiet_lap'!$D$24))),"Cần chốt dự phòng cấp 2",IF(AND(B17<>"G4",J17>'01_Thiet_lap'!$D$10),"Cần rà soát mức dự phòng",IF(AND(B17="G4",ISNUMBER('01_Thiet_lap'!$D$24),J17>'01_Thiet_lap'!$D$24),"Cần rà soát dự phòng cấp 2",IF(AND(J17>0,Q17=""),"Cần bổ sung lý do dùng dự phòng",IF(C17<>"Hợp lệ","Chi phát sinh ngoài ngày hợp lệ",IF(NOT(ISNUMBER(M17)),"Chờ xác nhận thuế/phí",IF(I17>D17,"Cần rà soát mức chi trong ngày","Đã ghi nhận")))))))))))))))) | S17: =IF(AND(ISNUMBER(A17),COUNTIF('02_Lo_trinh'!$A$7:$A$11,B17)=1,C17="Hợp lệ",COUNT(E17:H17)=4,I17>0,COUNTIF($A$7:$A$96,A17)=1),1,0)
A18: [Chưa chốt] | C18: Chưa xác nhận | D18: =IF(B18="","",IFERROR(VLOOKUP(B18,'02_Lo_trinh'!$A$7:$N$11,6,FALSE),"")) | I18: =IF(COUNT(E18:H18)=0,"",SUM(E18:H18)) | K18: =IF(OR(S18<>1,NOT(ISNUMBER(J18)),J18<0,J18>I18),"",IF(B18="G4",IF(ISNUMBER('01_Thiet_lap'!$D$24),MAX(0,'01_Thiet_lap'!$D$24-J18),""),MAX(0,'01_Thiet_lap'!$D$10-J18))) | L18: =IF(AND(ISNUMBER(I18),ISNUMBER(D18)),D18-I18,"") | N18: =IF(AND(ISNUMBER(I18),ISNUMBER(M18)),I18+M18,"") | O18: =IF(B18="","",IFERROR(VLOOKUP(B18,'02_Lo_trinh'!$A$7:$N$11,10,FALSE),"Cần chọn lại giai đoạn")) | P18: =IF(COUNT(E18:H18,M18)=0,"",IF(NOT(ISNUMBER(A18)),"Cần cập nhật ngày",IF(COUNTIF('02_Lo_trinh'!$A$7:$A$11,B18)<>1,"Cần chọn giai đoạn",IF(COUNTIF($A$7:$A$96,A18)>1,"Cần rà soát ngày trùng",IF(COUNT(E18:H18)<4,"Cần nhập đủ 4 khoản chi",IF(MIN(E18:H18)<0,"Cần rà soát khoản chi âm",IF(O18<>"Đã phê duyệt","Cần đối chiếu phê duyệt",IF(NOT(ISNUMBER(J18)),"Cần ghi phần dự phòng",IF(OR(J18<0,J18>I18),"Cần rà soát số tiền dự phòng",IF(AND(B18="G4",NOT(ISNUMBER('01_Thiet_lap'!$D$24))),"Cần chốt dự phòng cấp 2",IF(AND(B18<>"G4",J18>'01_Thiet_lap'!$D$10),"Cần rà soát mức dự phòng",IF(AND(B18="G4",ISNUMBER('01_Thiet_lap'!$D$24),J18>'01_Thiet_lap'!$D$24),"Cần rà soát dự phòng cấp 2",IF(AND(J18>0,Q18=""),"Cần bổ sung lý do dùng dự phòng",IF(C18<>"Hợp lệ","Chi phát sinh ngoài ngày hợp lệ",IF(NOT(ISNUMBER(M18)),"Chờ xác nhận thuế/phí",IF(I18>D18,"Cần rà soát mức chi trong ngày","Đã ghi nhận")))))))))))))))) | S18: =IF(AND(ISNUMBER(A18),COUNTIF('02_Lo_trinh'!$A$7:$A$11,B18)=1,C18="Hợp lệ",COUNT(E18:H18)=4,I18>0,COUNTIF($A$7:$A$96,A18)=1),1,0)
... A96: [Chưa chốt] | C96: Chưa xác nhận | D96: =IF(B96="","",IFERROR(VLOOKUP(B96,'02_Lo_trinh'!$A$7:$N$11,6,FALSE),"")) | I96: =IF(COUNT(E96:H96)=0,"",SUM(E96:H96)) | K96: =IF(OR(S96<>1,NOT(ISNUMBER(J96)),J96<0,J96>I96),"",IF(B96="G4",IF(ISNUMBER('01_Thiet_lap'!$D$24),MAX(0,'01_Thiet_lap'!$D$24-J96),""),MAX(0,'01_Thiet_lap'!$D$10-J96))) | L96: =IF(AND(ISNUMBER(I96),ISNUMBER(D96)),D96-I96,"") | N96: =IF(AND(ISNUMBER(I96),ISNUMBER(M96)),I96+M96,"") | O96: =IF(B96="","",IFERROR(VLOOKUP(B96,'02_Lo_trinh'!$A$7:$N$11,10,FALSE),"Cần chọn lại giai đoạn")) | P96: =IF(COUNT(E96:H96,M96)=0,"",IF(NOT(ISNUMBER(A96)),"Cần cập nhật ngày",IF(COUNTIF('02_Lo_trinh'!$A$7:$A$11,B96)<>1,"Cần chọn giai đoạn",IF(COUNTIF($A$7:$A$96,A96)>1,"Cần rà soát ngày trùng",IF(COUNT(E96:H96)<4,"Cần nhập đủ 4 khoản chi",IF(MIN(E96:H96)<0,"Cần rà soát khoản chi âm",IF(O96<>"Đã phê duyệt","Cần đối chiếu phê duyệt",IF(NOT(ISNUMBER(J96)),"Cần ghi phần dự phòng",IF(OR(J96<0,J96>I96),"Cần rà soát số tiền dự phòng",IF(AND(B96="G4",NOT(ISNUMBER('01_Thiet_lap'!$D$24))),"Cần chốt dự phòng cấp 2",IF(AND(B96<>"G4",J96>'01_Thiet_lap'!$D$10),"Cần rà soát mức dự phòng",IF(AND(B96="G4",ISNUMBER('01_Thiet_lap'!$D$24),J96>'01_Thiet_lap'!$D$24),"Cần rà soát dự phòng cấp 2",IF(AND(J96>0,Q96=""),"Cần bổ sung lý do dùng dự phòng",IF(C96<>"Hợp lệ","Chi phát sinh ngoài ngày hợp lệ",IF(NOT(ISNUMBER(M96)),"Chờ xác nhận thuế/phí",IF(I96>D96,"Cần rà soát mức chi trong ngày","Đã ghi nhận")))))))))))))))) | S96: =IF(AND(ISNUMBER(A96),COUNTIF('02_Lo_trinh'!$A$7:$A$11,B96)=1,C96="Hợp lệ",COUNT(E96:H96)=4,I96>0,COUNTIF($A$7:$A$96,A96)=1),1,0)
A98: Khung/ngày là mốc quản trị bình quân. Chênh lệch theo ngày cần được xem cùng chi tiêu lũy kế và phạm vi phê duyệt. Tổng gồm thuế/phí chỉ hiện sau khi khoản thuế/phí đã được nhập, kể cả bằng 0.
A100: Dự phòng còn giữ chỉ tính trên ngày hợp lệ có thông tin dự phòng đầy đủ; không mặc định được chuyển sang ngày sau. Dòng có chi nhưng thiếu ngày/mã vẫn nằm trong tổng chi toàn chiến dịch và được gắn nội dung cần rà soát.

Sheet 04_Danh_gia
A1: ĐÁNH GIÁ THEO CHU KỲ & HỒ SƠ ĐỐI CHIẾU
A3: Mỗi kỳ có các tiêu chí tham chiếu; chỉ cập nhật tiêu chí phù hợp với quyết định đang xem xét. Ô trống không được hiểu là đạt. Nhận định sơ bộ không thay thế phê duyệt.
A5: Cấp 1: cải thiện ≥20% HOẶC giảm chi phí ≥15% với chất lượng tương đương. Cấp 2: xem xét cả hai chu kỳ cấp 1, mức suy giảm và dư địa đúng tệp.
A6: Kỳ | B6: Tiêu chí | C6: Ngày đánh giá | D6: Mốc đối chiếu / tổng quan sát | E6: Kỳ hiện tại / đúng chủ đề | F6: Kết quả tính | G6: Mốc tham chiếu | H6: Nhận định sơ bộ | I6: Bằng chứng / nguồn đối chiếu | J6: Ghi chú / định nghĩa chỉ số
A7: KY01 | B7: Đúng nhóm doanh nghiệp và vai trò | C7: [Chưa chốt] | F7: =IF(E7="","",E7) | G7: Đã xác nhận | H7: =IF(E7="","Chưa nhập dữ liệu",IF(NOT(ISNUMBER(C7)),"Cần cập nhật ngày",IF(I7="","Chờ hồ sơ đối chiếu",IF(E7="Đã xác nhận","Đạt mốc tham chiếu","Cần xem xét thêm")))) | J7: Đối chiếu dữ liệu tiếp cận với nhóm doanh nghiệp và vai trò đã thống nhất.
A8: KY01 | B8: Lượt nhấp Search liên quan đúng chủ đề | C8: [Chưa chốt] | F8: =IF(AND(ISNUMBER(D8),ISNUMBER(E8),D8>0,E8>=0),E8/D8,"") | G8: ='01_Thiet_lap'!$D$18 | H8: =IF(COUNT(D8:E8)=0,"Chưa nhập dữ liệu",IF(NOT(ISNUMBER(F8)),"Cần rà soát số liệu",IF(NOT(ISNUMBER(C8)),"Cần cập nhật ngày",IF(E8>D8,"Cần rà soát số liệu",IF(D8<'01_Thiet_lap'!$D$23,"Cần thêm dữ liệu quan sát",IF(I8="","Chờ hồ sơ đối chiếu",IF(F8>=G8,"Đạt mốc tham chiếu","Cần xem xét thêm"))))))) | J8: Cột D: tổng nhấp được kiểm tra. Cột E: nhấp đúng chủ đề. Mốc 7/10 là tham chiếu vận hành, không khẳng định độ tin cậy thống kê.
A9: KY01 | B9: Duy trì mức quan tâm so với ban đầu | C9: [Chưa chốt] | F9: =IF(AND(ISNUMBER(D9),ISNUMBER(E9),D9>0,E9>=0),E9/D9,"") | G9: ='01_Thiet_lap'!$D$19 | H9: =IF(COUNT(D9:E9)=0,"Chưa nhập dữ liệu",IF(NOT(ISNUMBER(F9)),"Cần rà soát số liệu",IF(NOT(ISNUMBER(C9)),"Cần cập nhật ngày",IF(OR('01_Thiet_lap'!$D$28="",'01_Thiet_lap'!$D$28="[Chưa thống nhất]"),"Chờ thống nhất chỉ số",IF(I9="","Chờ hồ sơ đối chiếu",IF(F9>=G9,"Đạt mốc tham chiếu","Cần xem xét thêm")))))) | J9: D/E dùng cùng chỉ số quan tâm tại Thiết lập. Kết quả = hiện tại / ban đầu.
A10: KY01 | B10: Cải thiện của phương án được ưu tiên | C10: [Chưa chốt] | F10: =IF(AND(ISNUMBER(D10),ISNUMBER(E10),D10>0,E10>=0),E10/D10-1,"") | G10: ='01_Thiet_lap'!$D$20 | H10: =IF(COUNT(D10:E10)=0,"Chưa nhập dữ liệu",IF(NOT(ISNUMBER(F10)),"Cần rà soát số liệu",IF(NOT(ISNUMBER(C10)),"Cần cập nhật ngày",IF(OR('01_Thiet_lap'!$D$29="",'01_Thiet_lap'!$D$29="[Chưa thống nhất]"),"Chờ thống nhất chỉ số",IF(I10="","Chờ hồ sơ đối chiếu",IF(F10>=G10,"Đạt mốc tham chiếu","Cần xem xét thêm")))))) | J10: D: phương án đối chiếu; E: phương án được ưu tiên. Dùng chỉ số tăng là tốt hơn. Tiêu chí này là một lựa chọn thay thế cho giảm chi phí.
A11: KY01 | B11: Giảm chi phí với chất lượng tương đương | C11: [Chưa chốt] | F11: =IF(AND(ISNUMBER(D11),ISNUMBER(E11),D11>0,E11>=0),1-E11/D11,"") | G11: ='01_Thiet_lap'!$D$21 | H11: =IF(COUNT(D11:E11)=0,"Chưa nhập dữ liệu",IF(NOT(ISNUMBER(F11)),"Cần rà soát số liệu",IF(NOT(ISNUMBER(C11)),"Cần cập nhật ngày",IF(OR('01_Thiet_lap'!$D$30="",'01_Thiet_lap'!$D$30="[Chưa thống nhất]"),"Chờ thống nhất chỉ số",IF(I11="","Chờ hồ sơ đối chiếu",IF(F11>=G11,"Đạt mốc tham chiếu","Cần xem xét thêm")))))) | J11: D/E cùng đơn vị chi phí. Mức giảm = 1 − hiện tại/đối chiếu. Cần kèm bằng chứng chất lượng tương đương.
A12: KY01 | B12: Chất lượng ổn định khi tăng phân bổ | C12: [Chưa chốt] | F12: =IF(E12="","",E12) | G12: Đã xác nhận | H12: =IF(E12="","Chưa nhập dữ liệu",IF(NOT(ISNUMBER(C12)),"Cần cập nhật ngày",IF(I12="","Chờ hồ sơ đối chiếu",IF(E12="Đã xác nhận","Đạt mốc tham chiếu","Cần xem xét thêm")))) | J12: Ghi bằng chứng chất lượng được duy trì; không chỉ dựa trên số lượng tương tác.
A13: KY01 | B13: Mức suy giảm sau mở rộng cấp 1 | C13: [Chưa chốt] | F13: =IF(AND(ISNUMBER(D13),ISNUMBER(E13),D13>0,E13>=0),MAX(0,1-E13/D13),"") | G13: ='01_Thiet_lap'!$D$22 | H13: =IF(COUNT(D13:E13)=0,"Chưa nhập dữ liệu",IF(NOT(ISNUMBER(F13)),"Cần rà soát số liệu",IF(NOT(ISNUMBER(C13)),"Cần cập nhật ngày",IF(OR('01_Thiet_lap'!$D$28="",'01_Thiet_lap'!$D$28="[Chưa thống nhất]"),"Chờ thống nhất chỉ số",IF(I13="","Chờ hồ sơ đối chiếu",IF(F13<=G13,"Đạt mốc tham chiếu","Cần xem xét thêm")))))) | J13: Dùng khi xét cấp 2. D: mốc đối chiếu đã thống nhất; E: kỳ hiện tại. Mức giảm = MAX(0; 1 − hiện tại/đối chiếu).
A14: KY01 | B14: Dư địa tiếp cận thêm đúng nhóm mục tiêu | C14: [Chưa chốt] | F14: =IF(E14="","",E14) | G14: Đã xác nhận | H14: =IF(E14="","Chưa nhập dữ liệu",IF(NOT(ISNUMBER(C14)),"Cần cập nhật ngày",IF(I14="","Chờ hồ sơ đối chiếu",IF(E14="Đã xác nhận","Đạt mốc tham chiếu","Cần xem xét thêm")))) | J14: Dùng khi xem xét mở rộng, đặc biệt cấp 2; đối chiếu phạm vi tệp và chất lượng tiếp cận.
A15: KY01 | B15: Độ tin cậy của đo lường và trang đích | C15: [Chưa chốt] | F15: =IF(E15="","",E15) | G15: Đã xác nhận | H15: =IF(E15="","Chưa nhập dữ liệu",IF(NOT(ISNUMBER(C15)),"Cần cập nhật ngày",IF(I15="","Chờ hồ sơ đối chiếu",IF(E15="Đã xác nhận","Đạt mốc tham chiếu","Cần xem xét thêm")))) | J15: Đối chiếu nguồn dữ liệu, trang đích, sự kiện và nơi tiếp nhận biểu mẫu.
A16: KY01 | B16: Điều kiện tiếp cận lại nhóm đã tương tác | C16: [Chưa chốt] | F16: =IF(E16="","",E16) | G16: Đã xác nhận / Không áp dụng | H16: =IF(E16="","Chưa nhập dữ liệu",IF(E16="Không áp dụng","Không áp dụng",IF(NOT(ISNUMBER(C16)),"Cần cập nhật ngày",IF(I16="","Chờ hồ sơ đối chiếu",IF(E16="Đã xác nhận","Đạt mốc tham chiếu","Cần xem xét thêm"))))) | J16: Chỉ áp dụng khi đề xuất tiếp thị lại. Có thể chọn 'Không áp dụng' nếu chưa sử dụng phương án này.
A17: KY02 | B17: Đúng nhóm doanh nghiệp và vai trò | C17: [Chưa chốt] | F17: =IF(E17="","",E17) | G17: Đã xác nhận | H17: =IF(E17="","Chưa nhập dữ liệu",IF(NOT(ISNUMBER(C17)),"Cần cập nhật ngày",IF(I17="","Chờ hồ sơ đối chiếu",IF(E17="Đã xác nhận","Đạt mốc tham chiếu","Cần xem xét thêm")))) | J17: Đối chiếu dữ liệu tiếp cận với nhóm doanh nghiệp và vai trò đã thống nhất.
A18: KY02 | B18: Lượt nhấp Search liên quan đúng chủ đề | C18: [Chưa chốt] | F18: =IF(AND(ISNUMBER(D18),ISNUMBER(E18),D18>0,E18>=0),E18/D18,"") | G18: ='01_Thiet_lap'!$D$18 | H18: =IF(COUNT(D18:E18)=0,"Chưa nhập dữ liệu",IF(NOT(ISNUMBER(F18)),"Cần rà soát số liệu",IF(NOT(ISNUMBER(C18)),"Cần cập nhật ngày",IF(E18>D18,"Cần rà soát số liệu",IF(D18<'01_Thiet_lap'!$D$23,"Cần thêm dữ liệu quan sát",IF(I18="","Chờ hồ sơ đối chiếu",IF(F18>=G18,"Đạt mốc tham chiếu","Cần xem xét thêm"))))))) | J18: Cột D: tổng nhấp được kiểm tra. Cột E: nhấp đúng chủ đề. Mốc 7/10 là tham chiếu vận hành, không khẳng định độ tin cậy thống kê.
A19: KY02 | B19: Duy trì mức quan tâm so với ban đầu | C19: [Chưa chốt] | F19: =IF(AND(ISNUMBER(D19),ISNUMBER(E19),D19>0,E19>=0),E19/D19,"") | G19: ='01_Thiet_lap'!$D$19 | H19: =IF(COUNT(D19:E19)=0,"Chưa nhập dữ liệu",IF(NOT(ISNUMBER(F19)),"Cần rà soát số liệu",IF(NOT(ISNUMBER(C19)),"Cần cập nhật ngày",IF(OR('01_Thiet_lap'!$D$28="",'01_Thiet_lap'!$D$28="[Chưa thống nhất]"),"Chờ thống nhất chỉ số",IF(I19="","Chờ hồ sơ đối chiếu",IF(F19>=G19,"Đạt mốc tham chiếu","Cần xem xét thêm")))))) | J19: D/E dùng cùng chỉ số quan tâm tại Thiết lập. Kết quả = hiện tại / ban đầu.
A20: KY02 | B20: Cải thiện của phương án được ưu tiên | C20: [Chưa chốt] | F20: =IF(AND(ISNUMBER(D20),ISNUMBER(E20),D20>0,E20>=0),E20/D20-1,"") | G20: ='01_Thiet_lap'!$D$20 | H20: =IF(COUNT(D20:E20)=0,"Chưa nhập dữ liệu",IF(NOT(ISNUMBER(F20)),"Cần rà soát số liệu",IF(NOT(ISNUMBER(C20)),"Cần cập nhật ngày",IF(OR('01_Thiet_lap'!$D$29="",'01_Thiet_lap'!$D$29="[Chưa thống nhất]"),"Chờ thống nhất chỉ số",IF(I20="","Chờ hồ sơ đối chiếu",IF(F20>=G20,"Đạt mốc tham chiếu","Cần xem xét thêm")))))) | J20: D: phương án đối chiếu; E: phương án được ưu tiên. Dùng chỉ số tăng là tốt hơn. Tiêu chí này là một lựa chọn thay thế cho giảm chi phí.
A21: KY02 | B21: Giảm chi phí với chất lượng tương đương | C21: [Chưa chốt] | F21: =IF(AND(ISNUMBER(D21),ISNUMBER(E21),D21>0,E21>=0),1-E21/D21,"") | G21: ='01_Thiet_lap'!$D$21 | H21: =IF(COUNT(D21:E21)=0,"Chưa nhập dữ liệu",IF(NOT(ISNUMBER(F21)),"Cần rà soát số liệu",IF(NOT(ISNUMBER(C21)),"Cần cập nhật ngày",IF(OR('01_Thiet_lap'!$D$30="",'01_Thiet_lap'!$D$30="[Chưa thống nhất]"),"Chờ thống nhất chỉ số",IF(I21="","Chờ hồ sơ đối chiếu",IF(F21>=G21,"Đạt mốc tham chiếu","Cần xem xét thêm")))))) | J21: D/E cùng đơn vị chi phí. Mức giảm = 1 − hiện tại/đối chiếu. Cần kèm bằng chứng chất lượng tương đương.
A22: KY02 | B22: Chất lượng ổn định khi tăng phân bổ | C22: [Chưa chốt] | F22: =IF(E22="","",E22) | G22: Đã xác nhận | H22: =IF(E22="","Chưa nhập dữ liệu",IF(NOT(ISNUMBER(C22)),"Cần cập nhật ngày",IF(I22="","Chờ hồ sơ đối chiếu",IF(E22="Đã xác nhận","Đạt mốc tham chiếu","Cần xem xét thêm")))) | J22: Ghi bằng chứng chất lượng được duy trì; không chỉ dựa trên số lượng tương tác.
A23: KY02 | B23: Mức suy giảm sau mở rộng cấp 1 | C23: [Chưa chốt] | F23: =IF(AND(ISNUMBER(D23),ISNUMBER(E23),D23>0,E23>=0),MAX(0,1-E23/D23),"") | G23: ='01_Thiet_lap'!$D$22 | H23: =IF(COUNT(D23:E23)=0,"Chưa nhập dữ liệu",IF(NOT(ISNUMBER(F23)),"Cần rà soát số liệu",IF(NOT(ISNUMBER(C23)),"Cần cập nhật ngày",IF(OR('01_Thiet_lap'!$D$28="",'01_Thiet_lap'!$D$28="[Chưa thống nhất]"),"Chờ thống nhất chỉ số",IF(I23="","Chờ hồ sơ đối chiếu",IF(F23<=G23,"Đạt mốc tham chiếu","Cần xem xét thêm")))))) | J23: Dùng khi xét cấp 2. D: mốc đối chiếu đã thống nhất; E: kỳ hiện tại. Mức giảm = MAX(0; 1 − hiện tại/đối chiếu).
A24: KY02 | B24: Dư địa tiếp cận thêm đúng nhóm mục tiêu | C24: [Chưa chốt] | F24: =IF(E24="","",E24) | G24: Đã xác nhận | H24: =IF(E24="","Chưa nhập dữ liệu",IF(NOT(ISNUMBER(C24)),"Cần cập nhật ngày",IF(I24="","Chờ hồ sơ đối chiếu",IF(E24="Đã xác nhận","Đạt mốc tham chiếu","Cần xem xét thêm")))) | J24: Dùng khi xem xét mở rộng, đặc biệt cấp 2; đối chiếu phạm vi tệp và chất lượng tiếp cận.
A25: KY02 | B25: Độ tin cậy của đo lường và trang đích | C25: [Chưa chốt] | F25: =IF(E25="","",E25) | G25: Đã xác nhận | H25: =IF(E25="","Chưa nhập dữ liệu",IF(NOT(ISNUMBER(C25)),"Cần cập nhật ngày",IF(I25="","Chờ hồ sơ đối chiếu",IF(E25="Đã xác nhận","Đạt mốc tham chiếu","Cần xem xét thêm")))) | J25: Đối chiếu nguồn dữ liệu, trang đích, sự kiện và nơi tiếp nhận biểu mẫu.
A26: KY02 | B26: Điều kiện tiếp cận lại nhóm đã tương tác | C26: [Chưa chốt] | F26: =IF(E26="","",E26) | G26: Đã xác nhận / Không áp dụng | H26: =IF(E26="","Chưa nhập dữ liệu",IF(E26="Không áp dụng","Không áp dụng",IF(NOT(ISNUMBER(C26)),"Cần cập nhật ngày",IF(I26="","Chờ hồ sơ đối chiếu",IF(E26="Đã xác nhận","Đạt mốc tham chiếu","Cần xem xét thêm"))))) | J26: Chỉ áp dụng khi đề xuất tiếp thị lại. Có thể chọn 'Không áp dụng' nếu chưa sử dụng phương án này.
A27: KY03 | B27: Đúng nhóm doanh nghiệp và vai trò | C27: [Chưa chốt] | F27: =IF(E27="","",E27) | G27: Đã xác nhận | H27: =IF(E27="","Chưa nhập dữ liệu",IF(NOT(ISNUMBER(C27)),"Cần cập nhật ngày",IF(I27="","Chờ hồ sơ đối chiếu",IF(E27="Đã xác nhận","Đạt mốc tham chiếu","Cần xem xét thêm")))) | J27: Đối chiếu dữ liệu tiếp cận với nhóm doanh nghiệp và vai trò đã thống nhất.
A28: KY03 | B28: Lượt nhấp Search liên quan đúng chủ đề | C28: [Chưa chốt] | F28: =IF(AND(ISNUMBER(D28),ISNUMBER(E28),D28>0,E28>=0),E28/D28,"") | G28: ='01_Thiet_lap'!$D$18 | H28: =IF(COUNT(D28:E28)=0,"Chưa nhập dữ liệu",IF(NOT(ISNUMBER(F28)),"Cần rà soát số liệu",IF(NOT(ISNUMBER(C28)),"Cần cập nhật ngày",IF(E28>D28,"Cần rà soát số liệu",IF(D28<'01_Thiet_lap'!$D$23,"Cần thêm dữ liệu quan sát",IF(I28="","Chờ hồ sơ đối chiếu",IF(F28>=G28,"Đạt mốc tham chiếu","Cần xem xét thêm"))))))) | J28: Cột D: tổng nhấp được kiểm tra. Cột E: nhấp đúng chủ đề. Mốc 7/10 là tham chiếu vận hành, không khẳng định độ tin cậy thống kê.
A29: KY03 | B29: Duy trì mức quan tâm so với ban đầu | C29: [Chưa chốt] | F29: =IF(AND(ISNUMBER(D29),ISNUMBER(E29),D29>0,E29>=0),E29/D29,"") | G29: ='01_Thiet_lap'!$D$19 | H29: =IF(COUNT(D29:E29)=0,"Chưa nhập dữ liệu",IF(NOT(ISNUMBER(F29)),"Cần rà soát số liệu",IF(NOT(ISNUMBER(C29)),"Cần cập nhật ngày",IF(OR('01_Thiet_lap'!$D$28="",'01_Thiet_lap'!$D$28="[Chưa thống nhất]"),"Chờ thống nhất chỉ số",IF(I29="","Chờ hồ sơ đối chiếu",IF(F29>=G29,"Đạt mốc tham chiếu","Cần xem xét thêm")))))) | J29: D/E dùng cùng chỉ số quan tâm tại Thiết lập. Kết quả = hiện tại / ban đầu.
A30: KY03 | B30: Cải thiện của phương án được ưu tiên | C30: [Chưa chốt] | F30: =IF(AND(ISNUMBER(D30),ISNUMBER(E30),D30>0,E30>=0),E30/D30-1,"") | G30: ='01_Thiet_lap'!$D$20 | H30: =IF(COUNT(D30:E30)=0,"Chưa nhập dữ liệu",IF(NOT(ISNUMBER(F30)),"Cần rà soát số liệu",IF(NOT(ISNUMBER(C30)),"Cần cập nhật ngày",IF(OR('01_Thiet_lap'!$D$29="",'01_Thiet_lap'!$D$29="[Chưa thống nhất]"),"Chờ thống nhất chỉ số",IF(I30="","Chờ hồ sơ đối chiếu",IF(F30>=G30,"Đạt mốc tham chiếu","Cần xem xét thêm")))))) | J30: D: phương án đối chiếu; E: phương án được ưu tiên. Dùng chỉ số tăng là tốt hơn. Tiêu chí này là một lựa chọn thay thế cho giảm chi phí.
A31: KY03 | B31: Giảm chi phí với chất lượng tương đương | C31: [Chưa chốt] | F31: =IF(AND(ISNUMBER(D31),ISNUMBER(E31),D31>0,E31>=0),1-E31/D31,"") | G31: ='01_Thiet_lap'!$D$21 | H31: =IF(COUNT(D31:E31)=0,"Chưa nhập dữ liệu",IF(NOT(ISNUMBER(F31)),"Cần rà soát số liệu",IF(NOT(ISNUMBER(C31)),"Cần cập nhật ngày",IF(OR('01_Thiet_lap'!$D$30="",'01_Thiet_lap'!$D$30="[Chưa thống nhất]"),"Chờ thống nhất chỉ số",IF(I31="","Chờ hồ sơ đối chiếu",IF(F31>=G31,"Đạt mốc tham chiếu","Cần xem xét thêm")))))) | J31: D/E cùng đơn vị chi phí. Mức giảm = 1 − hiện tại/đối chiếu. Cần kèm bằng chứng chất lượng tương đương.
A32: KY03 | B32: Chất lượng ổn định khi tăng phân bổ | C32: [Chưa chốt] | F32: =IF(E32="","",E32) | G32: Đã xác nhận | H32: =IF(E32="","Chưa nhập dữ liệu",IF(NOT(ISNUMBER(C32)),"Cần cập nhật ngày",IF(I32="","Chờ hồ sơ đối chiếu",IF(E32="Đã xác nhận","Đạt mốc tham chiếu","Cần xem xét thêm")))) | J32: Ghi bằng chứng chất lượng được duy trì; không chỉ dựa trên số lượng tương tác.
A33: KY03 | B33: Mức suy giảm sau mở rộng cấp 1 | C33: [Chưa chốt] | F33: =IF(AND(ISNUMBER(D33),ISNUMBER(E33),D33>0,E33>=0),MAX(0,1-E33/D33),"") | G33: ='01_Thiet_lap'!$D$22 | H33: =IF(COUNT(D33:E33)=0,"Chưa nhập dữ liệu",IF(NOT(ISNUMBER(F33)),"Cần rà soát số liệu",IF(NOT(ISNUMBER(C33)),"Cần cập nhật ngày",IF(OR('01_Thiet_lap'!$D$28="",'01_Thiet_lap'!$D$28="[Chưa thống nhất]"),"Chờ thống nhất chỉ số",IF(I33="","Chờ hồ sơ đối chiếu",IF(F33<=G33,"Đạt mốc tham chiếu","Cần xem xét thêm")))))) | J33: Dùng khi xét cấp 2. D: mốc đối chiếu đã thống nhất; E: kỳ hiện tại. Mức giảm = MAX(0; 1 − hiện tại/đối chiếu).
A34: KY03 | B34: Dư địa tiếp cận thêm đúng nhóm mục tiêu | C34: [Chưa chốt] | F34: =IF(E34="","",E34) | G34: Đã xác nhận | H34: =IF(E34="","Chưa nhập dữ liệu",IF(NOT(ISNUMBER(C34)),"Cần cập nhật ngày",IF(I34="","Chờ hồ sơ đối chiếu",IF(E34="Đã xác nhận","Đạt mốc tham chiếu","Cần xem xét thêm")))) | J34: Dùng khi xem xét mở rộng, đặc biệt cấp 2; đối chiếu phạm vi tệp và chất lượng tiếp cận.
A35: KY03 | B35: Độ tin cậy của đo lường và trang đích | C35: [Chưa chốt] | F35: =IF(E35="","",E35) | G35: Đã xác nhận | H35: =IF(E35="","Chưa nhập dữ liệu",IF(NOT(ISNUMBER(C35)),"Cần cập nhật ngày",IF(I35="","Chờ hồ sơ đối chiếu",IF(E35="Đã xác nhận","Đạt mốc tham chiếu","Cần xem xét thêm")))) | J35: Đối chiếu nguồn dữ liệu, trang đích, sự kiện và nơi tiếp nhận biểu mẫu.
A36: KY03 | B36: Điều kiện tiếp cận lại nhóm đã tương tác | C36: [Chưa chốt] | F36: =IF(E36="","",E36) | G36: Đã xác nhận / Không áp dụng | H36: =IF(E36="","Chưa nhập dữ liệu",IF(E36="Không áp dụng","Không áp dụng",IF(NOT(ISNUMBER(C36)),"Cần cập nhật ngày",IF(I36="","Chờ hồ sơ đối chiếu",IF(E36="Đã xác nhận","Đạt mốc tham chiếu","Cần xem xét thêm"))))) | J36: Chỉ áp dụng khi đề xuất tiếp thị lại. Có thể chọn 'Không áp dụng' nếu chưa sử dụng phương án này.
A37: KY04 | B37: Đúng nhóm doanh nghiệp và vai trò | C37: [Chưa chốt] | F37: =IF(E37="","",E37) | G37: Đã xác nhận | H37: =IF(E37="","Chưa nhập dữ liệu",IF(NOT(ISNUMBER(C37)),"Cần cập nhật ngày",IF(I37="","Chờ hồ sơ đối chiếu",IF(E37="Đã xác nhận","Đạt mốc tham chiếu","Cần xem xét thêm")))) | J37: Đối chiếu dữ liệu tiếp cận với nhóm doanh nghiệp và vai trò đã thống nhất.
A38: KY04 | B38: Lượt nhấp Search liên quan đúng chủ đề | C38: [Chưa chốt] | F38: =IF(AND(ISNUMBER(D38),ISNUMBER(E38),D38>0,E38>=0),E38/D38,"") | G38: ='01_Thiet_lap'!$D$18 | H38: =IF(COUNT(D38:E38)=0,"Chưa nhập dữ liệu",IF(NOT(ISNUMBER(F38)),"Cần rà soát số liệu",IF(NOT(ISNUMBER(C38)),"Cần cập nhật ngày",IF(E38>D38,"Cần rà soát số liệu",IF(D38<'01_Thiet_lap'!$D$23,"Cần thêm dữ liệu quan sát",IF(I38="","Chờ hồ sơ đối chiếu",IF(F38>=G38,"Đạt mốc tham chiếu","Cần xem xét thêm"))))))) | J38: Cột D: tổng nhấp được kiểm tra. Cột E: nhấp đúng chủ đề. Mốc 7/10 là tham chiếu vận hành, không khẳng định độ tin cậy thống kê.
A39: KY04 | B39: Duy trì mức quan tâm so với ban đầu | C39: [Chưa chốt] | F39: =IF(AND(ISNUMBER(D39),ISNUMBER(E39),D39>0,E39>=0),E39/D39,"") | G39: ='01_Thiet_lap'!$D$19 | H39: =IF(COUNT(D39:E39)=0,"Chưa nhập dữ liệu",IF(NOT(ISNUMBER(F39)),"Cần rà soát số liệu",IF(NOT(ISNUMBER(C39)),"Cần cập nhật ngày",IF(OR('01_Thiet_lap'!$D$28="",'01_Thiet_lap'!$D$28="[Chưa thống nhất]"),"Chờ thống nhất chỉ số",IF(I39="","Chờ hồ sơ đối chiếu",IF(F39>=G39,"Đạt mốc tham chiếu","Cần xem xét thêm")))))) | J39: D/E dùng cùng chỉ số quan tâm tại Thiết lập. Kết quả = hiện tại / ban đầu.
A40: KY04 | B40: Cải thiện của phương án được ưu tiên | C40: [Chưa chốt] | F40: =IF(AND(ISNUMBER(D40),ISNUMBER(E40),D40>0,E40>=0),E40/D40-1,"") | G40: ='01_Thiet_lap'!$D$20 | H40: =IF(COUNT(D40:E40)=0,"Chưa nhập dữ liệu",IF(NOT(ISNUMBER(F40)),"Cần rà soát số liệu",IF(NOT(ISNUMBER(C40)),"Cần cập nhật ngày",IF(OR('01_Thiet_lap'!$D$29="",'01_Thiet_lap'!$D$29="[Chưa thống nhất]"),"Chờ thống nhất chỉ số",IF(I40="","Chờ hồ sơ đối chiếu",IF(F40>=G40,"Đạt mốc tham chiếu","Cần xem xét thêm")))))) | J40: D: phương án đối chiếu; E: phương án được ưu tiên. Dùng chỉ số tăng là tốt hơn. Tiêu chí này là một lựa chọn thay thế cho giảm chi phí.
A41: KY04 | B41: Giảm chi phí với chất lượng tương đương | C41: [Chưa chốt] | F41: =IF(AND(ISNUMBER(D41),ISNUMBER(E41),D41>0,E41>=0),1-E41/D41,"") | G41: ='01_Thiet_lap'!$D$21 | H41: =IF(COUNT(D41:E41)=0,"Chưa nhập dữ liệu",IF(NOT(ISNUMBER(F41)),"Cần rà soát số liệu",IF(NOT(ISNUMBER(C41)),"Cần cập nhật ngày",IF(OR('01_Thiet_lap'!$D$30="",'01_Thiet_lap'!$D$30="[Chưa thống nhất]"),"Chờ thống nhất chỉ số",IF(I41="","Chờ hồ sơ đối chiếu",IF(F41>=G41,"Đạt mốc tham chiếu","Cần xem xét thêm")))))) | J41: D/E cùng đơn vị chi phí. Mức giảm = 1 − hiện tại/đối chiếu. Cần kèm bằng chứng chất lượng tương đương.
A42: KY04 | B42: Chất lượng ổn định khi tăng phân bổ | C42: [Chưa chốt] | F42: =IF(E42="","",E42) | G42: Đã xác nhận | H42: =IF(E42="","Chưa nhập dữ liệu",IF(NOT(ISNUMBER(C42)),"Cần cập nhật ngày",IF(I42="","Chờ hồ sơ đối chiếu",IF(E42="Đã xác nhận","Đạt mốc tham chiếu","Cần xem xét thêm")))) | J42: Ghi bằng chứng chất lượng được duy trì; không chỉ dựa trên số lượng tương tác.
A43: KY04 | B43: Mức suy giảm sau mở rộng cấp 1 | C43: [Chưa chốt] | F43: =IF(AND(ISNUMBER(D43),ISNUMBER(E43),D43>0,E43>=0),MAX(0,1-E43/D43),"") | G43: ='01_Thiet_lap'!$D$22 | H43: =IF(COUNT(D43:E43)=0,"Chưa nhập dữ liệu",IF(NOT(ISNUMBER(F43)),"Cần rà soát số liệu",IF(NOT(ISNUMBER(C43)),"Cần cập nhật ngày",IF(OR('01_Thiet_lap'!$D$28="",'01_Thiet_lap'!$D$28="[Chưa thống nhất]"),"Chờ thống nhất chỉ số",IF(I43="","Chờ hồ sơ đối chiếu",IF(F43<=G43,"Đạt mốc tham chiếu","Cần xem xét thêm")))))) | J43: Dùng khi xét cấp 2. D: mốc đối chiếu đã thống nhất; E: kỳ hiện tại. Mức giảm = MAX(0; 1 − hiện tại/đối chiếu).
A44: KY04 | B44: Dư địa tiếp cận thêm đúng nhóm mục tiêu | C44: [Chưa chốt] | F44: =IF(E44="","",E44) | G44: Đã xác nhận | H44: =IF(E44="","Chưa nhập dữ liệu",IF(NOT(ISNUMBER(C44)),"Cần cập nhật ngày",IF(I44="","Chờ hồ sơ đối chiếu",IF(E44="Đã xác nhận","Đạt mốc tham chiếu","Cần xem xét thêm")))) | J44: Dùng khi xem xét mở rộng, đặc biệt cấp 2; đối chiếu phạm vi tệp và chất lượng tiếp cận.
A45: KY04 | B45: Độ tin cậy của đo lường và trang đích | C45: [Chưa chốt] | F45: =IF(E45="","",E45) | G45: Đã xác nhận | H45: =IF(E45="","Chưa nhập dữ liệu",IF(NOT(ISNUMBER(C45)),"Cần cập nhật ngày",IF(I45="","Chờ hồ sơ đối chiếu",IF(E45="Đã xác nhận","Đạt mốc tham chiếu","Cần xem xét thêm")))) | J45: Đối chiếu nguồn dữ liệu, trang đích, sự kiện và nơi tiếp nhận biểu mẫu.
A46: KY04 | B46: Điều kiện tiếp cận lại nhóm đã tương tác | C46: [Chưa chốt] | F46: =IF(E46="","",E46) | G46: Đã xác nhận / Không áp dụng | H46: =IF(E46="","Chưa nhập dữ liệu",IF(E46="Không áp dụng","Không áp dụng",IF(NOT(ISNUMBER(C46)),"Cần cập nhật ngày",IF(I46="","Chờ hồ sơ đối chiếu",IF(E46="Đã xác nhận","Đạt mốc tham chiếu","Cần xem xét thêm"))))) | J46: Chỉ áp dụng khi đề xuất tiếp thị lại. Có thể chọn 'Không áp dụng' nếu chưa sử dụng phương án này.
A47: KY05 | B47: Đúng nhóm doanh nghiệp và vai trò | C47: [Chưa chốt] | F47: =IF(E47="","",E47) | G47: Đã xác nhận | H47: =IF(E47="","Chưa nhập dữ liệu",IF(NOT(ISNUMBER(C47)),"Cần cập nhật ngày",IF(I47="","Chờ hồ sơ đối chiếu",IF(E47="Đã xác nhận","Đạt mốc tham chiếu","Cần xem xét thêm")))) | J47: Đối chiếu dữ liệu tiếp cận với nhóm doanh nghiệp và vai trò đã thống nhất.
A48: KY05 | B48: Lượt nhấp Search liên quan đúng chủ đề | C48: [Chưa chốt] | F48: =IF(AND(ISNUMBER(D48),ISNUMBER(E48),D48>0,E48>=0),E48/D48,"") | G48: ='01_Thiet_lap'!$D$18 | H48: =IF(COUNT(D48:E48)=0,"Chưa nhập dữ liệu",IF(NOT(ISNUMBER(F48)),"Cần rà soát số liệu",IF(NOT(ISNUMBER(C48)),"Cần cập nhật ngày",IF(E48>D48,"Cần rà soát số liệu",IF(D48<'01_Thiet_lap'!$D$23,"Cần thêm dữ liệu quan sát",IF(I48="","Chờ hồ sơ đối chiếu",IF(F48>=G48,"Đạt mốc tham chiếu","Cần xem xét thêm"))))))) | J48: Cột D: tổng nhấp được kiểm tra. Cột E: nhấp đúng chủ đề. Mốc 7/10 là tham chiếu vận hành, không khẳng định độ tin cậy thống kê.
A49: KY05 | B49: Duy trì mức quan tâm so với ban đầu | C49: [Chưa chốt] | F49: =IF(AND(ISNUMBER(D49),ISNUMBER(E49),D49>0,E49>=0),E49/D49,"") | G49: ='01_Thiet_lap'!$D$19 | H49: =IF(COUNT(D49:E49)=0,"Chưa nhập dữ liệu",IF(NOT(ISNUMBER(F49)),"Cần rà soát số liệu",IF(NOT(ISNUMBER(C49)),"Cần cập nhật ngày",IF(OR('01_Thiet_lap'!$D$28="",'01_Thiet_lap'!$D$28="[Chưa thống nhất]"),"Chờ thống nhất chỉ số",IF(I49="","Chờ hồ sơ đối chiếu",IF(F49>=G49,"Đạt mốc tham chiếu","Cần xem xét thêm")))))) | J49: D/E dùng cùng chỉ số quan tâm tại Thiết lập. Kết quả = hiện tại / ban đầu.
A50: KY05 | B50: Cải thiện của phương án được ưu tiên | C50: [Chưa chốt] | F50: =IF(AND(ISNUMBER(D50),ISNUMBER(E50),D50>0,E50>=0),E50/D50-1,"") | G50: ='01_Thiet_lap'!$D$20 | H50: =IF(COUNT(D50:E50)=0,"Chưa nhập dữ liệu",IF(NOT(ISNUMBER(F50)),"Cần rà soát số liệu",IF(NOT(ISNUMBER(C50)),"Cần cập nhật ngày",IF(OR('01_Thiet_lap'!$D$29="",'01_Thiet_lap'!$D$29="[Chưa thống nhất]"),"Chờ thống nhất chỉ số",IF(I50="","Chờ hồ sơ đối chiếu",IF(F50>=G50,"Đạt mốc tham chiếu","Cần xem xét thêm")))))) | J50: D: phương án đối chiếu; E: phương án được ưu tiên. Dùng chỉ số tăng là tốt hơn. Tiêu chí này là một lựa chọn thay thế cho giảm chi phí.
A51: KY05 | B51: Giảm chi phí với chất lượng tương đương | C51: [Chưa chốt] | F51: =IF(AND(ISNUMBER(D51),ISNUMBER(E51),D51>0,E51>=0),1-E51/D51,"") | G51: ='01_Thiet_lap'!$D$21 | H51: =IF(COUNT(D51:E51)=0,"Chưa nhập dữ liệu",IF(NOT(ISNUMBER(F51)),"Cần rà soát số liệu",IF(NOT(ISNUMBER(C51)),"Cần cập nhật ngày",IF(OR('01_Thiet_lap'!$D$30="",'01_Thiet_lap'!$D$30="[Chưa thống nhất]"),"Chờ thống nhất chỉ số",IF(I51="","Chờ hồ sơ đối chiếu",IF(F51>=G51,"Đạt mốc tham chiếu","Cần xem xét thêm")))))) | J51: D/E cùng đơn vị chi phí. Mức giảm = 1 − hiện tại/đối chiếu. Cần kèm bằng chứng chất lượng tương đương.
A52: KY05 | B52: Chất lượng ổn định khi tăng phân bổ | C52: [Chưa chốt] | F52: =IF(E52="","",E52) | G52: Đã xác nhận | H52: =IF(E52="","Chưa nhập dữ liệu",IF(NOT(ISNUMBER(C52)),"Cần cập nhật ngày",IF(I52="","Chờ hồ sơ đối chiếu",IF(E52="Đã xác nhận","Đạt mốc tham chiếu","Cần xem xét thêm")))) | J52: Ghi bằng chứng chất lượng được duy trì; không chỉ dựa trên số lượng tương tác.
A53: KY05 | B53: Mức suy giảm sau mở rộng cấp 1 | C53: [Chưa chốt] | F53: =IF(AND(ISNUMBER(D53),ISNUMBER(E53),D53>0,E53>=0),MAX(0,1-E53/D53),"") | G53: ='01_Thiet_lap'!$D$22 | H53: =IF(COUNT(D53:E53)=0,"Chưa nhập dữ liệu",IF(NOT(ISNUMBER(F53)),"Cần rà soát số liệu",IF(NOT(ISNUMBER(C53)),"Cần cập nhật ngày",IF(OR('01_Thiet_lap'!$D$28="",'01_Thiet_lap'!$D$28="[Chưa thống nhất]"),"Chờ thống nhất chỉ số",IF(I53="","Chờ hồ sơ đối chiếu",IF(F53<=G53,"Đạt mốc tham chiếu","Cần xem xét thêm")))))) | J53: Dùng khi xét cấp 2. D: mốc đối chiếu đã thống nhất; E: kỳ hiện tại. Mức giảm = MAX(0; 1 − hiện tại/đối chiếu).
A54: KY05 | B54: Dư địa tiếp cận thêm đúng nhóm mục tiêu | C54: [Chưa chốt] | F54: =IF(E54="","",E54) | G54: Đã xác nhận | H54: =IF(E54="","Chưa nhập dữ liệu",IF(NOT(ISNUMBER(C54)),"Cần cập nhật ngày",IF(I54="","Chờ hồ sơ đối chiếu",IF(E54="Đã xác nhận","Đạt mốc tham chiếu","Cần xem xét thêm")))) | J54: Dùng khi xem xét mở rộng, đặc biệt cấp 2; đối chiếu phạm vi tệp và chất lượng tiếp cận.
A55: KY05 | B55: Độ tin cậy của đo lường và trang đích | C55: [Chưa chốt] | F55: =IF(E55="","",E55) | G55: Đã xác nhận | H55: =IF(E55="","Chưa nhập dữ liệu",IF(NOT(ISNUMBER(C55)),"Cần cập nhật ngày",IF(I55="","Chờ hồ sơ đối chiếu",IF(E55="Đã xác nhận","Đạt mốc tham chiếu","Cần xem xét thêm")))) | J55: Đối chiếu nguồn dữ liệu, trang đích, sự kiện và nơi tiếp nhận biểu mẫu.
A56: KY05 | B56: Điều kiện tiếp cận lại nhóm đã tương tác | C56: [Chưa chốt] | F56: =IF(E56="","",E56) | G56: Đã xác nhận / Không áp dụng | H56: =IF(E56="","Chưa nhập dữ liệu",IF(E56="Không áp dụng","Không áp dụng",IF(NOT(ISNUMBER(C56)),"Cần cập nhật ngày",IF(I56="","Chờ hồ sơ đối chiếu",IF(E56="Đã xác nhận","Đạt mốc tham chiếu","Cần xem xét thêm"))))) | J56: Chỉ áp dụng khi đề xuất tiếp thị lại. Có thể chọn 'Không áp dụng' nếu chưa sử dụng phương án này.
A57: KY06 | B57: Đúng nhóm doanh nghiệp và vai trò | C57: [Chưa chốt] | F57: =IF(E57="","",E57) | G57: Đã xác nhận | H57: =IF(E57="","Chưa nhập dữ liệu",IF(NOT(ISNUMBER(C57)),"Cần cập nhật ngày",IF(I57="","Chờ hồ sơ đối chiếu",IF(E57="Đã xác nhận","Đạt mốc tham chiếu","Cần xem xét thêm")))) | J57: Đối chiếu dữ liệu tiếp cận với nhóm doanh nghiệp và vai trò đã thống nhất.
A58: KY06 | B58: Lượt nhấp Search liên quan đúng chủ đề | C58: [Chưa chốt] | F58: =IF(AND(ISNUMBER(D58),ISNUMBER(E58),D58>0,E58>=0),E58/D58,"") | G58: ='01_Thiet_lap'!$D$18 | H58: =IF(COUNT(D58:E58)=0,"Chưa nhập dữ liệu",IF(NOT(ISNUMBER(F58)),"Cần rà soát số liệu",IF(NOT(ISNUMBER(C58)),"Cần cập nhật ngày",IF(E58>D58,"Cần rà soát số liệu",IF(D58<'01_Thiet_lap'!$D$23,"Cần thêm dữ liệu quan sát",IF(I58="","Chờ hồ sơ đối chiếu",IF(F58>=G58,"Đạt mốc tham chiếu","Cần xem xét thêm"))))))) | J58: Cột D: tổng nhấp được kiểm tra. Cột E: nhấp đúng chủ đề. Mốc 7/10 là tham chiếu vận hành, không khẳng định độ tin cậy thống kê.
A59: KY06 | B59: Duy trì mức quan tâm so với ban đầu | C59: [Chưa chốt] | F59: =IF(AND(ISNUMBER(D59),ISNUMBER(E59),D59>0,E59>=0),E59/D59,"") | G59: ='01_Thiet_lap'!$D$19 | H59: =IF(COUNT(D59:E59)=0,"Chưa nhập dữ liệu",IF(NOT(ISNUMBER(F59)),"Cần rà soát số liệu",IF(NOT(ISNUMBER(C59)),"Cần cập nhật ngày",IF(OR('01_Thiet_lap'!$D$28="",'01_Thiet_lap'!$D$28="[Chưa thống nhất]"),"Chờ thống nhất chỉ số",IF(I59="","Chờ hồ sơ đối chiếu",IF(F59>=G59,"Đạt mốc tham chiếu","Cần xem xét thêm")))))) | J59: D/E dùng cùng chỉ số quan tâm tại Thiết lập. Kết quả = hiện tại / ban đầu.
A60: KY06 | B60: Cải thiện của phương án được ưu tiên | C60: [Chưa chốt] | F60: =IF(AND(ISNUMBER(D60),ISNUMBER(E60),D60>0,E60>=0),E60/D60-1,"") | G60: ='01_Thiet_lap'!$D$20 | H60: =IF(COUNT(D60:E60)=0,"Chưa nhập dữ liệu",IF(NOT(ISNUMBER(F60)),"Cần rà soát số liệu",IF(NOT(ISNUMBER(C60)),"Cần cập nhật ngày",IF(OR('01_Thiet_lap'!$D$29="",'01_Thiet_lap'!$D$29="[Chưa thống nhất]"),"Chờ thống nhất chỉ số",IF(I60="","Chờ hồ sơ đối chiếu",IF(F60>=G60,"Đạt mốc tham chiếu","Cần xem xét thêm")))))) | J60: D: phương án đối chiếu; E: phương án được ưu tiên. Dùng chỉ số tăng là tốt hơn. Tiêu chí này là một lựa chọn thay thế cho giảm chi phí.
A61: KY06 | B61: Giảm chi phí với chất lượng tương đương | C61: [Chưa chốt] | F61: =IF(AND(ISNUMBER(D61),ISNUMBER(E61),D61>0,E61>=0),1-E61/D61,"") | G61: ='01_Thiet_lap'!$D$21 | H61: =IF(COUNT(D61:E61)=0,"Chưa nhập dữ liệu",IF(NOT(ISNUMBER(F61)),"Cần rà soát số liệu",IF(NOT(ISNUMBER(C61)),"Cần cập nhật ngày",IF(OR('01_Thiet_lap'!$D$30="",'01_Thiet_lap'!$D$30="[Chưa thống nhất]"),"Chờ thống nhất chỉ số",IF(I61="","Chờ hồ sơ đối chiếu",IF(F61>=G61,"Đạt mốc tham chiếu","Cần xem xét thêm")))))) | J61: D/E cùng đơn vị chi phí. Mức giảm = 1 − hiện tại/đối chiếu. Cần kèm bằng chứng chất lượng tương đương.
A62: KY06 | B62: Chất lượng ổn định khi tăng phân bổ | C62: [Chưa chốt] | F62: =IF(E62="","",E62) | G62: Đã xác nhận | H62: =IF(E62="","Chưa nhập dữ liệu",IF(NOT(ISNUMBER(C62)),"Cần cập nhật ngày",IF(I62="","Chờ hồ sơ đối chiếu",IF(E62="Đã xác nhận","Đạt mốc tham chiếu","Cần xem xét thêm")))) | J62: Ghi bằng chứng chất lượng được duy trì; không chỉ dựa trên số lượng tương tác.
A63: KY06 | B63: Mức suy giảm sau mở rộng cấp 1 | C63: [Chưa chốt] | F63: =IF(AND(ISNUMBER(D63),ISNUMBER(E63),D63>0,E63>=0),MAX(0,1-E63/D63),"") | G63: ='01_Thiet_lap'!$D$22 | H63: =IF(COUNT(D63:E63)=0,"Chưa nhập dữ liệu",IF(NOT(ISNUMBER(F63)),"Cần rà soát số liệu",IF(NOT(ISNUMBER(C63)),"Cần cập nhật ngày",IF(OR('01_Thiet_lap'!$D$28="",'01_Thiet_lap'!$D$28="[Chưa thống nhất]"),"Chờ thống nhất chỉ số",IF(I63="","Chờ hồ sơ đối chiếu",IF(F63<=G63,"Đạt mốc tham chiếu","Cần xem xét thêm")))))) | J63: Dùng khi xét cấp 2. D: mốc đối chiếu đã thống nhất; E: kỳ hiện tại. Mức giảm = MAX(0; 1 − hiện tại/đối chiếu).
A64: KY06 | B64: Dư địa tiếp cận thêm đúng nhóm mục tiêu | C64: [Chưa chốt] | F64: =IF(E64="","",E64) | G64: Đã xác nhận | H64: =IF(E64="","Chưa nhập dữ liệu",IF(NOT(ISNUMBER(C64)),"Cần cập nhật ngày",IF(I64="","Chờ hồ sơ đối chiếu",IF(E64="Đã xác nhận","Đạt mốc tham chiếu","Cần xem xét thêm")))) | J64: Dùng khi xem xét mở rộng, đặc biệt cấp 2; đối chiếu phạm vi tệp và chất lượng tiếp cận.
A65: KY06 | B65: Độ tin cậy của đo lường và trang đích | C65: [Chưa chốt] | F65: =IF(E65="","",E65) | G65: Đã xác nhận | H65: =IF(E65="","Chưa nhập dữ liệu",IF(NOT(ISNUMBER(C65)),"Cần cập nhật ngày",IF(I65="","Chờ hồ sơ đối chiếu",IF(E65="Đã xác nhận","Đạt mốc tham chiếu","Cần xem xét thêm")))) | J65: Đối chiếu nguồn dữ liệu, trang đích, sự kiện và nơi tiếp nhận biểu mẫu.
A66: KY06 | B66: Điều kiện tiếp cận lại nhóm đã tương tác | C66: [Chưa chốt] | F66: =IF(E66="","",E66) | G66: Đã xác nhận / Không áp dụng | H66: =IF(E66="","Chưa nhập dữ liệu",IF(E66="Không áp dụng","Không áp dụng",IF(NOT(ISNUMBER(C66)),"Cần cập nhật ngày",IF(I66="","Chờ hồ sơ đối chiếu",IF(E66="Đã xác nhận","Đạt mốc tham chiếu","Cần xem xét thêm"))))) | J66: Chỉ áp dụng khi đề xuất tiếp thị lại. Có thể chọn 'Không áp dụng' nếu chưa sử dụng phương án này.
A67: KY07 | B67: Đúng nhóm doanh nghiệp và vai trò | C67: [Chưa chốt] | F67: =IF(E67="","",E67) | G67: Đã xác nhận | H67: =IF(E67="","Chưa nhập dữ liệu",IF(NOT(ISNUMBER(C67)),"Cần cập nhật ngày",IF(I67="","Chờ hồ sơ đối chiếu",IF(E67="Đã xác nhận","Đạt mốc tham chiếu","Cần xem xét thêm")))) | J67: Đối chiếu dữ liệu tiếp cận với nhóm doanh nghiệp và vai trò đã thống nhất.
A68: KY07 | B68: Lượt nhấp Search liên quan đúng chủ đề | C68: [Chưa chốt] | F68: =IF(AND(ISNUMBER(D68),ISNUMBER(E68),D68>0,E68>=0),E68/D68,"") | G68: ='01_Thiet_lap'!$D$18 | H68: =IF(COUNT(D68:E68)=0,"Chưa nhập dữ liệu",IF(NOT(ISNUMBER(F68)),"Cần rà soát số liệu",IF(NOT(ISNUMBER(C68)),"Cần cập nhật ngày",IF(E68>D68,"Cần rà soát số liệu",IF(D68<'01_Thiet_lap'!$D$23,"Cần thêm dữ liệu quan sát",IF(I68="","Chờ hồ sơ đối chiếu",IF(F68>=G68,"Đạt mốc tham chiếu","Cần xem xét thêm"))))))) | J68: Cột D: tổng nhấp được kiểm tra. Cột E: nhấp đúng chủ đề. Mốc 7/10 là tham chiếu vận hành, không khẳng định độ tin cậy thống kê.
A69: KY07 | B69: Duy trì mức quan tâm so với ban đầu | C69: [Chưa chốt] | F69: =IF(AND(ISNUMBER(D69),ISNUMBER(E69),D69>0,E69>=0),E69/D69,"") | G69: ='01_Thiet_lap'!$D$19 | H69: =IF(COUNT(D69:E69)=0,"Chưa nhập dữ liệu",IF(NOT(ISNUMBER(F69)),"Cần rà soát số liệu",IF(NOT(ISNUMBER(C69)),"Cần cập nhật ngày",IF(OR('01_Thiet_lap'!$D$28="",'01_Thiet_lap'!$D$28="[Chưa thống nhất]"),"Chờ thống nhất chỉ số",IF(I69="","Chờ hồ sơ đối chiếu",IF(F69>=G69,"Đạt mốc tham chiếu","Cần xem xét thêm")))))) | J69: D/E dùng cùng chỉ số quan tâm tại Thiết lập. Kết quả = hiện tại / ban đầu.
A70: KY07 | B70: Cải thiện của phương án được ưu tiên | C70: [Chưa chốt] | F70: =IF(AND(ISNUMBER(D70),ISNUMBER(E70),D70>0,E70>=0),E70/D70-1,"") | G70: ='01_Thiet_lap'!$D$20 | H70: =IF(COUNT(D70:E70)=0,"Chưa nhập dữ liệu",IF(NOT(ISNUMBER(F70)),"Cần rà soát số liệu",IF(NOT(ISNUMBER(C70)),"Cần cập nhật ngày",IF(OR('01_Thiet_lap'!$D$29="",'01_Thiet_lap'!$D$29="[Chưa thống nhất]"),"Chờ thống nhất chỉ số",IF(I70="","Chờ hồ sơ đối chiếu",IF(F70>=G70,"Đạt mốc tham chiếu","Cần xem xét thêm")))))) | J70: D: phương án đối chiếu; E: phương án được ưu tiên. Dùng chỉ số tăng là tốt hơn. Tiêu chí này là một lựa chọn thay thế cho giảm chi phí.
A71: KY07 | B71: Giảm chi phí với chất lượng tương đương | C71: [Chưa chốt] | F71: =IF(AND(ISNUMBER(D71),ISNUMBER(E71),D71>0,E71>=0),1-E71/D71,"") | G71: ='01_Thiet_lap'!$D$21 | H71: =IF(COUNT(D71:E71)=0,"Chưa nhập dữ liệu",IF(NOT(ISNUMBER(F71)),"Cần rà soát số liệu",IF(NOT(ISNUMBER(C71)),"Cần cập nhật ngày",IF(OR('01_Thiet_lap'!$D$30="",'01_Thiet_lap'!$D$30="[Chưa thống nhất]"),"Chờ thống nhất chỉ số",IF(I71="","Chờ hồ sơ đối chiếu",IF(F71>=G71,"Đạt mốc tham chiếu","Cần xem xét thêm")))))) | J71: D/E cùng đơn vị chi phí. Mức giảm = 1 − hiện tại/đối chiếu. Cần kèm bằng chứng chất lượng tương đương.
A72: KY07 | B72: Chất lượng ổn định khi tăng phân bổ | C72: [Chưa chốt] | F72: =IF(E72="","",E72) | G72: Đã xác nhận | H72: =IF(E72="","Chưa nhập dữ liệu",IF(NOT(ISNUMBER(C72)),"Cần cập nhật ngày",IF(I72="","Chờ hồ sơ đối chiếu",IF(E72="Đã xác nhận","Đạt mốc tham chiếu","Cần xem xét thêm")))) | J72: Ghi bằng chứng chất lượng được duy trì; không chỉ dựa trên số lượng tương tác.
A73: KY07 | B73: Mức suy giảm sau mở rộng cấp 1 | C73: [Chưa chốt] | F73: =IF(AND(ISNUMBER(D73),ISNUMBER(E73),D73>0,E73>=0),MAX(0,1-E73/D73),"") | G73: ='01_Thiet_lap'!$D$22 | H73: =IF(COUNT(D73:E73)=0,"Chưa nhập dữ liệu",IF(NOT(ISNUMBER(F73)),"Cần rà soát số liệu",IF(NOT(ISNUMBER(C73)),"Cần cập nhật ngày",IF(OR('01_Thiet_lap'!$D$28="",'01_Thiet_lap'!$D$28="[Chưa thống nhất]"),"Chờ thống nhất chỉ số",IF(I73="","Chờ hồ sơ đối chiếu",IF(F73<=G73,"Đạt mốc tham chiếu","Cần xem xét thêm")))))) | J73: Dùng khi xét cấp 2. D: mốc đối chiếu đã thống nhất; E: kỳ hiện tại. Mức giảm = MAX(0; 1 − hiện tại/đối chiếu).
A74: KY07 | B74: Dư địa tiếp cận thêm đúng nhóm mục tiêu | C74: [Chưa chốt] | F74: =IF(E74="","",E74) | G74: Đã xác nhận | H74: =IF(E74="","Chưa nhập dữ liệu",IF(NOT(ISNUMBER(C74)),"Cần cập nhật ngày",IF(I74="","Chờ hồ sơ đối chiếu",IF(E74="Đã xác nhận","Đạt mốc tham chiếu","Cần xem xét thêm")))) | J74: Dùng khi xem xét mở rộng, đặc biệt cấp 2; đối chiếu phạm vi tệp và chất lượng tiếp cận.
A75: KY07 | B75: Độ tin cậy của đo lường và trang đích | C75: [Chưa chốt] | F75: =IF(E75="","",E75) | G75: Đã xác nhận | H75: =IF(E75="","Chưa nhập dữ liệu",IF(NOT(ISNUMBER(C75)),"Cần cập nhật ngày",IF(I75="","Chờ hồ sơ đối chiếu",IF(E75="Đã xác nhận","Đạt mốc tham chiếu","Cần xem xét thêm")))) | J75: Đối chiếu nguồn dữ liệu, trang đích, sự kiện và nơi tiếp nhận biểu mẫu.
A76: KY07 | B76: Điều kiện tiếp cận lại nhóm đã tương tác | C76: [Chưa chốt] | F76: =IF(E76="","",E76) | G76: Đã xác nhận / Không áp dụng | H76: =IF(E76="","Chưa nhập dữ liệu",IF(E76="Không áp dụng","Không áp dụng",IF(NOT(ISNUMBER(C76)),"Cần cập nhật ngày",IF(I76="","Chờ hồ sơ đối chiếu",IF(E76="Đã xác nhận","Đạt mốc tham chiếu","Cần xem xét thêm"))))) | J76: Chỉ áp dụng khi đề xuất tiếp thị lại. Có thể chọn 'Không áp dụng' nếu chưa sử dụng phương án này.
A77: KY08 | B77: Đúng nhóm doanh nghiệp và vai trò | C77: [Chưa chốt] | F77: =IF(E77="","",E77) | G77: Đã xác nhận | H77: =IF(E77="","Chưa nhập dữ liệu",IF(NOT(ISNUMBER(C77)),"Cần cập nhật ngày",IF(I77="","Chờ hồ sơ đối chiếu",IF(E77="Đã xác nhận","Đạt mốc tham chiếu","Cần xem xét thêm")))) | J77: Đối chiếu dữ liệu tiếp cận với nhóm doanh nghiệp và vai trò đã thống nhất.
A78: KY08 | B78: Lượt nhấp Search liên quan đúng chủ đề | C78: [Chưa chốt] | F78: =IF(AND(ISNUMBER(D78),ISNUMBER(E78),D78>0,E78>=0),E78/D78,"") | G78: ='01_Thiet_lap'!$D$18 | H78: =IF(COUNT(D78:E78)=0,"Chưa nhập dữ liệu",IF(NOT(ISNUMBER(F78)),"Cần rà soát số liệu",IF(NOT(ISNUMBER(C78)),"Cần cập nhật ngày",IF(E78>D78,"Cần rà soát số liệu",IF(D78<'01_Thiet_lap'!$D$23,"Cần thêm dữ liệu quan sát",IF(I78="","Chờ hồ sơ đối chiếu",IF(F78>=G78,"Đạt mốc tham chiếu","Cần xem xét thêm"))))))) | J78: Cột D: tổng nhấp được kiểm tra. Cột E: nhấp đúng chủ đề. Mốc 7/10 là tham chiếu vận hành, không khẳng định độ tin cậy thống kê.
A79: KY08 | B79: Duy trì mức quan tâm so với ban đầu | C79: [Chưa chốt] | F79: =IF(AND(ISNUMBER(D79),ISNUMBER(E79),D79>0,E79>=0),E79/D79,"") | G79: ='01_Thiet_lap'!$D$19 | H79: =IF(COUNT(D79:E79)=0,"Chưa nhập dữ liệu",IF(NOT(ISNUMBER(F79)),"Cần rà soát số liệu",IF(NOT(ISNUMBER(C79)),"Cần cập nhật ngày",IF(OR('01_Thiet_lap'!$D$28="",'01_Thiet_lap'!$D$28="[Chưa thống nhất]"),"Chờ thống nhất chỉ số",IF(I79="","Chờ hồ sơ đối chiếu",IF(F79>=G79,"Đạt mốc tham chiếu","Cần xem xét thêm")))))) | J79: D/E dùng cùng chỉ số quan tâm tại Thiết lập. Kết quả = hiện tại / ban đầu.
A80: KY08 | B80: Cải thiện của phương án được ưu tiên | C80: [Chưa chốt] | F80: =IF(AND(ISNUMBER(D80),ISNUMBER(E80),D80>0,E80>=0),E80/D80-1,"") | G80: ='01_Thiet_lap'!$D$20 | H80: =IF(COUNT(D80:E80)=0,"Chưa nhập dữ liệu",IF(NOT(ISNUMBER(F80)),"Cần rà soát số liệu",IF(NOT(ISNUMBER(C80)),"Cần cập nhật ngày",IF(OR('01_Thiet_lap'!$D$29="",'01_Thiet_lap'!$D$29="[Chưa thống nhất]"),"Chờ thống nhất chỉ số",IF(I80="","Chờ hồ sơ đối chiếu",IF(F80>=G80,"Đạt mốc tham chiếu","Cần xem xét thêm")))))) | J80: D: phương án đối chiếu; E: phương án được ưu tiên. Dùng chỉ số tăng là tốt hơn. Tiêu chí này là một lựa chọn thay thế cho giảm chi phí.
A81: KY08 | B81: Giảm chi phí với chất lượng tương đương | C81: [Chưa chốt] | F81: =IF(AND(ISNUMBER(D81),ISNUMBER(E81),D81>0,E81>=0),1-E81/D81,"") | G81: ='01_Thiet_lap'!$D$21 | H81: =IF(COUNT(D81:E81)=0,"Chưa nhập dữ liệu",IF(NOT(ISNUMBER(F81)),"Cần rà soát số liệu",IF(NOT(ISNUMBER(C81)),"Cần cập nhật ngày",IF(OR('01_Thiet_lap'!$D$30="",'01_Thiet_lap'!$D$30="[Chưa thống nhất]"),"Chờ thống nhất chỉ số",IF(I81="","Chờ hồ sơ đối chiếu",IF(F81>=G81,"Đạt mốc tham chiếu","Cần xem xét thêm")))))) | J81: D/E cùng đơn vị chi phí. Mức giảm = 1 − hiện tại/đối chiếu. Cần kèm bằng chứng chất lượng tương đương.
A82: KY08 | B82: Chất lượng ổn định khi tăng phân bổ | C82: [Chưa chốt] | F82: =IF(E82="","",E82) | G82: Đã xác nhận | H82: =IF(E82="","Chưa nhập dữ liệu",IF(NOT(ISNUMBER(C82)),"Cần cập nhật ngày",IF(I82="","Chờ hồ sơ đối chiếu",IF(E82="Đã xác nhận","Đạt mốc tham chiếu","Cần xem xét thêm")))) | J82: Ghi bằng chứng chất lượng được duy trì; không chỉ dựa trên số lượng tương tác.
A83: KY08 | B83: Mức suy giảm sau mở rộng cấp 1 | C83: [Chưa chốt] | F83: =IF(AND(ISNUMBER(D83),ISNUMBER(E83),D83>0,E83>=0),MAX(0,1-E83/D83),"") | G83: ='01_Thiet_lap'!$D$22 | H83: =IF(COUNT(D83:E83)=0,"Chưa nhập dữ liệu",IF(NOT(ISNUMBER(F83)),"Cần rà soát số liệu",IF(NOT(ISNUMBER(C83)),"Cần cập nhật ngày",IF(OR('01_Thiet_lap'!$D$28="",'01_Thiet_lap'!$D$28="[Chưa thống nhất]"),"Chờ thống nhất chỉ số",IF(I83="","Chờ hồ sơ đối chiếu",IF(F83<=G83,"Đạt mốc tham chiếu","Cần xem xét thêm")))))) | J83: Dùng khi xét cấp 2. D: mốc đối chiếu đã thống nhất; E: kỳ hiện tại. Mức giảm = MAX(0; 1 − hiện tại/đối chiếu).
A84: KY08 | B84: Dư địa tiếp cận thêm đúng nhóm mục tiêu | C84: [Chưa chốt] | F84: =IF(E84="","",E84) | G84: Đã xác nhận | H84: =IF(E84="","Chưa nhập dữ liệu",IF(NOT(ISNUMBER(C84)),"Cần cập nhật ngày",IF(I84="","Chờ hồ sơ đối chiếu",IF(E84="Đã xác nhận","Đạt mốc tham chiếu","Cần xem xét thêm")))) | J84: Dùng khi xem xét mở rộng, đặc biệt cấp 2; đối chiếu phạm vi tệp và chất lượng tiếp cận.
A85: KY08 | B85: Độ tin cậy của đo lường và trang đích | C85: [Chưa chốt] | F85: =IF(E85="","",E85) | G85: Đã xác nhận | H85: =IF(E85="","Chưa nhập dữ liệu",IF(NOT(ISNUMBER(C85)),"Cần cập nhật ngày",IF(I85="","Chờ hồ sơ đối chiếu",IF(E85="Đã xác nhận","Đạt mốc tham chiếu","Cần xem xét thêm")))) | J85: Đối chiếu nguồn dữ liệu, trang đích, sự kiện và nơi tiếp nhận biểu mẫu.
A86: KY08 | B86: Điều kiện tiếp cận lại nhóm đã tương tác | C86: [Chưa chốt] | F86: =IF(E86="","",E86) | G86: Đã xác nhận / Không áp dụng | H86: =IF(E86="","Chưa nhập dữ liệu",IF(E86="Không áp dụng","Không áp dụng",IF(NOT(ISNUMBER(C86)),"Cần cập nhật ngày",IF(I86="","Chờ hồ sơ đối chiếu",IF(E86="Đã xác nhận","Đạt mốc tham chiếu","Cần xem xét thêm"))))) | J86: Chỉ áp dụng khi đề xuất tiếp thị lại. Có thể chọn 'Không áp dụng' nếu chưa sử dụng phương án này.
A87: KY09 | B87: Đúng nhóm doanh nghiệp và vai trò | C87: [Chưa chốt] | F87: =IF(E87="","",E87) | G87: Đã xác nhận | H87: =IF(E87="","Chưa nhập dữ liệu",IF(NOT(ISNUMBER(C87)),"Cần cập nhật ngày",IF(I87="","Chờ hồ sơ đối chiếu",IF(E87="Đã xác nhận","Đạt mốc tham chiếu","Cần xem xét thêm")))) | J87: Đối chiếu dữ liệu tiếp cận với nhóm doanh nghiệp và vai trò đã thống nhất.
A88: KY09 | B88: Lượt nhấp Search liên quan đúng chủ đề | C88: [Chưa chốt] | F88: =IF(AND(ISNUMBER(D88),ISNUMBER(E88),D88>0,E88>=0),E88/D88,"") | G88: ='01_Thiet_lap'!$D$18 | H88: =IF(COUNT(D88:E88)=0,"Chưa nhập dữ liệu",IF(NOT(ISNUMBER(F88)),"Cần rà soát số liệu",IF(NOT(ISNUMBER(C88)),"Cần cập nhật ngày",IF(E88>D88,"Cần rà soát số liệu",IF(D88<'01_Thiet_lap'!$D$23,"Cần thêm dữ liệu quan sát",IF(I88="","Chờ hồ sơ đối chiếu",IF(F88>=G88,"Đạt mốc tham chiếu","Cần xem xét thêm"))))))) | J88: Cột D: tổng nhấp được kiểm tra. Cột E: nhấp đúng chủ đề. Mốc 7/10 là tham chiếu vận hành, không khẳng định độ tin cậy thống kê.
A89: KY09 | B89: Duy trì mức quan tâm so với ban đầu | C89: [Chưa chốt] | F89: =IF(AND(ISNUMBER(D89),ISNUMBER(E89),D89>0,E89>=0),E89/D89,"") | G89: ='01_Thiet_lap'!$D$19 | H89: =IF(COUNT(D89:E89)=0,"Chưa nhập dữ liệu",IF(NOT(ISNUMBER(F89)),"Cần rà soát số liệu",IF(NOT(ISNUMBER(C89)),"Cần cập nhật ngày",IF(OR('01_Thiet_lap'!$D$28="",'01_Thiet_lap'!$D$28="[Chưa thống nhất]"),"Chờ thống nhất chỉ số",IF(I89="","Chờ hồ sơ đối chiếu",IF(F89>=G89,"Đạt mốc tham chiếu","Cần xem xét thêm")))))) | J89: D/E dùng cùng chỉ số quan tâm tại Thiết lập. Kết quả = hiện tại / ban đầu.
A90: KY09 | B90: Cải thiện của phương án được ưu tiên | C90: [Chưa chốt] | F90: =IF(AND(ISNUMBER(D90),ISNUMBER(E90),D90>0,E90>=0),E90/D90-1,"") | G90: ='01_Thiet_lap'!$D$20 | H90: =IF(COUNT(D90:E90)=0,"Chưa nhập dữ liệu",IF(NOT(ISNUMBER(F90)),"Cần rà soát số liệu",IF(NOT(ISNUMBER(C90)),"Cần cập nhật ngày",IF(OR('01_Thiet_lap'!$D$29="",'01_Thiet_lap'!$D$29="[Chưa thống nhất]"),"Chờ thống nhất chỉ số",IF(I90="","Chờ hồ sơ đối chiếu",IF(F90>=G90,"Đạt mốc tham chiếu","Cần xem xét thêm")))))) | J90: D: phương án đối chiếu; E: phương án được ưu tiên. Dùng chỉ số tăng là tốt hơn. Tiêu chí này là một lựa chọn thay thế cho giảm chi phí.
A91: KY09 | B91: Giảm chi phí với chất lượng tương đương | C91: [Chưa chốt] | F91: =IF(AND(ISNUMBER(D91),ISNUMBER(E91),D91>0,E91>=0),1-E91/D91,"") | G91: ='01_Thiet_lap'!$D$21 | H91: =IF(COUNT(D91:E91)=0,"Chưa nhập dữ liệu",IF(NOT(ISNUMBER(F91)),"Cần rà soát số liệu",IF(NOT(ISNUMBER(C91)),"Cần cập nhật ngày",IF(OR('01_Thiet_lap'!$D$30="",'01_Thiet_lap'!$D$30="[Chưa thống nhất]"),"Chờ thống nhất chỉ số",IF(I91="","Chờ hồ sơ đối chiếu",IF(F91>=G91,"Đạt mốc tham chiếu","Cần xem xét thêm")))))) | J91: D/E cùng đơn vị chi phí. Mức giảm = 1 − hiện tại/đối chiếu. Cần kèm bằng chứng chất lượng tương đương.
A92: KY09 | B92: Chất lượng ổn định khi tăng phân bổ | C92: [Chưa chốt] | F92: =IF(E92="","",E92) | G92: Đã xác nhận | H92: =IF(E92="","Chưa nhập dữ liệu",IF(NOT(ISNUMBER(C92)),"Cần cập nhật ngày",IF(I92="","Chờ hồ sơ đối chiếu",IF(E92="Đã xác nhận","Đạt mốc tham chiếu","Cần xem xét thêm")))) | J92: Ghi bằng chứng chất lượng được duy trì; không chỉ dựa trên số lượng tương tác.
A93: KY09 | B93: Mức suy giảm sau mở rộng cấp 1 | C93: [Chưa chốt] | F93: =IF(AND(ISNUMBER(D93),ISNUMBER(E93),D93>0,E93>=0),MAX(0,1-E93/D93),"") | G93: ='01_Thiet_lap'!$D$22 | H93: =IF(COUNT(D93:E93)=0,"Chưa nhập dữ liệu",IF(NOT(ISNUMBER(F93)),"Cần rà soát số liệu",IF(NOT(ISNUMBER(C93)),"Cần cập nhật ngày",IF(OR('01_Thiet_lap'!$D$28="",'01_Thiet_lap'!$D$28="[Chưa thống nhất]"),"Chờ thống nhất chỉ số",IF(I93="","Chờ hồ sơ đối chiếu",IF(F93<=G93,"Đạt mốc tham chiếu","Cần xem xét thêm")))))) | J93: Dùng khi xét cấp 2. D: mốc đối chiếu đã thống nhất; E: kỳ hiện tại. Mức giảm = MAX(0; 1 − hiện tại/đối chiếu).
A94: KY09 | B94: Dư địa tiếp cận thêm đúng nhóm mục tiêu | C94: [Chưa chốt] | F94: =IF(E94="","",E94) | G94: Đã xác nhận | H94: =IF(E94="","Chưa nhập dữ liệu",IF(NOT(ISNUMBER(C94)),"Cần cập nhật ngày",IF(I94="","Chờ hồ sơ đối chiếu",IF(E94="Đã xác nhận","Đạt mốc tham chiếu","Cần xem xét thêm")))) | J94: Dùng khi xem xét mở rộng, đặc biệt cấp 2; đối chiếu phạm vi tệp và chất lượng tiếp cận.
A95: KY09 | B95: Độ tin cậy của đo lường và trang đích | C95: [Chưa chốt] | F95: =IF(E95="","",E95) | G95: Đã xác nhận | H95: =IF(E95="","Chưa nhập dữ liệu",IF(NOT(ISNUMBER(C95)),"Cần cập nhật ngày",IF(I95="","Chờ hồ sơ đối chiếu",IF(E95="Đã xác nhận","Đạt mốc tham chiếu","Cần xem xét thêm")))) | J95: Đối chiếu nguồn dữ liệu, trang đích, sự kiện và nơi tiếp nhận biểu mẫu.
A96: KY09 | B96: Điều kiện tiếp cận lại nhóm đã tương tác | C96: [Chưa chốt] | F96: =IF(E96="","",E96) | G96: Đã xác nhận / Không áp dụng | H96: =IF(E96="","Chưa nhập dữ liệu",IF(E96="Không áp dụng","Không áp dụng",IF(NOT(ISNUMBER(C96)),"Cần cập nhật ngày",IF(I96="","Chờ hồ sơ đối chiếu",IF(E96="Đã xác nhận","Đạt mốc tham chiếu","Cần xem xét thêm"))))) | J96: Chỉ áp dụng khi đề xuất tiếp thị lại. Có thể chọn 'Không áp dụng' nếu chưa sử dụng phương án này.
A97: KY10 | B97: Đúng nhóm doanh nghiệp và vai trò | C97: [Chưa chốt] | F97: =IF(E97="","",E97) | G97: Đã xác nhận | H97: =IF(E97="","Chưa nhập dữ liệu",IF(NOT(ISNUMBER(C97)),"Cần cập nhật ngày",IF(I97="","Chờ hồ sơ đối chiếu",IF(E97="Đã xác nhận","Đạt mốc tham chiếu","Cần xem xét thêm")))) | J97: Đối chiếu dữ liệu tiếp cận với nhóm doanh nghiệp và vai trò đã thống nhất.
A98: KY10 | B98: Lượt nhấp Search liên quan đúng chủ đề | C98: [Chưa chốt] | F98: =IF(AND(ISNUMBER(D98),ISNUMBER(E98),D98>0,E98>=0),E98/D98,"") | G98: ='01_Thiet_lap'!$D$18 | H98: =IF(COUNT(D98:E98)=0,"Chưa nhập dữ liệu",IF(NOT(ISNUMBER(F98)),"Cần rà soát số liệu",IF(NOT(ISNUMBER(C98)),"Cần cập nhật ngày",IF(E98>D98,"Cần rà soát số liệu",IF(D98<'01_Thiet_lap'!$D$23,"Cần thêm dữ liệu quan sát",IF(I98="","Chờ hồ sơ đối chiếu",IF(F98>=G98,"Đạt mốc tham chiếu","Cần xem xét thêm"))))))) | J98: Cột D: tổng nhấp được kiểm tra. Cột E: nhấp đúng chủ đề. Mốc 7/10 là tham chiếu vận hành, không khẳng định độ tin cậy thống kê.
A99: KY10 | B99: Duy trì mức quan tâm so với ban đầu | C99: [Chưa chốt] | F99: =IF(AND(ISNUMBER(D99),ISNUMBER(E99),D99>0,E99>=0),E99/D99,"") | G99: ='01_Thiet_lap'!$D$19 | H99: =IF(COUNT(D99:E99)=0,"Chưa nhập dữ liệu",IF(NOT(ISNUMBER(F99)),"Cần rà soát số liệu",IF(NOT(ISNUMBER(C99)),"Cần cập nhật ngày",IF(OR('01_Thiet_lap'!$D$28="",'01_Thiet_lap'!$D$28="[Chưa thống nhất]"),"Chờ thống nhất chỉ số",IF(I99="","Chờ hồ sơ đối chiếu",IF(F99>=G99,"Đạt mốc tham chiếu","Cần xem xét thêm")))))) | J99: D/E dùng cùng chỉ số quan tâm tại Thiết lập. Kết quả = hiện tại / ban đầu.
A100: KY10 | B100: Cải thiện của phương án được ưu tiên | C100: [Chưa chốt] | F100: =IF(AND(ISNUMBER(D100),ISNUMBER(E100),D100>0,E100>=0),E100/D100-1,"") | G100: ='01_Thiet_lap'!$D$20 | H100: =IF(COUNT(D100:E100)=0,"Chưa nhập dữ liệu",IF(NOT(ISNUMBER(F100)),"Cần rà soát số liệu",IF(NOT(ISNUMBER(C100)),"Cần cập nhật ngày",IF(OR('01_Thiet_lap'!$D$29="",'01_Thiet_lap'!$D$29="[Chưa thống nhất]"),"Chờ thống nhất chỉ số",IF(I100="","Chờ hồ sơ đối chiếu",IF(F100>=G100,"Đạt mốc tham chiếu","Cần xem xét thêm")))))) | J100: D: phương án đối chiếu; E: phương án được ưu tiên. Dùng chỉ số tăng là tốt hơn. Tiêu chí này là một lựa chọn thay thế cho giảm chi phí.
A101: KY10 | B101: Giảm chi phí với chất lượng tương đương | C101: [Chưa chốt] | F101: =IF(AND(ISNUMBER(D101),ISNUMBER(E101),D101>0,E101>=0),1-E101/D101,"") | G101: ='01_Thiet_lap'!$D$21 | H101: =IF(COUNT(D101:E101)=0,"Chưa nhập dữ liệu",IF(NOT(ISNUMBER(F101)),"Cần rà soát số liệu",IF(NOT(ISNUMBER(C101)),"Cần cập nhật ngày",IF(OR('01_Thiet_lap'!$D$30="",'01_Thiet_lap'!$D$30="[Chưa thống nhất]"),"Chờ thống nhất chỉ số",IF(I101="","Chờ hồ sơ đối chiếu",IF(F101>=G101,"Đạt mốc tham chiếu","Cần xem xét thêm")))))) | J101: D/E cùng đơn vị chi phí. Mức giảm = 1 − hiện tại/đối chiếu. Cần kèm bằng chứng chất lượng tương đương.
A102: KY10 | B102: Chất lượng ổn định khi tăng phân bổ | C102: [Chưa chốt] | F102: =IF(E102="","",E102) | G102: Đã xác nhận | H102: =IF(E102="","Chưa nhập dữ liệu",IF(NOT(ISNUMBER(C102)),"Cần cập nhật ngày",IF(I102="","Chờ hồ sơ đối chiếu",IF(E102="Đã xác nhận","Đạt mốc tham chiếu","Cần xem xét thêm")))) | J102: Ghi bằng chứng chất lượng được duy trì; không chỉ dựa trên số lượng tương tác.
...

Sheet 05_Bao_cao_tuan
A1: BÁO CÁO TUẦN & ĐỀ XUẤT KỲ TIẾP THEO
A3: Điền ngày thực cho từng kỳ; số liệu lấy từ nhật ký theo khoảng ngày và mã giai đoạn. Sáu kỳ đầu theo lộ trình tham chiếu; sáu kỳ tiếp theo dành cho trường hợp cần theo dõi bổ sung.
A6: Kỳ | B6: Giai đoạn | C6: Từ ngày | D6: Đến ngày | E6: Ngày hợp lệ | F6: Chi quảng cáo | G6: Thuế/phí | H6: Tổng gồm thuế/phí | I6: Dự phòng còn giữ | J6: Nhóm đã tiếp cận | K6: Mức độ quan tâm thực tế | L6: Nội dung rút ra | M6: Đề xuất kỳ tiếp theo | N6: Cơ sở quyết định / bằng chứng | O6: Kiểm tra kỳ báo cáo
A7: KY01 | B7: G1 | C7: [Chưa chốt] | D7: [Chưa chốt] | E7: =IF(AND(ISNUMBER(C7),ISNUMBER(D7),D7>=C7,B7<>""),SUMIFS('03_Chi_tieu'!$S$7:$S$96,'03_Chi_tieu'!$A$7:$A$96,">="&C7,'03_Chi_tieu'!$A$7:$A$96,"<="&D7,'03_Chi_tieu'!$B$7:$B$96,B7),"") | F7: =IF(AND(AND(ISNUMBER(C7),ISNUMBER(D7),D7>=C7,B7<>""),COUNTIFS('03_Chi_tieu'!$A$7:$A$96,">="&C7,'03_Chi_tieu'!$A$7:$A$96,"<="&D7,'03_Chi_tieu'!$B$7:$B$96,B7,'03_Chi_tieu'!$I$7:$I$96,">0")>0),SUMIFS('03_Chi_tieu'!$I$7:$I$96,'03_Chi_tieu'!$A$7:$A$96,">="&C7,'03_Chi_tieu'!$A$7:$A$96,"<="&D7,'03_Chi_tieu'!$B$7:$B$96,B7),"") | G7: =IF(OR(NOT(ISNUMBER(F7)),COUNTIFS('03_Chi_tieu'!$A$7:$A$96,">="&C7,'03_Chi_tieu'!$A$7:$A$96,"<="&D7,'03_Chi_tieu'!$B$7:$B$96,B7,'03_Chi_tieu'!$I$7:$I$96,">0",'03_Chi_tieu'!$M$7:$M$96,"")>0),"",SUMIFS('03_Chi_tieu'!$M$7:$M$96,'03_Chi_tieu'!$A$7:$A$96,">="&C7,'03_Chi_tieu'!$A$7:$A$96,"<="&D7,'03_Chi_tieu'!$B$7:$B$96,B7)) | H7: =IF(AND(ISNUMBER(F7),ISNUMBER(G7)),F7+G7,"") | I7: =IF(OR(NOT(ISNUMBER(F7)),COUNTIFS('03_Chi_tieu'!$A$7:$A$96,">="&C7,'03_Chi_tieu'!$A$7:$A$96,"<="&D7,'03_Chi_tieu'!$B$7:$B$96,B7,'03_Chi_tieu'!$C$7:$C$96,"Hợp lệ",'03_Chi_tieu'!$J$7:$J$96,"")>0,AND(B7="G4",NOT(ISNUMBER('01_Thiet_lap'!$D$24)))),"",SUMIFS('03_Chi_tieu'!$K$7:$K$96,'03_Chi_tieu'!$A$7:$A$96,">="&C7,'03_Chi_tieu'!$A$7:$A$96,"<="&D7,'03_Chi_tieu'!$B$7:$B$96,B7)) | M7: Chờ đánh giá | O7: =IF(NOT(AND(ISNUMBER(C7),ISNUMBER(D7))),"Chờ chốt ngày",IF(D7<C7,"Cần rà soát khoảng ngày",IF(B7="","Cần chọn giai đoạn",IF(COUNTIFS($B$7:$B$18,B7,$C$7:$C$18,"<="&D7,$D$7:$D$18,">="&C7)>1,"Cần rà soát kỳ chồng lấn",IF(NOT(ISNUMBER(F7)),"Chưa có chi ghi nhận trong kỳ",IF(COUNTIFS('03_Chi_tieu'!$A$7:$A$96,">="&C7,'03_Chi_tieu'!$A$7:$A$96,"<="&D7,'03_Chi_tieu'!$B$7:$B$96,B7,'03_Chi_tieu'!$P$7:$P$96,"?*",'03_Chi_tieu'!$P$7:$P$96,"<>Đã ghi nhận")>0,"Có dòng chi cần rà soát","Đã tổng hợp"))))))
A8: KY02 | B8: G2 | C8: [Chưa chốt] | D8: [Chưa chốt] | E8: =IF(AND(ISNUMBER(C8),ISNUMBER(D8),D8>=C8,B8<>""),SUMIFS('03_Chi_tieu'!$S$7:$S$96,'03_Chi_tieu'!$A$7:$A$96,">="&C8,'03_Chi_tieu'!$A$7:$A$96,"<="&D8,'03_Chi_tieu'!$B$7:$B$96,B8),"") | F8: =IF(AND(AND(ISNUMBER(C8),ISNUMBER(D8),D8>=C8,B8<>""),COUNTIFS('03_Chi_tieu'!$A$7:$A$96,">="&C8,'03_Chi_tieu'!$A$7:$A$96,"<="&D8,'03_Chi_tieu'!$B$7:$B$96,B8,'03_Chi_tieu'!$I$7:$I$96,">0")>0),SUMIFS('03_Chi_tieu'!$I$7:$I$96,'03_Chi_tieu'!$A$7:$A$96,">="&C8,'03_Chi_tieu'!$A$7:$A$96,"<="&D8,'03_Chi_tieu'!$B$7:$B$96,B8),"") | G8: =IF(OR(NOT(ISNUMBER(F8)),COUNTIFS('03_Chi_tieu'!$A$7:$A$96,">="&C8,'03_Chi_tieu'!$A$7:$A$96,"<="&D8,'03_Chi_tieu'!$B$7:$B$96,B8,'03_Chi_tieu'!$I$7:$I$96,">0",'03_Chi_tieu'!$M$7:$M$96,"")>0),"",SUMIFS('03_Chi_tieu'!$M$7:$M$96,'03_Chi_tieu'!$A$7:$A$96,">="&C8,'03_Chi_tieu'!$A$7:$A$96,"<="&D8,'03_Chi_tieu'!$B$7:$B$96,B8)) | H8: =IF(AND(ISNUMBER(F8),ISNUMBER(G8)),F8+G8,"") | I8: =IF(OR(NOT(ISNUMBER(F8)),COUNTIFS('03_Chi_tieu'!$A$7:$A$96,">="&C8,'03_Chi_tieu'!$A$7:$A$96,"<="&D8,'03_Chi_tieu'!$B$7:$B$96,B8,'03_Chi_tieu'!$C$7:$C$96,"Hợp lệ",'03_Chi_tieu'!$J$7:$J$96,"")>0,AND(B8="G4",NOT(ISNUMBER('01_Thiet_lap'!$D$24)))),"",SUMIFS('03_Chi_tieu'!$K$7:$K$96,'03_Chi_tieu'!$A$7:$A$96,">="&C8,'03_Chi_tieu'!$A$7:$A$96,"<="&D8,'03_Chi_tieu'!$B$7:$B$96,B8)) | M8: Chờ đánh giá | O8: =IF(NOT(AND(ISNUMBER(C8),ISNUMBER(D8))),"Chờ chốt ngày",IF(D8<C8,"Cần rà soát khoảng ngày",IF(B8="","Cần chọn giai đoạn",IF(COUNTIFS($B$7:$B$18,B8,$C$7:$C$18,"<="&D8,$D$7:$D$18,">="&C8)>1,"Cần rà soát kỳ chồng lấn",IF(NOT(ISNUMBER(F8)),"Chưa có chi ghi nhận trong kỳ",IF(COUNTIFS('03_Chi_tieu'!$A$7:$A$96,">="&C8,'03_Chi_tieu'!$A$7:$A$96,"<="&D8,'03_Chi_tieu'!$B$7:$B$96,B8,'03_Chi_tieu'!$P$7:$P$96,"?*",'03_Chi_tieu'!$P$7:$P$96,"<>Đã ghi nhận")>0,"Có dòng chi cần rà soát","Đã tổng hợp"))))))
A9: KY03 | B9: G2 | C9: [Chưa chốt] | D9: [Chưa chốt] | E9: =IF(AND(ISNUMBER(C9),ISNUMBER(D9),D9>=C9,B9<>""),SUMIFS('03_Chi_tieu'!$S$7:$S$96,'03_Chi_tieu'!$A$7:$A$96,">="&C9,'03_Chi_tieu'!$A$7:$A$96,"<="&D9,'03_Chi_tieu'!$B$7:$B$96,B9),"") | F9: =IF(AND(AND(ISNUMBER(C9),ISNUMBER(D9),D9>=C9,B9<>""),COUNTIFS('03_Chi_tieu'!$A$7:$A$96,">="&C9,'03_Chi_tieu'!$A$7:$A$96,"<="&D9,'03_Chi_tieu'!$B$7:$B$96,B9,'03_Chi_tieu'!$I$7:$I$96,">0")>0),SUMIFS('03_Chi_tieu'!$I$7:$I$96,'03_Chi_tieu'!$A$7:$A$96,">="&C9,'03_Chi_tieu'!$A$7:$A$96,"<="&D9,'03_Chi_tieu'!$B$7:$B$96,B9),"") | G9: =IF(OR(NOT(ISNUMBER(F9)),COUNTIFS('03_Chi_tieu'!$A$7:$A$96,">="&C9,'03_Chi_tieu'!$A$7:$A$96,"<="&D9,'03_Chi_tieu'!$B$7:$B$96,B9,'03_Chi_tieu'!$I$7:$I$96,">0",'03_Chi_tieu'!$M$7:$M$96,"")>0),"",SUMIFS('03_Chi_tieu'!$M$7:$M$96,'03_Chi_tieu'!$A$7:$A$96,">="&C9,'03_Chi_tieu'!$A$7:$A$96,"<="&D9,'03_Chi_tieu'!$B$7:$B$96,B9)) | H9: =IF(AND(ISNUMBER(F9),ISNUMBER(G9)),F9+G9,"") | I9: =IF(OR(NOT(ISNUMBER(F9)),COUNTIFS('03_Chi_tieu'!$A$7:$A$96,">="&C9,'03_Chi_tieu'!$A$7:$A$96,"<="&D9,'03_Chi_tieu'!$B$7:$B$96,B9,'03_Chi_tieu'!$C$7:$C$96,"Hợp lệ",'03_Chi_tieu'!$J$7:$J$96,"")>0,AND(B9="G4",NOT(ISNUMBER('01_Thiet_lap'!$D$24)))),"",SUMIFS('03_Chi_tieu'!$K$7:$K$96,'03_Chi_tieu'!$A$7:$A$96,">="&C9,'03_Chi_tieu'!$A$7:$A$96,"<="&D9,'03_Chi_tieu'!$B$7:$B$96,B9)) | M9: Chờ đánh giá | O9: =IF(NOT(AND(ISNUMBER(C9),ISNUMBER(D9))),"Chờ chốt ngày",IF(D9<C9,"Cần rà soát khoảng ngày",IF(B9="","Cần chọn giai đoạn",IF(COUNTIFS($B$7:$B$18,B9,$C$7:$C$18,"<="&D9,$D$7:$D$18,">="&C9)>1,"Cần rà soát kỳ chồng lấn",IF(NOT(ISNUMBER(F9)),"Chưa có chi ghi nhận trong kỳ",IF(COUNTIFS('03_Chi_tieu'!$A$7:$A$96,">="&C9,'03_Chi_tieu'!$A$7:$A$96,"<="&D9,'03_Chi_tieu'!$B$7:$B$96,B9,'03_Chi_tieu'!$P$7:$P$96,"?*",'03_Chi_tieu'!$P$7:$P$96,"<>Đã ghi nhận")>0,"Có dòng chi cần rà soát","Đã tổng hợp"))))))
A10: KY04 | B10: G3.1 | C10: [Chưa chốt] | D10: [Chưa chốt] | E10: =IF(AND(ISNUMBER(C10),ISNUMBER(D10),D10>=C10,B10<>""),SUMIFS('03_Chi_tieu'!$S$7:$S$96,'03_Chi_tieu'!$A$7:$A$96,">="&C10,'03_Chi_tieu'!$A$7:$A$96,"<="&D10,'03_Chi_tieu'!$B$7:$B$96,B10),"") | F10: =IF(AND(AND(ISNUMBER(C10),ISNUMBER(D10),D10>=C10,B10<>""),COUNTIFS('03_Chi_tieu'!$A$7:$A$96,">="&C10,'03_Chi_tieu'!$A$7:$A$96,"<="&D10,'03_Chi_tieu'!$B$7:$B$96,B10,'03_Chi_tieu'!$I$7:$I$96,">0")>0),SUMIFS('03_Chi_tieu'!$I$7:$I$96,'03_Chi_tieu'!$A$7:$A$96,">="&C10,'03_Chi_tieu'!$A$7:$A$96,"<="&D10,'03_Chi_tieu'!$B$7:$B$96,B10),"") | G10: =IF(OR(NOT(ISNUMBER(F10)),COUNTIFS('03_Chi_tieu'!$A$7:$A$96,">="&C10,'03_Chi_tieu'!$A$7:$A$96,"<="&D10,'03_Chi_tieu'!$B$7:$B$96,B10,'03_Chi_tieu'!$I$7:$I$96,">0",'03_Chi_tieu'!$M$7:$M$96,"")>0),"",SUMIFS('03_Chi_tieu'!$M$7:$M$96,'03_Chi_tieu'!$A$7:$A$96,">="&C10,'03_Chi_tieu'!$A$7:$A$96,"<="&D10,'03_Chi_tieu'!$B$7:$B$96,B10)) | H10: =IF(AND(ISNUMBER(F10),ISNUMBER(G10)),F10+G10,"") | I10: =IF(OR(NOT(ISNUMBER(F10)),COUNTIFS('03_Chi_tieu'!$A$7:$A$96,">="&C10,'03_Chi_tieu'!$A$7:$A$96,"<="&D10,'03_Chi_tieu'!$B$7:$B$96,B10,'03_Chi_tieu'!$C$7:$C$96,"Hợp lệ",'03_Chi_tieu'!$J$7:$J$96,"")>0,AND(B10="G4",NOT(ISNUMBER('01_Thiet_lap'!$D$24)))),"",SUMIFS('03_Chi_tieu'!$K$7:$K$96,'03_Chi_tieu'!$A$7:$A$96,">="&C10,'03_Chi_tieu'!$A$7:$A$96,"<="&D10,'03_Chi_tieu'!$B$7:$B$96,B10)) | M10: Chờ đánh giá | O10: =IF(NOT(AND(ISNUMBER(C10),ISNUMBER(D10))),"Chờ chốt ngày",IF(D10<C10,"Cần rà soát khoảng ngày",IF(B10="","Cần chọn giai đoạn",IF(COUNTIFS($B$7:$B$18,B10,$C$7:$C$18,"<="&D10,$D$7:$D$18,">="&C10)>1,"Cần rà soát kỳ chồng lấn",IF(NOT(ISNUMBER(F10)),"Chưa có chi ghi nhận trong kỳ",IF(COUNTIFS('03_Chi_tieu'!$A$7:$A$96,">="&C10,'03_Chi_tieu'!$A$7:$A$96,"<="&D10,'03_Chi_tieu'!$B$7:$B$96,B10,'03_Chi_tieu'!$P$7:$P$96,"?*",'03_Chi_tieu'!$P$7:$P$96,"<>Đã ghi nhận")>0,"Có dòng chi cần rà soát","Đã tổng hợp"))))))
A11: KY05 | B11: G3.2 | C11: [Chưa chốt] | D11: [Chưa chốt] | E11: =IF(AND(ISNUMBER(C11),ISNUMBER(D11),D11>=C11,B11<>""),SUMIFS('03_Chi_tieu'!$S$7:$S$96,'03_Chi_tieu'!$A$7:$A$96,">="&C11,'03_Chi_tieu'!$A$7:$A$96,"<="&D11,'03_Chi_tieu'!$B$7:$B$96,B11),"") | F11: =IF(AND(AND(ISNUMBER(C11),ISNUMBER(D11),D11>=C11,B11<>""),COUNTIFS('03_Chi_tieu'!$A$7:$A$96,">="&C11,'03_Chi_tieu'!$A$7:$A$96,"<="&D11,'03_Chi_tieu'!$B$7:$B$96,B11,'03_Chi_tieu'!$I$7:$I$96,">0")>0),SUMIFS('03_Chi_tieu'!$I$7:$I$96,'03_Chi_tieu'!$A$7:$A$96,">="&C11,'03_Chi_tieu'!$A$7:$A$96,"<="&D11,'03_Chi_tieu'!$B$7:$B$96,B11),"") | G11: =IF(OR(NOT(ISNUMBER(F11)),COUNTIFS('03_Chi_tieu'!$A$7:$A$96,">="&C11,'03_Chi_tieu'!$A$7:$A$96,"<="&D11,'03_Chi_tieu'!$B$7:$B$96,B11,'03_Chi_tieu'!$I$7:$I$96,">0",'03_Chi_tieu'!$M$7:$M$96,"")>0),"",SUMIFS('03_Chi_tieu'!$M$7:$M$96,'03_Chi_tieu'!$A$7:$A$96,">="&C11,'03_Chi_tieu'!$A$7:$A$96,"<="&D11,'03_Chi_tieu'!$B$7:$B$96,B11)) | H11: =IF(AND(ISNUMBER(F11),ISNUMBER(G11)),F11+G11,"") | I11: =IF(OR(NOT(ISNUMBER(F11)),COUNTIFS('03_Chi_tieu'!$A$7:$A$96,">="&C11,'03_Chi_tieu'!$A$7:$A$96,"<="&D11,'03_Chi_tieu'!$B$7:$B$96,B11,'03_Chi_tieu'!$C$7:$C$96,"Hợp lệ",'03_Chi_tieu'!$J$7:$J$96,"")>0,AND(B11="G4",NOT(ISNUMBER('01_Thiet_lap'!$D$24)))),"",SUMIFS('03_Chi_tieu'!$K$7:$K$96,'03_Chi_tieu'!$A$7:$A$96,">="&C11,'03_Chi_tieu'!$A$7:$A$96,"<="&D11,'03_Chi_tieu'!$B$7:$B$96,B11)) | M11: Chờ đánh giá | O11: =IF(NOT(AND(ISNUMBER(C11),ISNUMBER(D11))),"Chờ chốt ngày",IF(D11<C11,"Cần rà soát khoảng ngày",IF(B11="","Cần chọn giai đoạn",IF(COUNTIFS($B$7:$B$18,B11,$C$7:$C$18,"<="&D11,$D$7:$D$18,">="&C11)>1,"Cần rà soát kỳ chồng lấn",IF(NOT(ISNUMBER(F11)),"Chưa có chi ghi nhận trong kỳ",IF(COUNTIFS('03_Chi_tieu'!$A$7:$A$96,">="&C11,'03_Chi_tieu'!$A$7:$A$96,"<="&D11,'03_Chi_tieu'!$B$7:$B$96,B11,'03_Chi_tieu'!$P$7:$P$96,"?*",'03_Chi_tieu'!$P$7:$P$96,"<>Đã ghi nhận")>0,"Có dòng chi cần rà soát","Đã tổng hợp"))))))
A12: KY06 | B12: G4 | C12: [Chưa chốt] | D12: [Chưa chốt] | E12: =IF(AND(ISNUMBER(C12),ISNUMBER(D12),D12>=C12,B12<>""),SUMIFS('03_Chi_tieu'!$S$7:$S$96,'03_Chi_tieu'!$A$7:$A$96,">="&C12,'03_Chi_tieu'!$A$7:$A$96,"<="&D12,'03_Chi_tieu'!$B$7:$B$96,B12),"") | F12: =IF(AND(AND(ISNUMBER(C12),ISNUMBER(D12),D12>=C12,B12<>""),COUNTIFS('03_Chi_tieu'!$A$7:$A$96,">="&C12,'03_Chi_tieu'!$A$7:$A$96,"<="&D12,'03_Chi_tieu'!$B$7:$B$96,B12,'03_Chi_tieu'!$I$7:$I$96,">0")>0),SUMIFS('03_Chi_tieu'!$I$7:$I$96,'03_Chi_tieu'!$A$7:$A$96,">="&C12,'03_Chi_tieu'!$A$7:$A$96,"<="&D12,'03_Chi_tieu'!$B$7:$B$96,B12),"") | G12: =IF(OR(NOT(ISNUMBER(F12)),COUNTIFS('03_Chi_tieu'!$A$7:$A$96,">="&C12,'03_Chi_tieu'!$A$7:$A$96,"<="&D12,'03_Chi_tieu'!$B$7:$B$96,B12,'03_Chi_tieu'!$I$7:$I$96,">0",'03_Chi_tieu'!$M$7:$M$96,"")>0),"",SUMIFS('03_Chi_tieu'!$M$7:$M$96,'03_Chi_tieu'!$A$7:$A$96,">="&C12,'03_Chi_tieu'!$A$7:$A$96,"<="&D12,'03_Chi_tieu'!$B$7:$B$96,B12)) | H12: =IF(AND(ISNUMBER(F12),ISNUMBER(G12)),F12+G12,"") | I12: =IF(OR(NOT(ISNUMBER(F12)),COUNTIFS('03_Chi_tieu'!$A$7:$A$96,">="&C12,'03_Chi_tieu'!$A$7:$A$96,"<="&D12,'03_Chi_tieu'!$B$7:$B$96,B12,'03_Chi_tieu'!$C$7:$C$96,"Hợp lệ",'03_Chi_tieu'!$J$7:$J$96,"")>0,AND(B12="G4",NOT(ISNUMBER('01_Thiet_lap'!$D$24)))),"",SUMIFS('03_Chi_tieu'!$K$7:$K$96,'03_Chi_tieu'!$A$7:$A$96,">="&C12,'03_Chi_tieu'!$A$7:$A$96,"<="&D12,'03_Chi_tieu'!$B$7:$B$96,B12)) | M12: Chờ đánh giá | O12: =IF(NOT(AND(ISNUMBER(C12),ISNUMBER(D12))),"Chờ chốt ngày",IF(D12<C12,"Cần rà soát khoảng ngày",IF(B12="","Cần chọn giai đoạn",IF(COUNTIFS($B$7:$B$18,B12,$C$7:$C$18,"<="&D12,$D$7:$D$18,">="&C12)>1,"Cần rà soát kỳ chồng lấn",IF(NOT(ISNUMBER(F12)),"Chưa có chi ghi nhận trong kỳ",IF(COUNTIFS('03_Chi_tieu'!$A$7:$A$96,">="&C12,'03_Chi_tieu'!$A$7:$A$96,"<="&D12,'03_Chi_tieu'!$B$7:$B$96,B12,'03_Chi_tieu'!$P$7:$P$96,"?*",'03_Chi_tieu'!$P$7:$P$96,"<>Đã ghi nhận")>0,"Có dòng chi cần rà soát","Đã tổng hợp"))))))
A13: KY07 | C13: [Chưa chốt] | D13: [Chưa chốt] | E13: =IF(AND(ISNUMBER(C13),ISNUMBER(D13),D13>=C13,B13<>""),SUMIFS('03_Chi_tieu'!$S$7:$S$96,'03_Chi_tieu'!$A$7:$A$96,">="&C13,'03_Chi_tieu'!$A$7:$A$96,"<="&D13,'03_Chi_tieu'!$B$7:$B$96,B13),"") | F13: =IF(AND(AND(ISNUMBER(C13),ISNUMBER(D13),D13>=C13,B13<>""),COUNTIFS('03_Chi_tieu'!$A$7:$A$96,">="&C13,'03_Chi_tieu'!$A$7:$A$96,"<="&D13,'03_Chi_tieu'!$B$7:$B$96,B13,'03_Chi_tieu'!$I$7:$I$96,">0")>0),SUMIFS('03_Chi_tieu'!$I$7:$I$96,'03_Chi_tieu'!$A$7:$A$96,">="&C13,'03_Chi_tieu'!$A$7:$A$96,"<="&D13,'03_Chi_tieu'!$B$7:$B$96,B13),"") | G13: =IF(OR(NOT(ISNUMBER(F13)),COUNTIFS('03_Chi_tieu'!$A$7:$A$96,">="&C13,'03_Chi_tieu'!$A$7:$A$96,"<="&D13,'03_Chi_tieu'!$B$7:$B$96,B13,'03_Chi_tieu'!$I$7:$I$96,">0",'03_Chi_tieu'!$M$7:$M$96,"")>0),"",SUMIFS('03_Chi_tieu'!$M$7:$M$96,'03_Chi_tieu'!$A$7:$A$96,">="&C13,'03_Chi_tieu'!$A$7:$A$96,"<="&D13,'03_Chi_tieu'!$B$7:$B$96,B13)) | H13: =IF(AND(ISNUMBER(F13),ISNUMBER(G13)),F13+G13,"") | I13: =IF(OR(NOT(ISNUMBER(F13)),COUNTIFS('03_Chi_tieu'!$A$7:$A$96,">="&C13,'03_Chi_tieu'!$A$7:$A$96,"<="&D13,'03_Chi_tieu'!$B$7:$B$96,B13,'03_Chi_tieu'!$C$7:$C$96,"Hợp lệ",'03_Chi_tieu'!$J$7:$J$96,"")>0,AND(B13="G4",NOT(ISNUMBER('01_Thiet_lap'!$D$24)))),"",SUMIFS('03_Chi_tieu'!$K$7:$K$96,'03_Chi_tieu'!$A$7:$A$96,">="&C13,'03_Chi_tieu'!$A$7:$A$96,"<="&D13,'03_Chi_tieu'!$B$7:$B$96,B13)) | M13: Chờ đánh giá | O13: =IF(NOT(AND(ISNUMBER(C13),ISNUMBER(D13))),"Chờ chốt ngày",IF(D13<C13,"Cần rà soát khoảng ngày",IF(B13="","Cần chọn giai đoạn",IF(COUNTIFS($B$7:$B$18,B13,$C$7:$C$18,"<="&D13,$D$7:$D$18,">="&C13)>1,"Cần rà soát kỳ chồng lấn",IF(NOT(ISNUMBER(F13)),"Chưa có chi ghi nhận trong kỳ",IF(COUNTIFS('03_Chi_tieu'!$A$7:$A$96,">="&C13,'03_Chi_tieu'!$A$7:$A$96,"<="&D13,'03_Chi_tieu'!$B$7:$B$96,B13,'03_Chi_tieu'!$P$7:$P$96,"?*",'03_Chi_tieu'!$P$7:$P$96,"<>Đã ghi nhận")>0,"Có dòng chi cần rà soát","Đã tổng hợp"))))))
A14: KY08 | C14: [Chưa chốt] | D14: [Chưa chốt] | E14: =IF(AND(ISNUMBER(C14),ISNUMBER(D14),D14>=C14,B14<>""),SUMIFS('03_Chi_tieu'!$S$7:$S$96,'03_Chi_tieu'!$A$7:$A$96,">="&C14,'03_Chi_tieu'!$A$7:$A$96,"<="&D14,'03_Chi_tieu'!$B$7:$B$96,B14),"") | F14: =IF(AND(AND(ISNUMBER(C14),ISNUMBER(D14),D14>=C14,B14<>""),COUNTIFS('03_Chi_tieu'!$A$7:$A$96,">="&C14,'03_Chi_tieu'!$A$7:$A$96,"<="&D14,'03_Chi_tieu'!$B$7:$B$96,B14,'03_Chi_tieu'!$I$7:$I$96,">0")>0),SUMIFS('03_Chi_tieu'!$I$7:$I$96,'03_Chi_tieu'!$A$7:$A$96,">="&C14,'03_Chi_tieu'!$A$7:$A$96,"<="&D14,'03_Chi_tieu'!$B$7:$B$96,B14),"") | G14: =IF(OR(NOT(ISNUMBER(F14)),COUNTIFS('03_Chi_tieu'!$A$7:$A$96,">="&C14,'03_Chi_tieu'!$A$7:$A$96,"<="&D14,'03_Chi_tieu'!$B$7:$B$96,B14,'03_Chi_tieu'!$I$7:$I$96,">0",'03_Chi_tieu'!$M$7:$M$96,"")>0),"",SUMIFS('03_Chi_tieu'!$M$7:$M$96,'03_Chi_tieu'!$A$7:$A$96,">="&C14,'03_Chi_tieu'!$A$7:$A$96,"<="&D14,'03_Chi_tieu'!$B$7:$B$96,B14)) | H14: =IF(AND(ISNUMBER(F14),ISNUMBER(G14)),F14+G14,"") | I14: =IF(OR(NOT(ISNUMBER(F14)),COUNTIFS('03_Chi_tieu'!$A$7:$A$96,">="&C14,'03_Chi_tieu'!$A$7:$A$96,"<="&D14,'03_Chi_tieu'!$B$7:$B$96,B14,'03_Chi_tieu'!$C$7:$C$96,"Hợp lệ",'03_Chi_tieu'!$J$7:$J$96,"")>0,AND(B14="G4",NOT(ISNUMBER('01_Thiet_lap'!$D$24)))),"",SUMIFS('03_Chi_tieu'!$K$7:$K$96,'03_Chi_tieu'!$A$7:$A$96,">="&C14,'03_Chi_tieu'!$A$7:$A$96,"<="&D14,'03_Chi_tieu'!$B$7:$B$96,B14)) | M14: Chờ đánh giá | O14: =IF(NOT(AND(ISNUMBER(C14),ISNUMBER(D14))),"Chờ chốt ngày",IF(D14<C14,"Cần rà soát khoảng ngày",IF(B14="","Cần chọn giai đoạn",IF(COUNTIFS($B$7:$B$18,B14,$C$7:$C$18,"<="&D14,$D$7:$D$18,">="&C14)>1,"Cần rà soát kỳ chồng lấn",IF(NOT(ISNUMBER(F14)),"Chưa có chi ghi nhận trong kỳ",IF(COUNTIFS('03_Chi_tieu'!$A$7:$A$96,">="&C14,'03_Chi_tieu'!$A$7:$A$96,"<="&D14,'03_Chi_tieu'!$B$7:$B$96,B14,'03_Chi_tieu'!$P$7:$P$96,"?*",'03_Chi_tieu'!$P$7:$P$96,"<>Đã ghi nhận")>0,"Có dòng chi cần rà soát","Đã tổng hợp"))))))
A15: KY09 | C15: [Chưa chốt] | D15: [Chưa chốt] | E15: =IF(AND(ISNUMBER(C15),ISNUMBER(D15),D15>=C15,B15<>""),SUMIFS('03_Chi_tieu'!$S$7:$S$96,'03_Chi_tieu'!$A$7:$A$96,">="&C15,'03_Chi_tieu'!$A$7:$A$96,"<="&D15,'03_Chi_tieu'!$B$7:$B$96,B15),"") | F15: =IF(AND(AND(ISNUMBER(C15),ISNUMBER(D15),D15>=C15,B15<>""),COUNTIFS('03_Chi_tieu'!$A$7:$A$96,">="&C15,'03_Chi_tieu'!$A$7:$A$96,"<="&D15,'03_Chi_tieu'!$B$7:$B$96,B15,'03_Chi_tieu'!$I$7:$I$96,">0")>0),SUMIFS('03_Chi_tieu'!$I$7:$I$96,'03_Chi_tieu'!$A$7:$A$96,">="&C15,'03_Chi_tieu'!$A$7:$A$96,"<="&D15,'03_Chi_tieu'!$B$7:$B$96,B15),"") | G15: =IF(OR(NOT(ISNUMBER(F15)),COUNTIFS('03_Chi_tieu'!$A$7:$A$96,">="&C15,'03_Chi_tieu'!$A$7:$A$96,"<="&D15,'03_Chi_tieu'!$B$7:$B$96,B15,'03_Chi_tieu'!$I$7:$I$96,">0",'03_Chi_tieu'!$M$7:$M$96,"")>0),"",SUMIFS('03_Chi_tieu'!$M$7:$M$96,'03_Chi_tieu'!$A$7:$A$96,">="&C15,'03_Chi_tieu'!$A$7:$A$96,"<="&D15,'03_Chi_tieu'!$B$7:$B$96,B15)) | H15: =IF(AND(ISNUMBER(F15),ISNUMBER(G15)),F15+G15,"") | I15: =IF(OR(NOT(ISNUMBER(F15)),COUNTIFS('03_Chi_tieu'!$A$7:$A$96,">="&C15,'03_Chi_tieu'!$A$7:$A$96,"<="&D15,'03_Chi_tieu'!$B$7:$B$96,B15,'03_Chi_tieu'!$C$7:$C$96,"Hợp lệ",'03_Chi_tieu'!$J$7:$J$96,"")>0,AND(B15="G4",NOT(ISNUMBER('01_Thiet_lap'!$D$24)))),"",SUMIFS('03_Chi_tieu'!$K$7:$K$96,'03_Chi_tieu'!$A$7:$A$96,">="&C15,'03_Chi_tieu'!$A$7:$A$96,"<="&D15,'03_Chi_tieu'!$B$7:$B$96,B15)) | M15: Chờ đánh giá | O15: =IF(NOT(AND(ISNUMBER(C15),ISNUMBER(D15))),"Chờ chốt ngày",IF(D15<C15,"Cần rà soát khoảng ngày",IF(B15="","Cần chọn giai đoạn",IF(COUNTIFS($B$7:$B$18,B15,$C$7:$C$18,"<="&D15,$D$7:$D$18,">="&C15)>1,"Cần rà soát kỳ chồng lấn",IF(NOT(ISNUMBER(F15)),"Chưa có chi ghi nhận trong kỳ",IF(COUNTIFS('03_Chi_tieu'!$A$7:$A$96,">="&C15,'03_Chi_tieu'!$A$7:$A$96,"<="&D15,'03_Chi_tieu'!$B$7:$B$96,B15,'03_Chi_tieu'!$P$7:$P$96,"?*",'03_Chi_tieu'!$P$7:$P$96,"<>Đã ghi nhận")>0,"Có dòng chi cần rà soát","Đã tổng hợp"))))))
A16: KY10 | C16: [Chưa chốt] | D16: [Chưa chốt] | E16: =IF(AND(ISNUMBER(C16),ISNUMBER(D16),D16>=C16,B16<>""),SUMIFS('03_Chi_tieu'!$S$7:$S$96,'03_Chi_tieu'!$A$7:$A$96,">="&C16,'03_Chi_tieu'!$A$7:$A$96,"<="&D16,'03_Chi_tieu'!$B$7:$B$96,B16),"") | F16: =IF(AND(AND(ISNUMBER(C16),ISNUMBER(D16),D16>=C16,B16<>""),COUNTIFS('03_Chi_tieu'!$A$7:$A$96,">="&C16,'03_Chi_tieu'!$A$7:$A$96,"<="&D16,'03_Chi_tieu'!$B$7:$B$96,B16,'03_Chi_tieu'!$I$7:$I$96,">0")>0),SUMIFS('03_Chi_tieu'!$I$7:$I$96,'03_Chi_tieu'!$A$7:$A$96,">="&C16,'03_Chi_tieu'!$A$7:$A$96,"<="&D16,'03_Chi_tieu'!$B$7:$B$96,B16),"") | G16: =IF(OR(NOT(ISNUMBER(F16)),COUNTIFS('03_Chi_tieu'!$A$7:$A$96,">="&C16,'03_Chi_tieu'!$A$7:$A$96,"<="&D16,'03_Chi_tieu'!$B$7:$B$96,B16,'03_Chi_tieu'!$I$7:$I$96,">0",'03_Chi_tieu'!$M$7:$M$96,"")>0),"",SUMIFS('03_Chi_tieu'!$M$7:$M$96,'03_Chi_tieu'!$A$7:$A$96,">="&C16,'03_Chi_tieu'!$A$7:$A$96,"<="&D16,'03_Chi_tieu'!$B$7:$B$96,B16)) | H16: =IF(AND(ISNUMBER(F16),ISNUMBER(G16)),F16+G16,"") | I16: =IF(OR(NOT(ISNUMBER(F16)),COUNTIFS('03_Chi_tieu'!$A$7:$A$96,">="&C16,'03_Chi_tieu'!$A$7:$A$96,"<="&D16,'03_Chi_tieu'!$B$7:$B$96,B16,'03_Chi_tieu'!$C$7:$C$96,"Hợp lệ",'03_Chi_tieu'!$J$7:$J$96,"")>0,AND(B16="G4",NOT(ISNUMBER('01_Thiet_lap'!$D$24)))),"",SUMIFS('03_Chi_tieu'!$K$7:$K$96,'03_Chi_tieu'!$A$7:$A$96,">="&C16,'03_Chi_tieu'!$A$7:$A$96,"<="&D16,'03_Chi_tieu'!$B$7:$B$96,B16)) | M16: Chờ đánh giá | O16: =IF(NOT(AND(ISNUMBER(C16),ISNUMBER(D16))),"Chờ chốt ngày",IF(D16<C16,"Cần rà soát khoảng ngày",IF(B16="","Cần chọn giai đoạn",IF(COUNTIFS($B$7:$B$18,B16,$C$7:$C$18,"<="&D16,$D$7:$D$18,">="&C16)>1,"Cần rà soát kỳ chồng lấn",IF(NOT(ISNUMBER(F16)),"Chưa có chi ghi nhận trong kỳ",IF(COUNTIFS('03_Chi_tieu'!$A$7:$A$96,">="&C16,'03_Chi_tieu'!$A$7:$A$96,"<="&D16,'03_Chi_tieu'!$B$7:$B$96,B16,'03_Chi_tieu'!$P$7:$P$96,"?*",'03_Chi_tieu'!$P$7:$P$96,"<>Đã ghi nhận")>0,"Có dòng chi cần rà soát","Đã tổng hợp"))))))
A17: KY11 | C17: [Chưa chốt] | D17: [Chưa chốt] | E17: =IF(AND(ISNUMBER(C17),ISNUMBER(D17),D17>=C17,B17<>""),SUMIFS('03_Chi_tieu'!$S$7:$S$96,'03_Chi_tieu'!$A$7:$A$96,">="&C17,'03_Chi_tieu'!$A$7:$A$96,"<="&D17,'03_Chi_tieu'!$B$7:$B$96,B17),"") | F17: =IF(AND(AND(ISNUMBER(C17),ISNUMBER(D17),D17>=C17,B17<>""),COUNTIFS('03_Chi_tieu'!$A$7:$A$96,">="&C17,'03_Chi_tieu'!$A$7:$A$96,"<="&D17,'03_Chi_tieu'!$B$7:$B$96,B17,'03_Chi_tieu'!$I$7:$I$96,">0")>0),SUMIFS('03_Chi_tieu'!$I$7:$I$96,'03_Chi_tieu'!$A$7:$A$96,">="&C17,'03_Chi_tieu'!$A$7:$A$96,"<="&D17,'03_Chi_tieu'!$B$7:$B$96,B17),"") | G17: =IF(OR(NOT(ISNUMBER(F17)),COUNTIFS('03_Chi_tieu'!$A$7:$A$96,">="&C17,'03_Chi_tieu'!$A$7:$A$96,"<="&D17,'03_Chi_tieu'!$B$7:$B$96,B17,'03_Chi_tieu'!$I$7:$I$96,">0",'03_Chi_tieu'!$M$7:$M$96,"")>0),"",SUMIFS('03_Chi_tieu'!$M$7:$M$96,'03_Chi_tieu'!$A$7:$A$96,">="&C17,'03_Chi_tieu'!$A$7:$A$96,"<="&D17,'03_Chi_tieu'!$B$7:$B$96,B17)) | H17: =IF(AND(ISNUMBER(F17),ISNUMBER(G17)),F17+G17,"") | I17: =IF(OR(NOT(ISNUMBER(F17)),COUNTIFS('03_Chi_tieu'!$A$7:$A$96,">="&C17,'03_Chi_tieu'!$A$7:$A$96,"<="&D17,'03_Chi_tieu'!$B$7:$B$96,B17,'03_Chi_tieu'!$C$7:$C$96,"Hợp lệ",'03_Chi_tieu'!$J$7:$J$96,"")>0,AND(B17="G4",NOT(ISNUMBER('01_Thiet_lap'!$D$24)))),"",SUMIFS('03_Chi_tieu'!$K$7:$K$96,'03_Chi_tieu'!$A$7:$A$96,">="&C17,'03_Chi_tieu'!$A$7:$A$96,"<="&D17,'03_Chi_tieu'!$B$7:$B$96,B17)) | M17: Chờ đánh giá | O17: =IF(NOT(AND(ISNUMBER(C17),ISNUMBER(D17))),"Chờ chốt ngày",IF(D17<C17,"Cần rà soát khoảng ngày",IF(B17="","Cần chọn giai đoạn",IF(COUNTIFS($B$7:$B$18,B17,$C$7:$C$18,"<="&D17,$D$7:$D$18,">="&C17)>1,"Cần rà soát kỳ chồng lấn",IF(NOT(ISNUMBER(F17)),"Chưa có chi ghi nhận trong kỳ",IF(COUNTIFS('03_Chi_tieu'!$A$7:$A$96,">="&C17,'03_Chi_tieu'!$A$7:$A$96,"<="&D17,'03_Chi_tieu'!$B$7:$B$96,B17,'03_Chi_tieu'!$P$7:$P$96,"?*",'03_Chi_tieu'!$P$7:$P$96,"<>Đã ghi nhận")>0,"Có dòng chi cần rà soát","Đã tổng hợp"))))))
A18: KY12 | C18: [Chưa chốt] | D18: [Chưa chốt] | E18: =IF(AND(ISNUMBER(C18),ISNUMBER(D18),D18>=C18,B18<>""),SUMIFS('03_Chi_tieu'!$S$7:$S$96,'03_Chi_tieu'!$A$7:$A$96,">="&C18,'03_Chi_tieu'!$A$7:$A$96,"<="&D18,'03_Chi_tieu'!$B$7:$B$96,B18),"") | F18: =IF(AND(AND(ISNUMBER(C18),ISNUMBER(D18),D18>=C18,B18<>""),COUNTIFS('03_Chi_tieu'!$A$7:$A$96,">="&C18,'03_Chi_tieu'!$A$7:$A$96,"<="&D18,'03_Chi_tieu'!$B$7:$B$96,B18,'03_Chi_tieu'!$I$7:$I$96,">0")>0),SUMIFS('03_Chi_tieu'!$I$7:$I$96,'03_Chi_tieu'!$A$7:$A$96,">="&C18,'03_Chi_tieu'!$A$7:$A$96,"<="&D18,'03_Chi_tieu'!$B$7:$B$96,B18),"") | G18: =IF(OR(NOT(ISNUMBER(F18)),COUNTIFS('03_Chi_tieu'!$A$7:$A$96,">="&C18,'03_Chi_tieu'!$A$7:$A$96,"<="&D18,'03_Chi_tieu'!$B$7:$B$96,B18,'03_Chi_tieu'!$I$7:$I$96,">0",'03_Chi_tieu'!$M$7:$M$96,"")>0),"",SUMIFS('03_Chi_tieu'!$M$7:$M$96,'03_Chi_tieu'!$A$7:$A$96,">="&C18,'03_Chi_tieu'!$A$7:$A$96,"<="&D18,'03_Chi_tieu'!$B$7:$B$96,B18)) | H18: =IF(AND(ISNUMBER(F18),ISNUMBER(G18)),F18+G18,"") | I18: =IF(OR(NOT(ISNUMBER(F18)),COUNTIFS('03_Chi_tieu'!$A$7:$A$96,">="&C18,'03_Chi_tieu'!$A$7:$A$96,"<="&D18,'03_Chi_tieu'!$B$7:$B$96,B18,'03_Chi_tieu'!$C$7:$C$96,"Hợp lệ",'03_Chi_tieu'!$J$7:$J$96,"")>0,AND(B18="G4",NOT(ISNUMBER('01_Thiet_lap'!$D$24)))),"",SUMIFS('03_Chi_tieu'!$K$7:$K$96,'03_Chi_tieu'!$A$7:$A$96,">="&C18,'03_Chi_tieu'!$A$7:$A$96,"<="&D18,'03_Chi_tieu'!$B$7:$B$96,B18)) | M18: Chờ đánh giá | O18: =IF(NOT(AND(ISNUMBER(C18),ISNUMBER(D18))),"Chờ chốt ngày",IF(D18<C18,"Cần rà soát khoảng ngày",IF(B18="","Cần chọn giai đoạn",IF(COUNTIFS($B$7:$B$18,B18,$C$7:$C$18,"<="&D18,$D$7:$D$18,">="&C18)>1,"Cần rà soát kỳ chồng lấn",IF(NOT(ISNUMBER(F18)),"Chưa có chi ghi nhận trong kỳ",IF(COUNTIFS('03_Chi_tieu'!$A$7:$A$96,">="&C18,'03_Chi_tieu'!$A$7:$A$96,"<="&D18,'03_Chi_tieu'!$B$7:$B$96,B18,'03_Chi_tieu'!$P$7:$P$96,"?*",'03_Chi_tieu'!$P$7:$P$96,"<>Đã ghi nhận")>0,"Có dòng chi cần rà soát","Đã tổng hợp"))))))
A20: Mỗi báo cáo cần đủ sáu nội dung: đã chi, đã tiếp cận nhóm nào, mức quan tâm, nội dung rút ra, đề xuất kỳ tiếp theo và dự phòng còn giữ. Nhận định và phê duyệt được cập nhật thủ công; công thức không tự quyết định tăng ngân sách.
A22: Không cộng chồng các kỳ có khoảng ngày trùng nhau trong cùng giai đoạn. Thuế/phí hoặc dự phòng còn thiếu sẽ để trống phần tổng hợp liên quan. Các kỳ bổ sung không tự làm tăng khung ngân sách đã được duyệt.

Sheet 06_Kiem_tra
A1: DANH SÁCH KIỂM TRA TRƯỚC TRIỂN KHAI
A3: Trạng thái ban đầu là Chưa xác nhận; phụ trách và thời hạn để placeholder. Chỉ chuyển trạng thái sau khi có nội dung đối chiếu phù hợp.
A6: STT | B6: Hạng mục | C6: Nội dung xác nhận | D6: Trạng thái | E6: Phụ trách | F6: Ngày dự kiến | G6: Ngày xác nhận | H6: Bằng chứng / ghi chú
A7: 1 | B7: Phạm vi ngân sách | C7: Xác nhận 1.000.000 VNĐ/ngày là chi quảng cáo hay đã gồm thuế/phí. | D7: Chưa xác nhận | E7: [Chưa phân công] | F7: [Chưa chốt] | G7: [Chưa chốt]
A8: 2 | B8: Tách thuế và phí | C8: Xác định phần thuế, phí dịch vụ và sản xuất nội dung ngoài ngân sách quảng cáo. | D8: Chưa xác nhận | E8: [Chưa phân công] | F8: [Chưa chốt] | G8: [Chưa chốt]
A9: 3 | B9: Lịch bắt đầu | C9: Thống nhất ngày bắt đầu và cập nhật vào Thiết lập / Lộ trình. | D9: Chưa xác nhận | E9: [Chưa phân công] | F9: [Chưa chốt] | G9: [Chưa chốt]
A10: 4 | B10: Lịch kết thúc | C10: Thống nhất ngày kết thúc, ngày không chạy và cách tính ngày hợp lệ. | D10: Chưa xác nhận | E10: [Chưa phân công] | F10: [Chưa chốt] | G10: [Chưa chốt]
A11: 5 | B11: Thẩm quyền điều chỉnh | C11: Xác nhận quyền phân bổ giữa kênh và giới hạn điều chỉnh trong khung ngân sách. | D11: Chưa xác nhận | E11: [Chưa phân công] | F11: [Chưa chốt] | G11: [Chưa chốt]
A12: 6 | B12: Sử dụng dự phòng | C12: Thống nhất cách ghi câu hỏi thử nghiệm, lý do dùng dự phòng và hồ sơ kết quả. | D12: Chưa xác nhận | E12: [Chưa phân công] | F12: [Chưa chốt] | G12: [Chưa chốt]
A13: 7 | B13: Nhóm mục tiêu LinkedIn | C13: Đối chiếu doanh nghiệp, ngành và vai trò với phạm vi mục tiêu. | D13: Chưa xác nhận | E13: [Chưa phân công] | F13: [Chưa chốt] | G13: [Chưa chốt]
A14: 8 | B14: Từ khóa Google Search | C14: Rà soát nhu cầu tìm kiếm, từ khóa và danh sách loại trừ. | D14: Chưa xác nhận | E14: [Chưa phân công] | F14: [Chưa chốt] | G14: [Chưa chốt]
A15: 9 | B15: Nội dung truyền thông | C15: Đối chiếu thông điệp và các nội dung chuyên môn với nguồn được phép sử dụng. | D15: Chưa xác nhận | E15: [Chưa phân công] | F15: [Chưa chốt] | G15: [Chưa chốt]
A16: 10 | B16: Trang đích và lời kêu gọi hành động | C16: Kiểm tra nội dung, liên kết, hiển thị và tương tác trên các thiết bị phù hợp. | D16: Chưa xác nhận | E16: [Chưa phân công] | F16: [Chưa chốt] | G16: [Chưa chốt]
A17: 11 | B17: Hệ thống đo lường | C17: Xác minh các sự kiện cần theo dõi và khả năng đối chiếu giữa các nguồn. | D17: Chưa xác nhận | E17: [Chưa phân công] | F17: [Chưa chốt] | G17: [Chưa chốt]
A18: 12 | B18: Biểu mẫu và nơi tiếp nhận | C18: Kiểm thử gửi form, nhận bản ghi và quy trình xác minh thông tin liên hệ hợp lệ. | D18: Chưa xác nhận | E18: [Chưa phân công] | F18: [Chưa chốt] | G18: [Chưa chốt]
... A22: 16 | B22: Báo cáo và xử lý sự cố | C22: Thống nhất kỳ báo cáo, đầu mối xử lý, cách tạm dừng hạng mục và xác minh trước khi chạy lại. | D22: Chưa xác nhận | E22: [Chưa phân công] | F22: [Chưa chốt] | G22: [Chưa chốt]
A24: Hạng mục đã xác nhận / không áp dụng | D24: =COUNTIF(D7:D22,"Đã xác nhận")+COUNTIF(D7:D22,"Không áp dụng") | F24: ="Trên tổng "&COUNTA(B7:B22)&" hạng mục"
A26: Hạng mục phát sinh vấn đề được theo dõi và xử lý riêng. Ngân sách liên quan được giữ lại trong quá trình khắc phục; việc chuyển sang hạng mục khác cần được xem xét theo phạm vi đã thống nhất.

Sheet 07_Kenh_ngay
A1: Chỉ số theo kênh và ngày
A2: Đầu vào trống; chỉ điền số liệu thực có nguồn. Không gộp reach giữa nền tảng.
A3: Một dòng cho mỗi ngày + kênh. 03_Chi_tieu là nguồn chi; G phải khớp nguồn. Route/Locale chỉ mô tả, ghi Mixed nếu nhiều biến thể; không lặp chi.
A4: Ngày | B4: Kênh | C4: Route | D4: Locale | E4: Impressions | F4: Clicks | G4: Chi quảng cáo (VNĐ) | H4: Paid sessions | I4: Engaged sessions | J4: Query clicks liên quan | K4: Query clicks đã phân loại | L4: Clicks term hiển thị | M4: Tổng Search clicks | N4: CTR | O4: Engagement rate | P4: Query relevance | Q4: Term coverage | R4: Cost / engaged session | S4: Nguồn và ngày trích | T4: Trạng thái | U4: Reach | V4: CPM | W4: CPC | X4: Raw leads | Y4: Verified leads | Z4: Effective lead rate | AA4: Chi từ nhật ký | AB4: Đối chiếu chi
N5: =IF(OR(NOT(ISNUMBER(E5)),E5<=0,NOT(ISNUMBER(F5))),"",F5/E5) | O5: =IF(OR(NOT(ISNUMBER(H5)),H5<=0,NOT(ISNUMBER(I5))),"",I5/H5) | P5: =IF(OR(NOT(ISNUMBER(K5)),K5<=0,NOT(ISNUMBER(J5))),"",J5/K5) | Q5: =IF(OR(NOT(ISNUMBER(M5)),M5<=0,NOT(ISNUMBER(L5))),"",L5/M5) | R5: =IF(OR(NOT(ISNUMBER(I5)),I5<=0,NOT(ISNUMBER(G5))),"",G5/I5) | V5: =IF(OR(NOT(ISNUMBER(E5)),E5<=0,NOT(ISNUMBER(G5))),"",1000*G5/E5) | W5: =IF(OR(NOT(ISNUMBER(F5)),F5<=0,NOT(ISNUMBER(G5))),"",G5/F5) | Z5: =IF(OR(NOT(ISNUMBER(X5)),X5<=0,NOT(ISNUMBER(Y5))),"",Y5/X5) | AA5: =IF(OR(NOT(ISNUMBER(A5)),B5=""),"",IF(B5="LinkedIn",IF(COUNTIFS('03_Chi_tieu'!$A$7:$A$96,A5,'03_Chi_tieu'!$E$7:$E$96,">=0")=0,"",SUMIF('03_Chi_tieu'!$A$7:$A$96,A5,'03_Chi_tieu'!$E$7:$E$96)),IF(B5="Search",IF(COUNTIFS('03_Chi_tieu'!$A$7:$A$96,A5,'03_Chi_tieu'!$F$7:$F$96,">=0")=0,"",SUMIF('03_Chi_tieu'!$A$7:$A$96,A5,'03_Chi_tieu'!$F$7:$F$96)),IF(B5="Retargeting",IF(COUNTIFS('03_Chi_tieu'!$A$7:$A$96,A5,'03_Chi_tieu'!$G$7:$G$96,">=0")=0,"",SUMIF('03_Chi_tieu'!$A$7:$A$96,A5,'03_Chi_tieu'!$G$7:$G$96)),IF(B5="Other",IF(COUNTIFS('03_Chi_tieu'!$A$7:$A$96,A5,'03_Chi_tieu'!$H$7:$H$96,">=0")=0,"",SUMIF('03_Chi_tieu'!$A$7:$A$96,A5,'03_Chi_tieu'!$H$7:$H$96)),""))))) | AB5: =IF(G5="","",IF(NOT(ISNUMBER(G5)),"Chi không hợp lệ",IF(OR(NOT(ISNUMBER(A5)),B5=""),"Thiếu ngày/kênh",IF(COUNTIFS($A$5:$A$104,A5,$B$5:$B$104,B5)>1,"Trùng ngày/kênh",IF(AA5="","Thiếu nguồn hoặc kênh",IF(G5=AA5,"Khớp","Lệch"))))))
N6: =IF(OR(NOT(ISNUMBER(E6)),E6<=0,NOT(ISNUMBER(F6))),"",F6/E6) | O6: =IF(OR(NOT(ISNUMBER(H6)),H6<=0,NOT(ISNUMBER(I6))),"",I6/H6) | P6: =IF(OR(NOT(ISNUMBER(K6)),K6<=0,NOT(ISNUMBER(J6))),"",J6/K6) | Q6: =IF(OR(NOT(ISNUMBER(M6)),M6<=0,NOT(ISNUMBER(L6))),"",L6/M6) | R6: =IF(OR(NOT(ISNUMBER(I6)),I6<=0,NOT(ISNUMBER(G6))),"",G6/I6) | V6: =IF(OR(NOT(ISNUMBER(E6)),E6<=0,NOT(ISNUMBER(G6))),"",1000*G6/E6) | W6: =IF(OR(NOT(ISNUMBER(F6)),F6<=0,NOT(ISNUMBER(G6))),"",G6/F6) | Z6: =IF(OR(NOT(ISNUMBER(X6)),X6<=0,NOT(ISNUMBER(Y6))),"",Y6/X6) | AA6: =IF(OR(NOT(ISNUMBER(A6)),B6=""),"",IF(B6="LinkedIn",IF(COUNTIFS('03_Chi_tieu'!$A$7:$A$96,A6,'03_Chi_tieu'!$E$7:$E$96,">=0")=0,"",SUMIF('03_Chi_tieu'!$A$7:$A$96,A6,'03_Chi_tieu'!$E$7:$E$96)),IF(B6="Search",IF(COUNTIFS('03_Chi_tieu'!$A$7:$A$96,A6,'03_Chi_tieu'!$F$7:$F$96,">=0")=0,"",SUMIF('03_Chi_tieu'!$A$7:$A$96,A6,'03_Chi_tieu'!$F$7:$F$96)),IF(B6="Retargeting",IF(COUNTIFS('03_Chi_tieu'!$A$7:$A$96,A6,'03_Chi_tieu'!$G$7:$G$96,">=0")=0,"",SUMIF('03_Chi_tieu'!$A$7:$A$96,A6,'03_Chi_tieu'!$G$7:$G$96)),IF(B6="Other",IF(COUNTIFS('03_Chi_tieu'!$A$7:$A$96,A6,'03_Chi_tieu'!$H$7:$H$96,">=0")=0,"",SUMIF('03_Chi_tieu'!$A$7:$A$96,A6,'03_Chi_tieu'!$H$7:$H$96)),""))))) | AB6: =IF(G6="","",IF(NOT(ISNUMBER(G6)),"Chi không hợp lệ",IF(OR(NOT(ISNUMBER(A6)),B6=""),"Thiếu ngày/kênh",IF(COUNTIFS($A$5:$A$104,A6,$B$5:$B$104,B6)>1,"Trùng ngày/kênh",IF(AA6="","Thiếu nguồn hoặc kênh",IF(G6=AA6,"Khớp","Lệch"))))))
N7: =IF(OR(NOT(ISNUMBER(E7)),E7<=0,NOT(ISNUMBER(F7))),"",F7/E7) | O7: =IF(OR(NOT(ISNUMBER(H7)),H7<=0,NOT(ISNUMBER(I7))),"",I7/H7) | P7: =IF(OR(NOT(ISNUMBER(K7)),K7<=0,NOT(ISNUMBER(J7))),"",J7/K7) | Q7: =IF(OR(NOT(ISNUMBER(M7)),M7<=0,NOT(ISNUMBER(L7))),"",L7/M7) | R7: =IF(OR(NOT(ISNUMBER(I7)),I7<=0,NOT(ISNUMBER(G7))),"",G7/I7) | V7: =IF(OR(NOT(ISNUMBER(E7)),E7<=0,NOT(ISNUMBER(G7))),"",1000*G7/E7) | W7: =IF(OR(NOT(ISNUMBER(F7)),F7<=0,NOT(ISNUMBER(G7))),"",G7/F7) | Z7: =IF(OR(NOT(ISNUMBER(X7)),X7<=0,NOT(ISNUMBER(Y7))),"",Y7/X7) | AA7: =IF(OR(NOT(ISNUMBER(A7)),B7=""),"",IF(B7="LinkedIn",IF(COUNTIFS('03_Chi_tieu'!$A$7:$A$96,A7,'03_Chi_tieu'!$E$7:$E$96,">=0")=0,"",SUMIF('03_Chi_tieu'!$A$7:$A$96,A7,'03_Chi_tieu'!$E$7:$E$96)),IF(B7="Search",IF(COUNTIFS('03_Chi_tieu'!$A$7:$A$96,A7,'03_Chi_tieu'!$F$7:$F$96,">=0")=0,"",SUMIF('03_Chi_tieu'!$A$7:$A$96,A7,'03_Chi_tieu'!$F$7:$F$96)),IF(B7="Retargeting",IF(COUNTIFS('03_Chi_tieu'!$A$7:$A$96,A7,'03_Chi_tieu'!$G$7:$G$96,">=0")=0,"",SUMIF('03_Chi_tieu'!$A$7:$A$96,A7,'03_Chi_tieu'!$G$7:$G$96)),IF(B7="Other",IF(COUNTIFS('03_Chi_tieu'!$A$7:$A$96,A7,'03_Chi_tieu'!$H$7:$H$96,">=0")=0,"",SUMIF('03_Chi_tieu'!$A$7:$A$96,A7,'03_Chi_tieu'!$H$7:$H$96)),""))))) | AB7: =IF(G7="","",IF(NOT(ISNUMBER(G7)),"Chi không hợp lệ",IF(OR(NOT(ISNUMBER(A7)),B7=""),"Thiếu ngày/kênh",IF(COUNTIFS($A$5:$A$104,A7,$B$5:$B$104,B7)>1,"Trùng ngày/kênh",IF(AA7="","Thiếu nguồn hoặc kênh",IF(G7=AA7,"Khớp","Lệch"))))))
N8: =IF(OR(NOT(ISNUMBER(E8)),E8<=0,NOT(ISNUMBER(F8))),"",F8/E8) | O8: =IF(OR(NOT(ISNUMBER(H8)),H8<=0,NOT(ISNUMBER(I8))),"",I8/H8) | P8: =IF(OR(NOT(ISNUMBER(K8)),K8<=0,NOT(ISNUMBER(J8))),"",J8/K8) | Q8: =IF(OR(NOT(ISNUMBER(M8)),M8<=0,NOT(ISNUMBER(L8))),"",L8/M8) | R8: =IF(OR(NOT(ISNUMBER(I8)),I8<=0,NOT(ISNUMBER(G8))),"",G8/I8) | V8: =IF(OR(NOT(ISNUMBER(E8)),E8<=0,NOT(ISNUMBER(G8))),"",1000*G8/E8) | W8: =IF(OR(NOT(ISNUMBER(F8)),F8<=0,NOT(ISNUMBER(G8))),"",G8/F8) | Z8: =IF(OR(NOT(ISNUMBER(X8)),X8<=0,NOT(ISNUMBER(Y8))),"",Y8/X8) | AA8: =IF(OR(NOT(ISNUMBER(A8)),B8=""),"",IF(B8="LinkedIn",IF(COUNTIFS('03_Chi_tieu'!$A$7:$A$96,A8,'03_Chi_tieu'!$E$7:$E$96,">=0")=0,"",SUMIF('03_Chi_tieu'!$A$7:$A$96,A8,'03_Chi_tieu'!$E$7:$E$96)),IF(B8="Search",IF(COUNTIFS('03_Chi_tieu'!$A$7:$A$96,A8,'03_Chi_tieu'!$F$7:$F$96,">=0")=0,"",SUMIF('03_Chi_tieu'!$A$7:$A$96,A8,'03_Chi_tieu'!$F$7:$F$96)),IF(B8="Retargeting",IF(COUNTIFS('03_Chi_tieu'!$A$7:$A$96,A8,'03_Chi_tieu'!$G$7:$G$96,">=0")=0,"",SUMIF('03_Chi_tieu'!$A$7:$A$96,A8,'03_Chi_tieu'!$G$7:$G$96)),IF(B8="Other",IF(COUNTIFS('03_Chi_tieu'!$A$7:$A$96,A8,'03_Chi_tieu'!$H$7:$H$96,">=0")=0,"",SUMIF('03_Chi_tieu'!$A$7:$A$96,A8,'03_Chi_tieu'!$H$7:$H$96)),""))))) | AB8: =IF(G8="","",IF(NOT(ISNUMBER(G8)),"Chi không hợp lệ",IF(OR(NOT(ISNUMBER(A8)),B8=""),"Thiếu ngày/kênh",IF(COUNTIFS($A$5:$A$104,A8,$B$5:$B$104,B8)>1,"Trùng ngày/kênh",IF(AA8="","Thiếu nguồn hoặc kênh",IF(G8=AA8,"Khớp","Lệch"))))))
N9: =IF(OR(NOT(ISNUMBER(E9)),E9<=0,NOT(ISNUMBER(F9))),"",F9/E9) | O9: =IF(OR(NOT(ISNUMBER(H9)),H9<=0,NOT(ISNUMBER(I9))),"",I9/H9) | P9: =IF(OR(NOT(ISNUMBER(K9)),K9<=0,NOT(ISNUMBER(J9))),"",J9/K9) | Q9: =IF(OR(NOT(ISNUMBER(M9)),M9<=0,NOT(ISNUMBER(L9))),"",L9/M9) | R9: =IF(OR(NOT(ISNUMBER(I9)),I9<=0,NOT(ISNUMBER(G9))),"",G9/I9) | V9: =IF(OR(NOT(ISNUMBER(E9)),E9<=0,NOT(ISNUMBER(G9))),"",1000*G9/E9) | W9: =IF(OR(NOT(ISNUMBER(F9)),F9<=0,NOT(ISNUMBER(G9))),"",G9/F9) | Z9: =IF(OR(NOT(ISNUMBER(X9)),X9<=0,NOT(ISNUMBER(Y9))),"",Y9/X9) | AA9: =IF(OR(NOT(ISNUMBER(A9)),B9=""),"",IF(B9="LinkedIn",IF(COUNTIFS('03_Chi_tieu'!$A$7:$A$96,A9,'03_Chi_tieu'!$E$7:$E$96,">=0")=0,"",SUMIF('03_Chi_tieu'!$A$7:$A$96,A9,'03_Chi_tieu'!$E$7:$E$96)),IF(B9="Search",IF(COUNTIFS('03_Chi_tieu'!$A$7:$A$96,A9,'03_Chi_tieu'!$F$7:$F$96,">=0")=0,"",SUMIF('03_Chi_tieu'!$A$7:$A$96,A9,'03_Chi_tieu'!$F$7:$F$96)),IF(B9="Retargeting",IF(COUNTIFS('03_Chi_tieu'!$A$7:$A$96,A9,'03_Chi_tieu'!$G$7:$G$96,">=0")=0,"",SUMIF('03_Chi_tieu'!$A$7:$A$96,A9,'03_Chi_tieu'!$G$7:$G$96)),IF(B9="Other",IF(COUNTIFS('03_Chi_tieu'!$A$7:$A$96,A9,'03_Chi_tieu'!$H$7:$H$96,">=0")=0,"",SUMIF('03_Chi_tieu'!$A$7:$A$96,A9,'03_Chi_tieu'!$H$7:$H$96)),""))))) | AB9: =IF(G9="","",IF(NOT(ISNUMBER(G9)),"Chi không hợp lệ",IF(OR(NOT(ISNUMBER(A9)),B9=""),"Thiếu ngày/kênh",IF(COUNTIFS($A$5:$A$104,A9,$B$5:$B$104,B9)>1,"Trùng ngày/kênh",IF(AA9="","Thiếu nguồn hoặc kênh",IF(G9=AA9,"Khớp","Lệch"))))))
N10: =IF(OR(NOT(ISNUMBER(E10)),E10<=0,NOT(ISNUMBER(F10))),"",F10/E10) | O10: =IF(OR(NOT(ISNUMBER(H10)),H10<=0,NOT(ISNUMBER(I10))),"",I10/H10) | P10: =IF(OR(NOT(ISNUMBER(K10)),K10<=0,NOT(ISNUMBER(J10))),"",J10/K10) | Q10: =IF(OR(NOT(ISNUMBER(M10)),M10<=0,NOT(ISNUMBER(L10))),"",L10/M10) | R10: =IF(OR(NOT(ISNUMBER(I10)),I10<=0,NOT(ISNUMBER(G10))),"",G10/I10) | V10: =IF(OR(NOT(ISNUMBER(E10)),E10<=0,NOT(ISNUMBER(G10))),"",1000*G10/E10) | W10: =IF(OR(NOT(ISNUMBER(F10)),F10<=0,NOT(ISNUMBER(G10))),"",G10/F10) | Z10: =IF(OR(NOT(ISNUMBER(X10)),X10<=0,NOT(ISNUMBER(Y10))),"",Y10/X10) | AA10: =IF(OR(NOT(ISNUMBER(A10)),B10=""),"",IF(B10="LinkedIn",IF(COUNTIFS('03_Chi_tieu'!$A$7:$A$96,A10,'03_Chi_tieu'!$E$7:$E$96,">=0")=0,"",SUMIF('03_Chi_tieu'!$A$7:$A$96,A10,'03_Chi_tieu'!$E$7:$E$96)),IF(B10="Search",IF(COUNTIFS('03_Chi_tieu'!$A$7:$A$96,A10,'03_Chi_tieu'!$F$7:$F$96,">=0")=0,"",SUMIF('03_Chi_tieu'!$A$7:$A$96,A10,'03_Chi_tieu'!$F$7:$F$96)),IF(B10="Retargeting",IF(COUNTIFS('03_Chi_tieu'!$A$7:$A$96,A10,'03_Chi_tieu'!$G$7:$G$96,">=0")=0,"",SUMIF('03_Chi_tieu'!$A$7:$A$96,A10,'03_Chi_tieu'!$G$7:$G$96)),IF(B10="Other",IF(COUNTIFS('03_Chi_tieu'!$A$7:$A$96,A10,'03_Chi_tieu'!$H$7:$H$96,">=0")=0,"",SUMIF('03_Chi_tieu'!$A$7:$A$96,A10,'03_Chi_tieu'!$H$7:$H$96)),""))))) | AB10: =IF(G10="","",IF(NOT(ISNUMBER(G10)),"Chi không hợp lệ",IF(OR(NOT(ISNUMBER(A10)),B10=""),"Thiếu ngày/kênh",IF(COUNTIFS($A$5:$A$104,A10,$B$5:$B$104,B10)>1,"Trùng ngày/kênh",IF(AA10="","Thiếu nguồn hoặc kênh",IF(G10=AA10,"Khớp","Lệch"))))))
N11: =IF(OR(NOT(ISNUMBER(E11)),E11<=0,NOT(ISNUMBER(F11))),"",F11/E11) | O11: =IF(OR(NOT(ISNUMBER(H11)),H11<=0,NOT(ISNUMBER(I11))),"",I11/H11) | P11: =IF(OR(NOT(ISNUMBER(K11)),K11<=0,NOT(ISNUMBER(J11))),"",J11/K11) | Q11: =IF(OR(NOT(ISNUMBER(M11)),M11<=0,NOT(ISNUMBER(L11))),"",L11/M11) | R11: =IF(OR(NOT(ISNUMBER(I11)),I11<=0,NOT(ISNUMBER(G11))),"",G11/I11) | V11: =IF(OR(NOT(ISNUMBER(E11)),E11<=0,NOT(ISNUMBER(G11))),"",1000*G11/E11) | W11: =IF(OR(NOT(ISNUMBER(F11)),F11<=0,NOT(ISNUMBER(G11))),"",G11/F11) | Z11: =IF(OR(NOT(ISNUMBER(X11)),X11<=0,NOT(ISNUMBER(Y11))),"",Y11/X11) | AA11: =IF(OR(NOT(ISNUMBER(A11)),B11=""),"",IF(B11="LinkedIn",IF(COUNTIFS('03_Chi_tieu'!$A$7:$A$96,A11,'03_Chi_tieu'!$E$7:$E$96,">=0")=0,"",SUMIF('03_Chi_tieu'!$A$7:$A$96,A11,'03_Chi_tieu'!$E$7:$E$96)),IF(B11="Search",IF(COUNTIFS('03_Chi_tieu'!$A$7:$A$96,A11,'03_Chi_tieu'!$F$7:$F$96,">=0")=0,"",SUMIF('03_Chi_tieu'!$A$7:$A$96,A11,'03_Chi_tieu'!$F$7:$F$96)),IF(B11="Retargeting",IF(COUNTIFS('03_Chi_tieu'!$A$7:$A$96,A11,'03_Chi_tieu'!$G$7:$G$96,">=0")=0,"",SUMIF('03_Chi_tieu'!$A$7:$A$96,A11,'03_Chi_tieu'!$G$7:$G$96)),IF(B11="Other",IF(COUNTIFS('03_Chi_tieu'!$A$7:$A$96,A11,'03_Chi_tieu'!$H$7:$H$96,">=0")=0,"",SUMIF('03_Chi_tieu'!$A$7:$A$96,A11,'03_Chi_tieu'!$H$7:$H$96)),""))))) | AB11: =IF(G11="","",IF(NOT(ISNUMBER(G11)),"Chi không hợp lệ",IF(OR(NOT(ISNUMBER(A11)),B11=""),"Thiếu ngày/kênh",IF(COUNTIFS($A$5:$A$104,A11,$B$5:$B$104,B11)>1,"Trùng ngày/kênh",IF(AA11="","Thiếu nguồn hoặc kênh",IF(G11=AA11,"Khớp","Lệch"))))))
N12: =IF(OR(NOT(ISNUMBER(E12)),E12<=0,NOT(ISNUMBER(F12))),"",F12/E12) | O12: =IF(OR(NOT(ISNUMBER(H12)),H12<=0,NOT(ISNUMBER(I12))),"",I12/H12) | P12: =IF(OR(NOT(ISNUMBER(K12)),K12<=0,NOT(ISNUMBER(J12))),"",J12/K12) | Q12: =IF(OR(NOT(ISNUMBER(M12)),M12<=0,NOT(ISNUMBER(L12))),"",L12/M12) | R12: =IF(OR(NOT(ISNUMBER(I12)),I12<=0,NOT(ISNUMBER(G12))),"",G12/I12) | V12: =IF(OR(NOT(ISNUMBER(E12)),E12<=0,NOT(ISNUMBER(G12))),"",1000*G12/E12) | W12: =IF(OR(NOT(ISNUMBER(F12)),F12<=0,NOT(ISNUMBER(G12))),"",G12/F12) | Z12: =IF(OR(NOT(ISNUMBER(X12)),X12<=0,NOT(ISNUMBER(Y12))),"",Y12/X12) | AA12: =IF(OR(NOT(ISNUMBER(A12)),B12=""),"",IF(B12="LinkedIn",IF(COUNTIFS('03_Chi_tieu'!$A$7:$A$96,A12,'03_Chi_tieu'!$E$7:$E$96,">=0")=0,"",SUMIF('03_Chi_tieu'!$A$7:$A$96,A12,'03_Chi_tieu'!$E$7:$E$96)),IF(B12="Search",IF(COUNTIFS('03_Chi_tieu'!$A$7:$A$96,A12,'03_Chi_tieu'!$F$7:$F$96,">=0")=0,"",SUMIF('03_Chi_tieu'!$A$7:$A$96,A12,'03_Chi_tieu'!$F$7:$F$96)),IF(B12="Retargeting",IF(COUNTIFS('03_Chi_tieu'!$A$7:$A$96,A12,'03_Chi_tieu'!$G$7:$G$96,">=0")=0,"",SUMIF('03_Chi_tieu'!$A$7:$A$96,A12,'03_Chi_tieu'!$G$7:$G$96)),IF(B12="Other",IF(COUNTIFS('03_Chi_tieu'!$A$7:$A$96,A12,'03_Chi_tieu'!$H$7:$H$96,">=0")=0,"",SUMIF('03_Chi_tieu'!$A$7:$A$96,A12,'03_Chi_tieu'!$H$7:$H$96)),""))))) | AB12: =IF(G12="","",IF(NOT(ISNUMBER(G12)),"Chi không hợp lệ",IF(OR(NOT(ISNUMBER(A12)),B12=""),"Thiếu ngày/kênh",IF(COUNTIFS($A$5:$A$104,A12,$B$5:$B$104,B12)>1,"Trùng ngày/kênh",IF(AA12="","Thiếu nguồn hoặc kênh",IF(G12=AA12,"Khớp","Lệch"))))))
N13: =IF(OR(NOT(ISNUMBER(E13)),E13<=0,NOT(ISNUMBER(F13))),"",F13/E13) | O13: =IF(OR(NOT(ISNUMBER(H13)),H13<=0,NOT(ISNUMBER(I13))),"",I13/H13) | P13: =IF(OR(NOT(ISNUMBER(K13)),K13<=0,NOT(ISNUMBER(J13))),"",J13/K13) | Q13: =IF(OR(NOT(ISNUMBER(M13)),M13<=0,NOT(ISNUMBER(L13))),"",L13/M13) | R13: =IF(OR(NOT(ISNUMBER(I13)),I13<=0,NOT(ISNUMBER(G13))),"",G13/I13) | V13: =IF(OR(NOT(ISNUMBER(E13)),E13<=0,NOT(ISNUMBER(G13))),"",1000*G13/E13) | W13: =IF(OR(NOT(ISNUMBER(F13)),F13<=0,NOT(ISNUMBER(G13))),"",G13/F13) | Z13: =IF(OR(NOT(ISNUMBER(X13)),X13<=0,NOT(ISNUMBER(Y13))),"",Y13/X13) | AA13: =IF(OR(NOT(ISNUMBER(A13)),B13=""),"",IF(B13="LinkedIn",IF(COUNTIFS('03_Chi_tieu'!$A$7:$A$96,A13,'03_Chi_tieu'!$E$7:$E$96,">=0")=0,"",SUMIF('03_Chi_tieu'!$A$7:$A$96,A13,'03_Chi_tieu'!$E$7:$E$96)),IF(B13="Search",IF(COUNTIFS('03_Chi_tieu'!$A$7:$A$96,A13,'03_Chi_tieu'!$F$7:$F$96,">=0")=0,"",SUMIF('03_Chi_tieu'!$A$7:$A$96,A13,'03_Chi_tieu'!$F$7:$F$96)),IF(B13="Retargeting",IF(COUNTIFS('03_Chi_tieu'!$A$7:$A$96,A13,'03_Chi_tieu'!$G$7:$G$96,">=0")=0,"",SUMIF('03_Chi_tieu'!$A$7:$A$96,A13,'03_Chi_tieu'!$G$7:$G$96)),IF(B13="Other",IF(COUNTIFS('03_Chi_tieu'!$A$7:$A$96,A13,'03_Chi_tieu'!$H$7:$H$96,">=0")=0,"",SUMIF('03_Chi_tieu'!$A$7:$A$96,A13,'03_Chi_tieu'!$H$7:$H$96)),""))))) | AB13: =IF(G13="","",IF(NOT(ISNUMBER(G13)),"Chi không hợp lệ",IF(OR(NOT(ISNUMBER(A13)),B13=""),"Thiếu ngày/kênh",IF(COUNTIFS($A$5:$A$104,A13,$B$5:$B$104,B13)>1,"Trùng ngày/kênh",IF(AA13="","Thiếu nguồn hoặc kênh",IF(G13=AA13,"Khớp","Lệch"))))))
N14: =IF(OR(NOT(ISNUMBER(E14)),E14<=0,NOT(ISNUMBER(F14))),"",F14/E14) | O14: =IF(OR(NOT(ISNUMBER(H14)),H14<=0,NOT(ISNUMBER(I14))),"",I14/H14) | P14: =IF(OR(NOT(ISNUMBER(K14)),K14<=0,NOT(ISNUMBER(J14))),"",J14/K14) | Q14: =IF(OR(NOT(ISNUMBER(M14)),M14<=0,NOT(ISNUMBER(L14))),"",L14/M14) | R14: =IF(OR(NOT(ISNUMBER(I14)),I14<=0,NOT(ISNUMBER(G14))),"",G14/I14) | V14: =IF(OR(NOT(ISNUMBER(E14)),E14<=0,NOT(ISNUMBER(G14))),"",1000*G14/E14) | W14: =IF(OR(NOT(ISNUMBER(F14)),F14<=0,NOT(ISNUMBER(G14))),"",G14/F14) | Z14: =IF(OR(NOT(ISNUMBER(X14)),X14<=0,NOT(ISNUMBER(Y14))),"",Y14/X14) | AA14: =IF(OR(NOT(ISNUMBER(A14)),B14=""),"",IF(B14="LinkedIn",IF(COUNTIFS('03_Chi_tieu'!$A$7:$A$96,A14,'03_Chi_tieu'!$E$7:$E$96,">=0")=0,"",SUMIF('03_Chi_tieu'!$A$7:$A$96,A14,'03_Chi_tieu'!$E$7:$E$96)),IF(B14="Search",IF(COUNTIFS('03_Chi_tieu'!$A$7:$A$96,A14,'03_Chi_tieu'!$F$7:$F$96,">=0")=0,"",SUMIF('03_Chi_tieu'!$A$7:$A$96,A14,'03_Chi_tieu'!$F$7:$F$96)),IF(B14="Retargeting",IF(COUNTIFS('03_Chi_tieu'!$A$7:$A$96,A14,'03_Chi_tieu'!$G$7:$G$96,">=0")=0,"",SUMIF('03_Chi_tieu'!$A$7:$A$96,A14,'03_Chi_tieu'!$G$7:$G$96)),IF(B14="Other",IF(COUNTIFS('03_Chi_tieu'!$A$7:$A$96,A14,'03_Chi_tieu'!$H$7:$H$96,">=0")=0,"",SUMIF('03_Chi_tieu'!$A$7:$A$96,A14,'03_Chi_tieu'!$H$7:$H$96)),""))))) | AB14: =IF(G14="","",IF(NOT(ISNUMBER(G14)),"Chi không hợp lệ",IF(OR(NOT(ISNUMBER(A14)),B14=""),"Thiếu ngày/kênh",IF(COUNTIFS($A$5:$A$104,A14,$B$5:$B$104,B14)>1,"Trùng ngày/kênh",IF(AA14="","Thiếu nguồn hoặc kênh",IF(G14=AA14,"Khớp","Lệch"))))))
N15: =IF(OR(NOT(ISNUMBER(E15)),E15<=0,NOT(ISNUMBER(F15))),"",F15/E15) | O15: =IF(OR(NOT(ISNUMBER(H15)),H15<=0,NOT(ISNUMBER(I15))),"",I15/H15) | P15: =IF(OR(NOT(ISNUMBER(K15)),K15<=0,NOT(ISNUMBER(J15))),"",J15/K15) | Q15: =IF(OR(NOT(ISNUMBER(M15)),M15<=0,NOT(ISNUMBER(L15))),"",L15/M15) | R15: =IF(OR(NOT(ISNUMBER(I15)),I15<=0,NOT(ISNUMBER(G15))),"",G15/I15) | V15: =IF(OR(NOT(ISNUMBER(E15)),E15<=0,NOT(ISNUMBER(G15))),"",1000*G15/E15) | W15: =IF(OR(NOT(ISNUMBER(F15)),F15<=0,NOT(ISNUMBER(G15))),"",G15/F15) | Z15: =IF(OR(NOT(ISNUMBER(X15)),X15<=0,NOT(ISNUMBER(Y15))),"",Y15/X15) | AA15: =IF(OR(NOT(ISNUMBER(A15)),B15=""),"",IF(B15="LinkedIn",IF(COUNTIFS('03_Chi_tieu'!$A$7:$A$96,A15,'03_Chi_tieu'!$E$7:$E$96,">=0")=0,"",SUMIF('03_Chi_tieu'!$A$7:$A$96,A15,'03_Chi_tieu'!$E$7:$E$96)),IF(B15="Search",IF(COUNTIFS('03_Chi_tieu'!$A$7:$A$96,A15,'03_Chi_tieu'!$F$7:$F$96,">=0")=0,"",SUMIF('03_Chi_tieu'!$A$7:$A$96,A15,'03_Chi_tieu'!$F$7:$F$96)),IF(B15="Retargeting",IF(COUNTIFS('03_Chi_tieu'!$A$7:$A$96,A15,'03_Chi_tieu'!$G$7:$G$96,">=0")=0,"",SUMIF('03_Chi_tieu'!$A$7:$A$96,A15,'03_Chi_tieu'!$G$7:$G$96)),IF(B15="Other",IF(COUNTIFS('03_Chi_tieu'!$A$7:$A$96,A15,'03_Chi_tieu'!$H$7:$H$96,">=0")=0,"",SUMIF('03_Chi_tieu'!$A$7:$A$96,A15,'03_Chi_tieu'!$H$7:$H$96)),""))))) | AB15: =IF(G15="","",IF(NOT(ISNUMBER(G15)),"Chi không hợp lệ",IF(OR(NOT(ISNUMBER(A15)),B15=""),"Thiếu ngày/kênh",IF(COUNTIFS($A$5:$A$104,A15,$B$5:$B$104,B15)>1,"Trùng ngày/kênh",IF(AA15="","Thiếu nguồn hoặc kênh",IF(G15=AA15,"Khớp","Lệch"))))))
N16: =IF(OR(NOT(ISNUMBER(E16)),E16<=0,NOT(ISNUMBER(F16))),"",F16/E16) | O16: =IF(OR(NOT(ISNUMBER(H16)),H16<=0,NOT(ISNUMBER(I16))),"",I16/H16) | P16: =IF(OR(NOT(ISNUMBER(K16)),K16<=0,NOT(ISNUMBER(J16))),"",J16/K16) | Q16: =IF(OR(NOT(ISNUMBER(M16)),M16<=0,NOT(ISNUMBER(L16))),"",L16/M16) | R16: =IF(OR(NOT(ISNUMBER(I16)),I16<=0,NOT(ISNUMBER(G16))),"",G16/I16) | V16: =IF(OR(NOT(ISNUMBER(E16)),E16<=0,NOT(ISNUMBER(G16))),"",1000*G16/E16) | W16: =IF(OR(NOT(ISNUMBER(F16)),F16<=0,NOT(ISNUMBER(G16))),"",G16/F16) | Z16: =IF(OR(NOT(ISNUMBER(X16)),X16<=0,NOT(ISNUMBER(Y16))),"",Y16/X16) | AA16: =IF(OR(NOT(ISNUMBER(A16)),B16=""),"",IF(B16="LinkedIn",IF(COUNTIFS('03_Chi_tieu'!$A$7:$A$96,A16,'03_Chi_tieu'!$E$7:$E$96,">=0")=0,"",SUMIF('03_Chi_tieu'!$A$7:$A$96,A16,'03_Chi_tieu'!$E$7:$E$96)),IF(B16="Search",IF(COUNTIFS('03_Chi_tieu'!$A$7:$A$96,A16,'03_Chi_tieu'!$F$7:$F$96,">=0")=0,"",SUMIF('03_Chi_tieu'!$A$7:$A$96,A16,'03_Chi_tieu'!$F$7:$F$96)),IF(B16="Retargeting",IF(COUNTIFS('03_Chi_tieu'!$A$7:$A$96,A16,'03_Chi_tieu'!$G$7:$G$96,">=0")=0,"",SUMIF('03_Chi_tieu'!$A$7:$A$96,A16,'03_Chi_tieu'!$G$7:$G$96)),IF(B16="Other",IF(COUNTIFS('03_Chi_tieu'!$A$7:$A$96,A16,'03_Chi_tieu'!$H$7:$H$96,">=0")=0,"",SUMIF('03_Chi_tieu'!$A$7:$A$96,A16,'03_Chi_tieu'!$H$7:$H$96)),""))))) | AB16: =IF(G16="","",IF(NOT(ISNUMBER(G16)),"Chi không hợp lệ",IF(OR(NOT(ISNUMBER(A16)),B16=""),"Thiếu ngày/kênh",IF(COUNTIFS($A$5:$A$104,A16,$B$5:$B$104,B16)>1,"Trùng ngày/kênh",IF(AA16="","Thiếu nguồn hoặc kênh",IF(G16=AA16,"Khớp","Lệch"))))))
... N104: =IF(OR(NOT(ISNUMBER(E104)),E104<=0,NOT(ISNUMBER(F104))),"",F104/E104) | O104: =IF(OR(NOT(ISNUMBER(H104)),H104<=0,NOT(ISNUMBER(I104))),"",I104/H104) | P104: =IF(OR(NOT(ISNUMBER(K104)),K104<=0,NOT(ISNUMBER(J104))),"",J104/K104) | Q104: =IF(OR(NOT(ISNUMBER(M104)),M104<=0,NOT(ISNUMBER(L104))),"",L104/M104) | R104: =IF(OR(NOT(ISNUMBER(I104)),I104<=0,NOT(ISNUMBER(G104))),"",G104/I104) | V104: =IF(OR(NOT(ISNUMBER(E104)),E104<=0,NOT(ISNUMBER(G104))),"",1000*G104/E104) | W104: =IF(OR(NOT(ISNUMBER(F104)),F104<=0,NOT(ISNUMBER(G104))),"",G104/F104) | Z104: =IF(OR(NOT(ISNUMBER(X104)),X104<=0,NOT(ISNUMBER(Y104))),"",Y104/X104) | AA104: =IF(OR(NOT(ISNUMBER(A104)),B104=""),"",IF(B104="LinkedIn",IF(COUNTIFS('03_Chi_tieu'!$A$7:$A$96,A104,'03_Chi_tieu'!$E$7:$E$96,">=0")=0,"",SUMIF('03_Chi_tieu'!$A$7:$A$96,A104,'03_Chi_tieu'!$E$7:$E$96)),IF(B104="Search",IF(COUNTIFS('03_Chi_tieu'!$A$7:$A$96,A104,'03_Chi_tieu'!$F$7:$F$96,">=0")=0,"",SUMIF('03_Chi_tieu'!$A$7:$A$96,A104,'03_Chi_tieu'!$F$7:$F$96)),IF(B104="Retargeting",IF(COUNTIFS('03_Chi_tieu'!$A$7:$A$96,A104,'03_Chi_tieu'!$G$7:$G$96,">=0")=0,"",SUMIF('03_Chi_tieu'!$A$7:$A$96,A104,'03_Chi_tieu'!$G$7:$G$96)),IF(B104="Other",IF(COUNTIFS('03_Chi_tieu'!$A$7:$A$96,A104,'03_Chi_tieu'!$H$7:$H$96,">=0")=0,"",SUMIF('03_Chi_tieu'!$A$7:$A$96,A104,'03_Chi_tieu'!$H$7:$H$96)),""))))) | AB104: =IF(G104="","",IF(NOT(ISNUMBER(G104)),"Chi không hợp lệ",IF(OR(NOT(ISNUMBER(A104)),B104=""),"Thiếu ngày/kênh",IF(COUNTIFS($A$5:$A$104,A104,$B$5:$B$104,B104)>1,"Trùng ngày/kênh",IF(AA104="","Thiếu nguồn hoặc kênh",IF(G104=AA104,"Khớp","Lệch"))))))

Sheet 08_Tu_khoa
A1: Từ khóa và negative
A2: Ứng viên offline; volume trống/không hiển thị không có nghĩa nhu cầu bằng 0.
A4: Loại | B4: Cụm từ | C4: Locale | D4: Intent / loại trừ | E4: Route | F4: Match giả thuyết | G4: Volume hiển thị | H4: Cấu hình và kỳ | I4: Ngày quan sát | J4: Trạng thái nguồn | K4: Nguồn / ghi chú
A5: Keyword (VI) | B5: phần mềm MES đóng gói kiểm thử bán dẫn | C5: VI | D5: Solution | E5: OSAT | F5: Phrase | G5: - (no displayed data) | H5: Vietnam, Sep 2025-Aug 2026 | I5: Chưa query | J5: Candidate; chưa query | K5: S02 S3 draft; ứng viên tiếng Việt
A6: Keyword (VI) | B6: truy xuất lot kiểm thử bán dẫn | C6: VI | D6: Problem/solution | E6: OSAT | F6: Exact | G6: - (no displayed data) | H6: Vietnam, Sep 2025-Aug 2026 | I6: Chưa query | J6: Candidate; chưa query | K6: S02 S3 draft; ứng viên tiếng Việt
A7: Keyword (VI) | B7: quản lý WIP gia công chip ngoài | C7: VI | D7: Problem/solution | E7: Fabless | F7: Phrase | G7: - (no displayed data) | H7: Vietnam, Sep 2025-Aug 2026 | I7: Chưa query | J7: Candidate; chưa query | K7: S02 S3 draft; ứng viên tiếng Việt
A8: Keyword (VI) | B8: theo dõi gia công ngoài bán dẫn | C8: VI | D8: Problem | E8: Fabless | F8: Exact | G8: - (no displayed data) | H8: Vietnam, Sep 2025-Aug 2026 | I8: Chưa query | J8: Candidate; chưa query | K8: S02 S3 draft; ứng viên tiếng Việt
A9: Keyword (VI) | B9: tích hợp ERP MES nhà máy bán dẫn | C9: VI | D9: Solution | E9: Supplier/Partner | F9: Phrase | G9: - (no displayed data) | H9: Vietnam, Sep 2025-Aug 2026 | I9: Chưa query | J9: Candidate; chưa query | K9: S02 S3 draft; ứng viên tiếng Việt
A10: Keyword (VI) | B10: đối tác triển khai MES bán dẫn | C10: VI | D10: Partner/solution | E10: Supplier/Partner | F10: Exact | G10: - (no displayed data) | H10: Vietnam, Sep 2025-Aug 2026 | I10: Chưa query | J10: Candidate; chưa query | K10: S02 S3 draft; ứng viên tiếng Việt
A11: Keyword (VI) | B11: Digiwin Việt Nam bán dẫn | C11: VI | D11: Brand/navigation | E11: Brand candidate | F11: Exact | G11: - (no displayed data) | H11: Vietnam, Sep 2025-Aug 2026 | I11: Chưa query | J11: Candidate; chưa query | K11: S02 S3 draft; brand ứng viên tiếng Việt
A12: Keyword (EN) | B12: OSAT lot traceability software | C12: EN | D12: Solution | E12: OSAT | F12: Phrase | G12: - (no displayed data) | H12: Vietnam, Sep 2025-Aug 2026 | I12: Chưa query | J12: Candidate; chưa query | K12: S02 S3 draft; candidate English
A13: Keyword (EN) | B13: semiconductor test data management | C13: EN | D13: Solution | E13: OSAT | F13: Exact | G13: - (no displayed data) | H13: Vietnam, Sep 2025-Aug 2026 | I13: Chưa query | J13: Candidate; chưa query | K13: S02 S3 draft; candidate English
A14: Keyword (EN) | B14: fabless outsourced WIP tracking | C14: EN | D14: Solution | E14: Fabless | F14: Phrase | G14: - (no displayed data) | H14: Vietnam, Sep 2025-Aug 2026 | I14: Chưa query | J14: Candidate; chưa query | K14: S02 S3 draft; candidate English
A15: Keyword (EN) | B15: semiconductor subcontract production tracking | C15: EN | D15: Solution | E15: Fabless | F15: Exact | G15: - (no displayed data) | H15: Vietnam, Sep 2025-Aug 2026 | I15: Chưa query | J15: Candidate; chưa query | K15: S02 S3 draft; candidate English
... A60: Negative review | B60: arduino | C60: EN | D60: Consumer DIY | E60: Toàn chiến dịch | F60: Negative phrase | G60: - (negative) | H60: Toàn quốc | I60: 2026-09-14 | J60: Chưa áp dụng | K60: Loại trừ bo mạch vi điều khiển DIY học sinh/sinh viên

Sheet 09_Audience_schema
A1: Account và audience metadata
A2: Chỉ schema. Không nhập danh sách Lark, contact, lead, PII hoặc audience export.
A4: Mã bản ghi nội bộ | B4: Entity pháp lý | C4: FDI / nội địa / unknown | D4: Route chính | E4: Hoạt động bán dẫn có nguồn | F4: Nguồn công khai | G4: Ngày nguồn | H4: Trạng thái verified/candidate/unknown | I4: Role hypothesis | J4: Quyền dùng proof | K4: Reviewer / ghi chú

Sheet 10_KPI_dictionary
A1: Định nghĩa KPI
A2: Đề xuất từ S04; baseline và ngưỡng quyết định chờ dữ liệu giao thật.
A4: KPI | B4: Tử số / giá trị | C4: Mẫu số | D4: Nguồn | E4: Phạm vi và kỳ | F4: Baseline | G4: Quy tắc khi thiếu dữ liệu | H4: Trạng thái / dùng để quyết định
A5: CTR | B5: Clicks | C5: Impressions | D5: Native platform | E5: Cùng campaign và kỳ | F5: Unknown | G5: Impressions = 0: không tính | H5: Chẩn đoán; không phải brand lift
A6: Paid engagement rate | B6: Engaged paid sessions | C6: Paid sessions | D6: Verified GA4 | E6: Cùng route, locale, source, kỳ | F6: Unknown | G6: Sessions = 0: không tính | H6: Proxy attention
A7: Visible query relevance | B7: Clicks visible terms liên quan | C7: Clicks visible terms đã phân loại | D7: Google search terms | E7: Cùng tập query và rubric | F7: Unknown | G7: Thiếu clicks: insufficient evidence | H7: Đề xuất tối thiểu 20 clicks đã phân loại
A8: Visible term coverage | B8: Clicks terms hiển thị | C8: Tổng Search clicks | D8: Google Ads | E8: Cùng campaign và kỳ | F8: Unknown | G8: Không có total clicks: không tính | H8: Báo kèm query relevance
A9: Cost per engaged session | B9: Chi quảng cáo cùng paid slice | C9: Engaged paid sessions cùng slice | D9: Platform + GA4 đối soát | E9: Cùng route/source/locale/kỳ | F9: Unknown | G9: Engaged sessions = 0: không tính | H9: So khi attribution tương thích
A10: LinkedIn frequency | B10: Impressions | C10: Native unique reach | D10: Campaign Manager | E10: Cùng campaign và kỳ | F10: Unknown | G10: Reach = 0/ẩn: không tính | H10: Không cộng reach xuyên nền tảng
A11: Budget remaining | B11: Trần kỳ đã duyệt trừ thực chi | C11: Không có | D11: Phê duyệt + platform bill | E11: Ngày hợp lệ; thuế/phí cần chốt | F11: Unknown | G11: Chưa duyệt trần: không tính | H11: Draft 1m/ngày không là quyền chi
A12: Reach | B12: Native unique reach | C12: Không có | D12: Native platform | E12: Cùng campaign và kỳ | F12: Unknown | G12: Ẩn/thiếu: unknown | H12: Không cộng unique reach xuyên nền tảng
A13: CPM | B13: Chi quảng cáo × 1000 | C13: Impressions | D13: Platform report | E13: Cùng kênh/campaign/ngày | F13: Unknown | G13: Impressions = 0: không tính | H13: Chi cần khớp nhật ký nguồn
A14: CPC | B14: Chi quảng cáo | C14: Clicks | D14: Platform report | E14: Cùng kênh/campaign/ngày | F14: Unknown | G14: Clicks = 0: không tính | H14: Chi cần khớp nhật ký nguồn
A15: Raw leads | B15: Số bản ghi raw chưa loại test/trùng | C15: Không có | D15: Receiver được xác minh | E15: Cùng source/route/kỳ | F15: Unknown | G15: Nguồn chưa xác minh: unknown | H15: Tách khỏi accepted/verified leads
... A18: Daily spend reconciliation | B18: Chi phân tích G khớp nhật ký 03_Chi_tieu | C18: Không có | D18: 03_Chi_tieu + platform | E18: Cùng ngày và kênh | F18: Unknown | G18: Nguồn/kênh thiếu: không báo cáo | H18: Chỉ báo cáo metric chi khi AB = Khớp
A21: QUYẾT ĐỊNH KHUNG THỜI GIAN VÀ TRẦN ĐỊNH HƯỚNG
A22: Phạm vi | B22: Qua hết hai chu kỳ Scale1 / cấp 1
A23: Cửa sổ lịch | B23: 8 tuần lịch = 56 ngày lịch
A24: Ngày paid tối đa | B24: Tối đa 35 ngày paid/hợp lệ trong cửa sổ 56 ngày; không mặc định liên tiếp
A25: Mốc chi lịch sử | B25: 1.000.000 VNĐ / ngày paid; theo 01_Thiet_lap!D7
A26: Trần định hướng | B26: 35.000.000 VNĐ qua Scale1 = tối đa 35 ngày paid × mốc 1m/ngày
A27: Phê duyệt chi | B27: Trần định hướng không phải lệnh chi hoặc xác nhận ngân sách đã duyệt; gate giai đoạn vẫn áp dụng
A28: Chưa chốt | B28: Lịch ngày paid, ngày bắt đầu/kết thúc, thuế và phí; không suy diễn lịch chạy từ 35 ngày
A29: Đối soát | B29: 02_Lo_trinh G1 + G2 + G3.1 + G3.2 = 7 + 14 + 7 + 7 ngày tham chiếu; 03_Chi_tieu ghi thực chi theo ngày thực
